Workbook

Sheet Sumario
A1: Equipo | B1: Manager | C1: Saldo Inicial | D1: Gasto | E1: Ingresos | F1: Premios | G1: Saldo Actual | H1: Jugadores | I1: Valor Plantilla
A2: AdolfitoFlick | B2: Jose | C2: 100000000 | D2: =IFERROR(SUMIF(Fichajes!G:G,A2,Fichajes!I:I),0) -> 1363579862 | E2: =IFERROR(SUMIF(Fichajes!H:H,A2,Fichajes!I:I),0) -> 1302581395 | F2: =SUMIF(Premios!A:A,A2,Premios!E:E) -> 64700000 | G2: =C2-D2+E2+F2 -> 103701533 | H2: =COUNTIF(AdolfitoFlick!E:E,"X") -> 0 | I2: 244476931 | J2: =I2+G2 -> 348178464
A3: CrisGC14 | B3: Cristian | C3: 100000000 | D3: =IFERROR(SUMIF(Fichajes!G:G,A3,Fichajes!I:I),0) -> 637182397 | E3: =IFERROR(SUMIF(Fichajes!H:H,A3,Fichajes!I:I),0) -> 566505557 | F3: =SUMIF(Premios!A:A,A3,Premios!E:E) -> 55300000 | G3: =C3-D3+E3+F3 -> 84623160 | H3: =COUNTIF(CrisGC14!E:E,"X") -> 5 | I3: 208024347 | J3: =I3+G3 -> 292647507
A4: davidcdl10 | B4: Diez | C4: 100000000 | D4: =IFERROR(SUMIF(Fichajes!G:G,A4,Fichajes!I:I),0) -> 1313284059 | E4: =IFERROR(SUMIF(Fichajes!H:H,A4,Fichajes!I:I),0) -> 1274294160 | F4: =SUMIF(Premios!A:A,A4,Premios!E:E) -> 64700000 | G4: =C4-D4+E4+F4 -> 125710101 | H4: =COUNTIF(davidcdl10!E:E,"X") -> 7 | I4: 264054935 | J4: =I4+G4 -> 389765036
A5: Desteban19 | B5: David | C5: 100000000 | D5: =IFERROR(SUMIF(Fichajes!G:G,A5,Fichajes!I:I),0) -> 1971859169 | E5: =IFERROR(SUMIF(Fichajes!H:H,A5,Fichajes!I:I),0) -> 1931381128 | F5: =SUMIF(Premios!A:A,A5,Premios!E:E) -> 66700000 | G5: =C5-D5+E5+F5 -> 126221959 | H5: =COUNTIF(Desteban19!E:E,"X") -> 20 | I5: 353435221 | J5: =I5+G5 -> 479657180
A6: FC Capitan | B6: Dani Capitan | C6: 100000000 | D6: =IFERROR(SUMIF(Fichajes!G:G,A6,Fichajes!I:I),0) -> 1526797672 | E6: =IFERROR(SUMIF(Fichajes!H:H,A6,Fichajes!I:I),0) -> 1616953841 | F6: =SUMIF(Premios!A:A,A6,Premios!E:E) -> 64400000 | G6: =C6-D6+E6+F6 -> 254556169 | H6: =COUNTIF('FC Capitan'!E:E,"X") -> 1 | I6: 187973098 | J6: =I6+G6 -> 442529267
A7: FC Recreativo de Juerga | B7: Cano | C7: 100000000 | D7: =IFERROR(SUMIF(Fichajes!G:G,A7,Fichajes!I:I),0) -> 1246569425 | E7: =IFERROR(SUMIF(Fichajes!H:H,A7,Fichajes!I:I),0) -> 1297664581 | F7: =SUMIF(Premios!A:A,A7,Premios!E:E) -> 67400000 | G7: =C7-D7+E7+F7 -> 218495156 | H7: =COUNTIF('FC Recreativo de Juerga'!E:E,"X") -> 24 | I7: 235537339 | J7: =I7+G7 -> 454032495
A8: JMGuti14 | B8: Jona | C8: 100000000 | D8: =IFERROR(SUMIF(Fichajes!G:G,A8,Fichajes!I:I),0) -> 778796018 | E8: =IFERROR(SUMIF(Fichajes!H:H,A8,Fichajes!I:I),0) -> 720394620 | F8: =SUMIF(Premios!A:A,A8,Premios!E:E) -> 62000000 | G8: =C8-D8+E8+F8 -> 103598602 | H8: =COUNTIF(JMGuti14!E:E,"X") -> 9 | I8: 242665307 | J8: =I8+G8 -> 346263909
A9: Reivaj95 | B9: Javi | C9: 100000000 | D9: =IFERROR(SUMIF(Fichajes!G:G,A9,Fichajes!I:I),0) -> 2301792361 | E9: =IFERROR(SUMIF(Fichajes!H:H,A9,Fichajes!I:I),0) -> 2348240333 | F9: =SUMIF(Premios!A:A,A9,Premios!E:E) -> 82100000 | G9: =C9-D9+E9+F9 -> 228547972 | H9: =COUNTIF(Reivaj95!E:E,"X") -> 0 | I9: 353155756 | J9: =I9+G9 -> 581703728
A10: Shiquetito 9 | B10: Alvarito | C10: 100000000 | D10: =IFERROR(SUMIF(Fichajes!G:G,A10,Fichajes!I:I),0) -> 602185440 | E10: =IFERROR(SUMIF(Fichajes!H:H,A10,Fichajes!I:I),0) -> 572401121 | F10: =SUMIF(Premios!A:A,A10,Premios!E:E) -> 49100000 | G10: =C10-D10+E10+F10 -> 119315681 | H10: =COUNTIF('Shiquetito 9'!E:E,"X") -> 14 | I10: 224496375 | J10: =I10+G10 -> 343812056
A11: yandrak | B11: Diaz | C11: 100000000 | D11: =IFERROR(SUMIF(Fichajes!G:G,A11,Fichajes!I:I),0) -> 1207671008 | E11: =IFERROR(SUMIF(Fichajes!H:H,A11,Fichajes!I:I),0) -> 1140725189 | F11: =SUMIF(Premios!A:A,A11,Premios!E:E) -> 58400000 | G11: =C11-D11+E11+F11 -> 91454181 | H11: =COUNTIF(yandrak!E:E,"X") -> 3 | I11: 198920627 | J11: =I11+G11 -> 290374808
G14: =G3-G16-G17 -> 81123160
G16: 1500000
G17: 2000000

Sheet Nombres
A1: Jugador | B1: Jugador Fantasy | C1: Equipo | D1: Posicion | E1: FAN
A2: Christensen | B2: A. Christensen | C2: Barcelona | D2: DEF | E2: =OR(ISBLANK(B2),ISBLANK(A2)) -> FALSE
A3: Carreras | B3: A. F. Carreras | C3: Real Madrid | D3: DEF | E3: =OR(ISBLANK(B3),ISBLANK(A3)) -> FALSE
A4: Alvaro Nuñez | B4: Á. Núñez | C4: Elche | D4: DEF | E4: =OR(ISBLANK(B4),ISBLANK(A4)) -> FALSE
A5: Aarón | B5: Aarón | C5: Real Oviedo | D5: POR | E5: =OR(ISBLANK(B5),ISBLANK(A5)) -> FALSE
A6: Ez Abde | B6: Abde | C6: Betis | D6: DEL | E6: =OR(ISBLANK(B6),ISBLANK(A6)) -> FALSE
B7: Abdon | C7: Mallorca | D7: DEL | E7: =OR(ISBLANK(B7),ISBLANK(A7)) -> TRUE
B8: Abel Ruiz | C8: Girona | D8: DEL | E8: =OR(ISBLANK(B8),ISBLANK(A8)) -> TRUE
A9: Abqar | B9: Abqar | C9: Getafe | D9: DEF | E9: =OR(ISBLANK(B9),ISBLANK(A9)) -> FALSE
B10: Adam Boayar | C10: Elche | D10: MED | E10: =OR(ISBLANK(B10),ISBLANK(A10)) -> TRUE
B11: Adams | C11: Sevilla | D11: DEL | E11: =OR(ISBLANK(B11),ISBLANK(A11)) -> TRUE
A12: Adrian | B12: Adrián | C12: Betis | D12: POR | E12: =OR(ISBLANK(B12),ISBLANK(A12)) -> FALSE
B13: Adrián Molina | C13: Rayo | D13: POR | E13: =OR(ISBLANK(B13),ISBLANK(A13)) -> TRUE
A14: Affengruber | B14: Affengruber | C14: Elche | D14: DEF | E14: =OR(ISBLANK(B14),ISBLANK(A14)) -> FALSE
A15: Agirrezabala | B15: Agirrezabala | C15: Valencia | D15: POR | E15: =OR(ISBLANK(B15),ISBLANK(A15)) -> FALSE
A16: Agoume | B16: Agoume | C16: Sevilla | D16: MED | E16: =OR(ISBLANK(B16),ISBLANK(A16)) -> FALSE
A17: Aguado | B17: Aguado | C17: Elche | D17: MED | E17: =OR(ISBLANK(B17),ISBLANK(A17)) -> FALSE
B18: Ahijado | C18: Real Oviedo | D18: DEF | E18: =OR(ISBLANK(B18),ISBLANK(A18)) -> TRUE
B19: Aihen | C19: Real Sociedad | D19: DEF | E19: =OR(ISBLANK(B19),ISBLANK(A19)) -> TRUE
B20: Aimar Blázquez | C20: Valencia | D20: DEL | E20: =OR(ISBLANK(B20),ISBLANK(A20)) -> TRUE
A21: Aitor Fdez | B21: Aitor | C21: Osasuna | D21: POR | E21: =OR(ISBLANK(B21),ISBLANK(A21)) -> FALSE
B22: Aitor Fraga | C22: Real Sociedad | D22: POR | E22: =OR(ISBLANK(B22),ISBLANK(A22)) -> TRUE
A23: Akhomach | B23: Akhomach | C23: Villarreal | D23: DEL | E23: =OR(ISBLANK(B23),ISBLANK(A23)) -> FALSE
B24: Alaba | C24: Real Madrid | D24: DEF | E24: =OR(ISBLANK(B24),ISBLANK(A24)) -> TRUE
B25: Albert Niculaesei | C25: Elche | D25: DEF | E25: =OR(ISBLANK(B25),ISBLANK(A25)) -> TRUE
A26: Alberto F | B26: Alberto | C26: Sevilla | D26: POR | E26: =OR(ISBLANK(B26),ISBLANK(A26)) -> FALSE
B27: Alberto Risco | C27: Getafe | D27: MED | E27: =OR(ISBLANK(B27),ISBLANK(A27)) -> TRUE
A28: Alderete | B28: Alderete | C28: Getafe | D28: DEF | E28: =OR(ISBLANK(B28),ISBLANK(A28)) -> FALSE
A29: Rego | B29: Alejandro Rego | C29: Athletic | D29: DEF | E29: =OR(ISBLANK(B29),ISBLANK(A29)) -> FALSE
B30: Aleksandar Andreev | C30: Girona | D30: POR | E30: =OR(ISBLANK(B30),ISBLANK(A30)) -> TRUE
A31: Alemao | B31: Alemão | C31: Rayo | D31: DEL | E31: =OR(ISBLANK(B31),ISBLANK(A31)) -> FALSE
A32: Aleña | B32: Aleñá | C32: Alavés | D32: MED | E32: =OR(ISBLANK(B32),ISBLANK(A32)) -> FALSE
B33: Álex Costa | C33: Sevilla | D33: DEL | E33: =OR(ISBLANK(B33),ISBLANK(A33)) -> TRUE
B34: Álex Moreno | C34: Girona | D34: DEF | E34: =OR(ISBLANK(B34),ISBLANK(A34)) -> TRUE
A35: Trent | B35: Alexander-Arnold | C35: Real Madrid | D35: DEF | E35: =OR(ISBLANK(B35),ISBLANK(A35)) -> FALSE
A36: Alexis Sanchez | B36: Alexis | C36: Sevilla | D36: DEL | E36: =OR(ISBLANK(B36),ISBLANK(A36)) -> FALSE
A37: Alfon | B37: Alfon | C37: Sevilla | D37: DEL | E37: =OR(ISBLANK(B37),ISBLANK(A37)) -> FALSE
A38: Rahim | B38: Alhassane | C38: Real Oviedo | D38: DEF | E38: =OR(ISBLANK(B38),ISBLANK(A38)) -> FALSE
B39: Ali Houary | C39: Elche | D39: DEL | E39: =OR(ISBLANK(B39),ISBLANK(A39)) -> TRUE
A40: Almada | B40: Almada | C40: Atlético | D40: MED | E40: =OR(ISBLANK(B40),ISBLANK(A40)) -> FALSE
A41: Almeida | B41: Almeida | C41: Valencia | D41: MED | E41: =OR(ISBLANK(B41),ISBLANK(A41)) -> FALSE
A42: Almeida | B42: Almeida | C42: Valencia | D42: MED | E42: =OR(ISBLANK(B42),ISBLANK(A42)) -> FALSE
A43: Altamira | B43: Altimira | C43: Betis | D43: MED | E43: =OR(ISBLANK(B43),ISBLANK(A43)) -> FALSE
A44: Altamira | B44: Altimira | C44: Villarreal | D44: DEF | E44: =OR(ISBLANK(B44),ISBLANK(A44)) -> FALSE
A45: Alvarez | B45: Alvarez | C45: Atlético | D45: DEL | E45: =OR(ISBLANK(B45),ISBLANK(A45)) -> FALSE
B46: Álvaro | C46: Sevilla | D46: POR | E46: =OR(ISBLANK(B46),ISBLANK(A46)) -> TRUE
A47: Alvaro Garcia | B47: Álvaro García | C47: Rayo | D47: MED | E47: =OR(ISBLANK(B47),ISBLANK(A47)) -> FALSE
A48: Alvaro | B48: Alvaro R. | C48: Elche | D48: DEL | E48: =OR(ISBLANK(B48),ISBLANK(A48)) -> FALSE
A49: Andre Silva | B49: André Silva | C49: Elche | D49: DEL | E49: =OR(ISBLANK(B49),ISBLANK(A49)) -> FALSE
A50: Andrei | B50: Andrei | C50: Rayo | D50: DEF | E50: =OR(ISBLANK(B50),ISBLANK(A50)) -> FALSE
A51: Antonio Sanchez | B51: Antonio | C51: Mallorca | D51: MED | E51: =OR(ISBLANK(B51),ISBLANK(A51)) -> FALSE
B52: Antonio Martínez Bastida | C52: Elche | D52: MED | E52: =OR(ISBLANK(B52),ISBLANK(A52)) -> TRUE
A53: Antony | B53: Antony | C53: Betis | D53: DEL | E53: =OR(ISBLANK(B53),ISBLANK(A53)) -> FALSE
A54: Arambarri | B54: Arambarri | C54: Getafe | D54: MED | E54: =OR(ISBLANK(B54),ISBLANK(A54)) -> FALSE
A55: Aramburu | B55: Aramburu | C55: Real Sociedad | D55: DEF | E55: =OR(ISBLANK(B55),ISBLANK(A55)) -> FALSE
A56: Araujo | B56: Araújo | C56: Barcelona | D56: DEF | E56: =OR(ISBLANK(B56),ISBLANK(A56)) -> FALSE
A57: Areso | B57: Areso | C57: Athletic | D57: DEF | E57: =OR(ISBLANK(B57),ISBLANK(A57)) -> FALSE
B58: Aritz | C58: Real Sociedad | D58: DEF | E58: =OR(ISBLANK(B58),ISBLANK(A58)) -> TRUE
B59: Arnau | C59: Girona | D59: DEF | E59: =OR(ISBLANK(B59),ISBLANK(A59)) -> TRUE
A60: Arriaga | B60: Arriaga | C60: Levante | D60: MED | E60: =OR(ISBLANK(B60),ISBLANK(A60)) -> FALSE
A61: Asano | B61: Asano | C61: Mallorca | D61: DEL | E61: =OR(ISBLANK(B61),ISBLANK(A61)) -> FALSE
A62: Asencio | B62: Asencio | C62: Real Madrid | D62: DEF | E62: =OR(ISBLANK(B62),ISBLANK(A62)) -> FALSE
A63: Aspas | B63: Aspas | C63: Celta | D63: DEL | E63: =OR(ISBLANK(B63),ISBLANK(A63)) -> FALSE
A64: Asprilla | B64: Asprilla | C64: Girona | D64: DEL | E64: =OR(ISBLANK(B64),ISBLANK(A64)) -> FALSE
B65: Ayoze | C65: Villarreal | D65: DEL | E65: =OR(ISBLANK(B65),ISBLANK(A65)) -> TRUE
A66: Azpilicueta | B66: Azpilicueta | C66: Sevilla | D66: DEF | E66: =OR(ISBLANK(B66),ISBLANK(A66)) -> FALSE
A67: Bade | B67: Bade | C67: Sevilla | D67: DEF | E67: =OR(ISBLANK(B67),ISBLANK(A67)) -> FALSE
A68: Alex Baena | B68: Baena | C68: Atlético | D68: MED | E68: =OR(ISBLANK(B68),ISBLANK(A68)) -> FALSE
A69: Bailly | B69: Bailly | C69: Real Oviedo | D69: DEF | E69: =OR(ISBLANK(B69),ISBLANK(A69)) -> FALSE
A70: Bakambu | B70: Bakambu | C70: Betis | D70: DEL | E70: =OR(ISBLANK(B70),ISBLANK(A70)) -> FALSE
A71: Alex Balde | B71: Balde | C71: Barcelona | D71: DEF | E71: =OR(ISBLANK(B71),ISBLANK(A71)) -> FALSE
A72: Balliu | B72: Balliu | C72: Rayo | D72: DEF | E72: =OR(ISBLANK(B72),ISBLANK(A72)) -> FALSE
B73: Bambo | C73: Elche | D73: DEF | E73: =OR(ISBLANK(B73),ISBLANK(A73)) -> TRUE
B74: Bardghji | C74: Barcelona | D74: DEL | E74: =OR(ISBLANK(B74),ISBLANK(A74)) -> TRUE
A75: Barrenetxea | B75: Barrenetxea | C75: Real Sociedad | D75: MED | E75: =OR(ISBLANK(B75),ISBLANK(A75)) -> FALSE
A76: Barrios | B76: Barrios | C76: Atlético | D76: MED | E76: =OR(ISBLANK(B76),ISBLANK(A76)) -> FALSE
A77: Bartra | B77: Bartra | C77: Betis | D77: DEF | E77: =OR(ISBLANK(B77),ISBLANK(A77)) -> FALSE
A78: Batalla | B78: Batalla | C78: Rayo | D78: POR | E78: =OR(ISBLANK(B78),ISBLANK(A78)) -> FALSE
A79: Becker | B79: Becker | C79: Osasuna | D79: MED | E79: =OR(ISBLANK(B79),ISBLANK(A79)) -> FALSE
B80: Bekhoucha | C80: Getafe | D80: DEF | E80: =OR(ISBLANK(B80),ISBLANK(A80)) -> TRUE
A81: Bellerin | B81: Bellerín | C81: Betis | D81: DEF | E81: =OR(ISBLANK(B81),ISBLANK(A81)) -> FALSE
A82: Bellingham | B82: Bellingham | C82: Real Madrid | D82: MED | E82: =OR(ISBLANK(B82),ISBLANK(A82)) -> FALSE
A83: Fran Beltran | B83: Beltrán | C83: Celta | D83: MED | E83: =OR(ISBLANK(B83),ISBLANK(A83)) -> FALSE
A84: Fran Beltran | B84: Beltrán | C84: Valencia | D84: MED | E84: =OR(ISBLANK(B84),ISBLANK(A84)) -> FALSE
B85: Benavidez | C85: Alavés | D85: MED | E85: =OR(ISBLANK(B85),ISBLANK(A85)) -> TRUE
A86: Benito | B86: Benito | C86: Osasuna | D86: DEL | E86: =OR(ISBLANK(B86),ISBLANK(A86)) -> FALSE
A87: Berenguer | B87: Berenguer | C87: Athletic | D87: DEL | E87: =OR(ISBLANK(B87),ISBLANK(A87)) -> FALSE
B88: Bergstrom | C88: Mallorca | D88: POR | E88: =OR(ISBLANK(B88),ISBLANK(A88)) -> TRUE
A89: Marc Bernal | B89: Bernal | C89: Barcelona | D89: MED | E89: =OR(ISBLANK(B89),ISBLANK(A89)) -> FALSE
A90: Bigas | B90: Bigas | C90: Elche | D90: DEF | E90: =OR(ISBLANK(B90),ISBLANK(A90)) -> FALSE
A91: Blanco | B91: Blanco | C91: Alavés | D91: MED | E91: =OR(ISBLANK(B91),ISBLANK(A91)) -> FALSE
A92: Daley Blind | B92: Blind | C92: Girona | D92: DEF | E92: =OR(ISBLANK(B92),ISBLANK(A92)) -> FALSE
B93: Boiro | C93: Athletic | D93: DEF | E93: =OR(ISBLANK(B93),ISBLANK(A93)) -> TRUE
A94: Lucas Boye | B94: Boyé | C94: Alavés | D94: DEL | E94: =OR(ISBLANK(B94),ISBLANK(A94)) -> FALSE
A95: Boyomo | B95: Boyomo | C95: Osasuna | D95: DEF | E95: =OR(ISBLANK(B95),ISBLANK(A95)) -> FALSE
A96: Brahim | B96: Brahim | C96: Real Madrid | D96: MED | E96: =OR(ISBLANK(B96),ISBLANK(A96)) -> FALSE
A97: Brais Mendez | B97: Brais | C97: Real Sociedad | D97: MED | E97: =OR(ISBLANK(B97),ISBLANK(A97)) -> FALSE
B98: Brandon | C98: Real Oviedo | D98: MED | E98: =OR(ISBLANK(B98),ISBLANK(A98)) -> TRUE
B99: Brekalo | C99: Real Oviedo | D99: MED | E99: =OR(ISBLANK(B99),ISBLANK(A99)) -> TRUE
A100: Abel Bretones | B100: Bretones | C100: Osasuna | D100: DEF | E100: =OR(ISBLANK(B100),ISBLANK(A100)) -> FALSE
...

Sheet Fichajes
A1: ID | B1: Jugador Fantasy | C1: Posicion | D1: Equipo Real | E1: Jugador | F1: Fecha | G1: Comprador | H1: Vendedor | I1: Precio
A2: 1 | B2: =IF(ISERROR(VLOOKUP(E2,Nombres!A:D,2,FALSE)),"PROBLEMAAAAAA",VLOOKUP(E2,Nombres!A:D,2,FALSE)) -> Oroz | C2: =IF(ISERROR(VLOOKUP(E2,Nombres!A:D,4,FALSE)),"PROBLEMAAAAAA",VLOOKUP(E2,Nombres!A:D,4,FALSE)) -> MED | D2: =IF(ISERROR(VLOOKUP(E2,Nombres!A:D,3,FALSE)),"PROBLEMAAAAAA",VLOOKUP(E2,Nombres!A:D,3,FALSE)) -> Osasuna | E2: Aimar | F2: 45872 | G2: AdolfitoFlick | H2: Liga | I2: 0
A3: 2 | B3: =IF(ISERROR(VLOOKUP(E3,Nombres!A:D,2,FALSE)),"PROBLEMAAAAAA",VLOOKUP(E3,Nombres!A:D,2,FALSE)) -> Alderete | C3: =IF(ISERROR(VLOOKUP(E3,Nombres!A:D,4,FALSE)),"PROBLEMAAAAAA",VLOOKUP(E3,Nombres!A:D,4,FALSE)) -> DEF | D3: =IF(ISERROR(VLOOKUP(E3,Nombres!A:D,3,FALSE)),"PROBLEMAAAAAA",VLOOKUP(E3,Nombres!A:D,3,FALSE)) -> Getafe | E3: Alderete | F3: 45872 | G3: FC Recreativo de Juerga | H3: Liga | I3: 0
A4: 3 | B4: =IF(ISERROR(VLOOKUP(E4,Nombres!A:D,2,FALSE)),"PROBLEMAAAAAA",VLOOKUP(E4,Nombres!A:D,2,FALSE)) -> Almeida | C4: =IF(ISERROR(VLOOKUP(E4,Nombres!A:D,4,FALSE)),"PROBLEMAAAAAA",VLOOKUP(E4,Nombres!A:D,4,FALSE)) -> MED | D4: =IF(ISERROR(VLOOKUP(E4,Nombres!A:D,3,FALSE)),"PROBLEMAAAAAA",VLOOKUP(E4,Nombres!A:D,3,FALSE)) -> Valencia | E4: Almeida | F4: 45872 | G4: davidcdl10 | H4: Liga | I4: 0
A5: 4 | B5: =IF(ISERROR(VLOOKUP(E5,Nombres!A:D,2,FALSE)),"PROBLEMAAAAAA",VLOOKUP(E5,Nombres!A:D,2,FALSE)) -> Álvaro García | C5: =IF(ISERROR(VLOOKUP(E5,Nombres!A:D,4,FALSE)),"PROBLEMAAAAAA",VLOOKUP(E5,Nombres!A:D,4,FALSE)) -> MED | D5: =IF(ISERROR(VLOOKUP(E5,Nombres!A:D,3,FALSE)),"PROBLEMAAAAAA",VLOOKUP(E5,Nombres!A:D,3,FALSE)) -> Rayo | E5: Alvaro Garcia | F5: 45872 | G5: CrisGC14 | H5: Liga | I5: 0
A6: 5 | B6: =IF(ISERROR(VLOOKUP(E6,Nombres!A:D,2,FALSE)),"PROBLEMAAAAAA",VLOOKUP(E6,Nombres!A:D,2,FALSE)) -> Á. Núñez | C6: =IF(ISERROR(VLOOKUP(E6,Nombres!A:D,4,FALSE)),"PROBLEMAAAAAA",VLOOKUP(E6,Nombres!A:D,4,FALSE)) -> DEF | D6: =IF(ISERROR(VLOOKUP(E6,Nombres!A:D,3,FALSE)),"PROBLEMAAAAAA",VLOOKUP(E6,Nombres!A:D,3,FALSE)) -> Elche | E6: Alvaro Nuñez | F6: 45872 | G6: AdolfitoFlick | H6: Liga | I6: 0
A7: 6 | B7: =IF(ISERROR(VLOOKUP(E7,Nombres!A:D,2,FALSE)),"PROBLEMAAAAAA",VLOOKUP(E7,Nombres!A:D,2,FALSE)) -> Andrei | C7: =IF(ISERROR(VLOOKUP(E7,Nombres!A:D,4,FALSE)),"PROBLEMAAAAAA",VLOOKUP(E7,Nombres!A:D,4,FALSE)) -> DEF | D7: =IF(ISERROR(VLOOKUP(E7,Nombres!A:D,3,FALSE)),"PROBLEMAAAAAA",VLOOKUP(E7,Nombres!A:D,3,FALSE)) -> Rayo | E7: Andrei | F7: 45872 | G7: yandrak | H7: Liga | I7: 0
A8: 7 | B8: =IF(ISERROR(VLOOKUP(E8,Nombres!A:D,2,FALSE)),"PROBLEMAAAAAA",VLOOKUP(E8,Nombres!A:D,2,FALSE)) -> Arambarri | C8: =IF(ISERROR(VLOOKUP(E8,Nombres!A:D,4,FALSE)),"PROBLEMAAAAAA",VLOOKUP(E8,Nombres!A:D,4,FALSE)) -> MED | D8: =IF(ISERROR(VLOOKUP(E8,Nombres!A:D,3,FALSE)),"PROBLEMAAAAAA",VLOOKUP(E8,Nombres!A:D,3,FALSE)) -> Getafe | E8: Arambarri | F8: 45872 | G8: JMGuti14 | H8: Liga | I8: 0
A9: 8 | B9: =IF(ISERROR(VLOOKUP(E9,Nombres!A:D,2,FALSE)),"PROBLEMAAAAAA",VLOOKUP(E9,Nombres!A:D,2,FALSE)) -> Araújo | C9: =IF(ISERROR(VLOOKUP(E9,Nombres!A:D,4,FALSE)),"PROBLEMAAAAAA",VLOOKUP(E9,Nombres!A:D,4,FALSE)) -> DEF | D9: =IF(ISERROR(VLOOKUP(E9,Nombres!A:D,3,FALSE)),"PROBLEMAAAAAA",VLOOKUP(E9,Nombres!A:D,3,FALSE)) -> Barcelona | E9: Araujo | F9: 45872 | G9: FC Capitan | H9: Liga | I9: 0
A10: 9 | B10: =IF(ISERROR(VLOOKUP(E10,Nombres!A:D,2,FALSE)),"PROBLEMAAAAAA",VLOOKUP(E10,Nombres!A:D,2,FALSE)) -> Asano | C10: =IF(ISERROR(VLOOKUP(E10,Nombres!A:D,4,FALSE)),"PROBLEMAAAAAA",VLOOKUP(E10,Nombres!A:D,4,FALSE)) -> DEL | D10: =IF(ISERROR(VLOOKUP(E10,Nombres!A:D,3,FALSE)),"PROBLEMAAAAAA",VLOOKUP(E10,Nombres!A:D,3,FALSE)) -> Mallorca | E10: Asano | F10: 45872 | G10: FC Recreativo de Juerga | H10: Liga | I10: 0
A11: 10 | B11: =IF(ISERROR(VLOOKUP(E11,Nombres!A:D,2,FALSE)),"PROBLEMAAAAAA",VLOOKUP(E11,Nombres!A:D,2,FALSE)) -> Asencio | C11: =IF(ISERROR(VLOOKUP(E11,Nombres!A:D,4,FALSE)),"PROBLEMAAAAAA",VLOOKUP(E11,Nombres!A:D,4,FALSE)) -> DEF | D11: =IF(ISERROR(VLOOKUP(E11,Nombres!A:D,3,FALSE)),"PROBLEMAAAAAA",VLOOKUP(E11,Nombres!A:D,3,FALSE)) -> Real Madrid | E11: Asencio | F11: 45872 | G11: CrisGC14 | H11: Liga | I11: 0
A12: 11 | B12: =IF(ISERROR(VLOOKUP(E12,Nombres!A:D,2,FALSE)),"PROBLEMAAAAAA",VLOOKUP(E12,Nombres!A:D,2,FALSE)) -> Asprilla | C12: =IF(ISERROR(VLOOKUP(E12,Nombres!A:D,4,FALSE)),"PROBLEMAAAAAA",VLOOKUP(E12,Nombres!A:D,4,FALSE)) -> DEL | D12: =IF(ISERROR(VLOOKUP(E12,Nombres!A:D,3,FALSE)),"PROBLEMAAAAAA",VLOOKUP(E12,Nombres!A:D,3,FALSE)) -> Girona | E12: Asprilla | F12: 45872 | G12: FC Capitan | H12: Liga | I12: 0
A13: 12 | B13: =IF(ISERROR(VLOOKUP(E13,Nombres!A:D,2,FALSE)),"PROBLEMAAAAAA",VLOOKUP(E13,Nombres!A:D,2,FALSE)) -> Bade | C13: =IF(ISERROR(VLOOKUP(E13,Nombres!A:D,4,FALSE)),"PROBLEMAAAAAA",VLOOKUP(E13,Nombres!A:D,4,FALSE)) -> DEF | D13: =IF(ISERROR(VLOOKUP(E13,Nombres!A:D,3,FALSE)),"PROBLEMAAAAAA",VLOOKUP(E13,Nombres!A:D,3,FALSE)) -> Sevilla | E13: Bade | F13: 45872 | G13: davidcdl10 | H13: Liga | I13: 0
... A816: 815 | B816: =IF(ISERROR(VLOOKUP(E816,Nombres!A:D,2,FALSE)),"PROBLEMAAAAAA",VLOOKUP(E816,Nombres!A:D,2,FALSE)) -> Mastantuono | C816: =IF(ISERROR(VLOOKUP(E816,Nombres!A:D,4,FALSE)),"PROBLEMAAAAAA",VLOOKUP(E816,Nombres!A:D,4,FALSE)) -> DEL | D816: =IF(ISERROR(VLOOKUP(E816,Nombres!A:D,3,FALSE)),"PROBLEMAAAAAA",VLOOKUP(E816,Nombres!A:D,3,FALSE)) -> Real Madrid | E816: Mastantuono | F816: 45942 | G816: Shiquetito 9 | H816: Liga | I816: 53968850
A817: 816 | B817: =IF(ISERROR(VLOOKUP(E817,Nombres!A:D,2,FALSE)),"PROBLEMAAAAAA",VLOOKUP(E817,Nombres!A:D,2,FALSE)) -> Yuri | C817: =IF(ISERROR(VLOOKUP(E817,Nombres!A:D,4,FALSE)),"PROBLEMAAAAAA",VLOOKUP(E817,Nombres!A:D,4,FALSE)) -> DEF | D817: =IF(ISERROR(VLOOKUP(E817,Nombres!A:D,3,FALSE)),"PROBLEMAAAAAA",VLOOKUP(E817,Nombres!A:D,3,FALSE)) -> Athletic | E817: Yuri | F817: 45942 | G817: FC Recreativo de Juerga
A818: 817 | B818: =IF(ISERROR(VLOOKUP(E818,Nombres!A:D,2,FALSE)),"PROBLEMAAAAAA",VLOOKUP(E818,Nombres!A:D,2,FALSE)) -> Denis Suárez | C818: =IF(ISERROR(VLOOKUP(E818,Nombres!A:D,4,FALSE)),"PROBLEMAAAAAA",VLOOKUP(E818,Nombres!A:D,4,FALSE)) -> MED | D818: =IF(ISERROR(VLOOKUP(E818,Nombres!A:D,3,FALSE)),"PROBLEMAAAAAA",VLOOKUP(E818,Nombres!A:D,3,FALSE)) -> Alavés | E818: Denis Suarez | F818: 45942 | G818: Liga | H818: AdolfitoFlick | I818: 705614
A819: 818 | B819: =IF(ISERROR(VLOOKUP(E819,Nombres!A:D,2,FALSE)),"PROBLEMAAAAAA",VLOOKUP(E819,Nombres!A:D,2,FALSE)) -> Danjuma | C819: =IF(ISERROR(VLOOKUP(E819,Nombres!A:D,4,FALSE)),"PROBLEMAAAAAA",VLOOKUP(E819,Nombres!A:D,4,FALSE)) -> DEL | D819: =IF(ISERROR(VLOOKUP(E819,Nombres!A:D,3,FALSE)),"PROBLEMAAAAAA",VLOOKUP(E819,Nombres!A:D,3,FALSE)) -> Valencia | E819: Danjuma | F819: 45943 | G819: AdolfitoFlick | H819: davidcdl10 | I819: 23115355
A820: 819 | B820: =IF(ISERROR(VLOOKUP(E820,Nombres!A:D,2,FALSE)),"PROBLEMAAAAAA",VLOOKUP(E820,Nombres!A:D,2,FALSE)) -> André Silva | C820: =IF(ISERROR(VLOOKUP(E820,Nombres!A:D,4,FALSE)),"PROBLEMAAAAAA",VLOOKUP(E820,Nombres!A:D,4,FALSE)) -> DEL | D820: =IF(ISERROR(VLOOKUP(E820,Nombres!A:D,3,FALSE)),"PROBLEMAAAAAA",VLOOKUP(E820,Nombres!A:D,3,FALSE)) -> Elche | E820: Andre Silva | F820: 45943 | G820: AdolfitoFlick | H820: Reivaj95 | I820: 10100101
A821: 820 | B821: =IF(ISERROR(VLOOKUP(E821,Nombres!A:D,2,FALSE)),"PROBLEMAAAAAA",VLOOKUP(E821,Nombres!A:D,2,FALSE)) -> Rafa Marín | C821: =IF(ISERROR(VLOOKUP(E821,Nombres!A:D,4,FALSE)),"PROBLEMAAAAAA",VLOOKUP(E821,Nombres!A:D,4,FALSE)) -> DEF | D821: =IF(ISERROR(VLOOKUP(E821,Nombres!A:D,3,FALSE)),"PROBLEMAAAAAA",VLOOKUP(E821,Nombres!A:D,3,FALSE)) -> Villarreal | E821: Rafa Marin | F821: 45943 | G821: FC Capitan | H821: Liga | I821: 39261200
A822: 821 | B822: =IF(ISERROR(VLOOKUP(E822,Nombres!A:D,2,FALSE)),"PROBLEMAAAAAA",VLOOKUP(E822,Nombres!A:D,2,FALSE)) -> Vivian | C822: =IF(ISERROR(VLOOKUP(E822,Nombres!A:D,4,FALSE)),"PROBLEMAAAAAA",VLOOKUP(E822,Nombres!A:D,4,FALSE)) -> DEF | D822: =IF(ISERROR(VLOOKUP(E822,Nombres!A:D,3,FALSE)),"PROBLEMAAAAAA",VLOOKUP(E822,Nombres!A:D,3,FALSE)) -> Athletic | E822: Vivian | F822: 45943 | G822: FC Capitan | H822: Liga | I822: 34200833
A823: 822 | B823: =IF(ISERROR(VLOOKUP(E823,Nombres!A:D,2,FALSE)),"PROBLEMAAAAAA",VLOOKUP(E823,Nombres!A:D,2,FALSE)) -> Sow | C823: =IF(ISERROR(VLOOKUP(E823,Nombres!A:D,4,FALSE)),"PROBLEMAAAAAA",VLOOKUP(E823,Nombres!A:D,4,FALSE)) -> MED | D823: =IF(ISERROR(VLOOKUP(E823,Nombres!A:D,3,FALSE)),"PROBLEMAAAAAA",VLOOKUP(E823,Nombres!A:D,3,FALSE)) -> Sevilla | E823: Sow | F823: 45944 | G823: Shiquetito 9 | H823: davidcdl10 | I823: 2213460
A824: 823 | B824: =IF(ISERROR(VLOOKUP(E824,Nombres!A:D,2,FALSE)),"PROBLEMAAAAAA",VLOOKUP(E824,Nombres!A:D,2,FALSE)) -> Hugo Álvarez | C824: =IF(ISERROR(VLOOKUP(E824,Nombres!A:D,4,FALSE)),"PROBLEMAAAAAA",VLOOKUP(E824,Nombres!A:D,4,FALSE)) -> MED | D824: =IF(ISERROR(VLOOKUP(E824,Nombres!A:D,3,FALSE)),"PROBLEMAAAAAA",VLOOKUP(E824,Nombres!A:D,3,FALSE)) -> Celta | E824: Hugo Alvarez | F824: 45944 | G824: Shiquetito 9 | H824: davidcdl10 | I824: 6700000
A825: 824 | B825: =IF(ISERROR(VLOOKUP(E825,Nombres!A:D,2,FALSE)),"PROBLEMAAAAAA",VLOOKUP(E825,Nombres!A:D,2,FALSE)) -> Edu Expósito | C825: =IF(ISERROR(VLOOKUP(E825,Nombres!A:D,4,FALSE)),"PROBLEMAAAAAA",VLOOKUP(E825,Nombres!A:D,4,FALSE)) -> MED | D825: =IF(ISERROR(VLOOKUP(E825,Nombres!A:D,3,FALSE)),"PROBLEMAAAAAA",VLOOKUP(E825,Nombres!A:D,3,FALSE)) -> Espanyol | E825: Edu Exposito | F825: 45944 | G825: Shiquetito 9 | H825: Desteban19 | I825: 22875987
A826: 825 | B826: =IF(ISERROR(VLOOKUP(E826,Nombres!A:D,2,FALSE)),"PROBLEMAAAAAA",VLOOKUP(E826,Nombres!A:D,2,FALSE)) -> Román | C826: =IF(ISERROR(VLOOKUP(E826,Nombres!A:D,4,FALSE)),"PROBLEMAAAAAA",VLOOKUP(E826,Nombres!A:D,4,FALSE)) -> MED | D826: =IF(ISERROR(VLOOKUP(E826,Nombres!A:D,3,FALSE)),"PROBLEMAAAAAA",VLOOKUP(E826,Nombres!A:D,3,FALSE)) -> Celta | E826: Roman | F826: 45944 | G826: Liga | H826: JMGuti14 | I826: 420382
A827: 826 | B827: =IF(ISERROR(VLOOKUP(E827,Nombres!A:D,2,FALSE)),"PROBLEMAAAAAA",VLOOKUP(E827,Nombres!A:D,2,FALSE)) -> Mikautadze | C827: =IF(ISERROR(VLOOKUP(E827,Nombres!A:D,4,FALSE)),"PROBLEMAAAAAA",VLOOKUP(E827,Nombres!A:D,4,FALSE)) -> DEL | D827: =IF(ISERROR(VLOOKUP(E827,Nombres!A:D,3,FALSE)),"PROBLEMAAAAAA",VLOOKUP(E827,Nombres!A:D,3,FALSE)) -> Villarreal | E827: Mikautadze | F827: 45944 | G827: Shiquetito 9 | H827: FC Capitan | I827: 45100000
A828: 827 | B828: =IF(ISERROR(VLOOKUP(E828,Nombres!A:D,2,FALSE)),"PROBLEMAAAAAA",VLOOKUP(E828,Nombres!A:D,2,FALSE)) -> Morlanes | C828: =IF(ISERROR(VLOOKUP(E828,Nombres!A:D,4,FALSE)),"PROBLEMAAAAAA",VLOOKUP(E828,Nombres!A:D,4,FALSE)) -> MED | D828: =IF(ISERROR(VLOOKUP(E828,Nombres!A:D,3,FALSE)),"PROBLEMAAAAAA",VLOOKUP(E828,Nombres!A:D,3,FALSE)) -> Mallorca | E828: Morlanes | F828: 45944 | G828: davidcdl10 | H828: FC Capitan | I828: 1610010
A829: 828 | B829: =IF(ISERROR(VLOOKUP(E829,Nombres!A:D,2,FALSE)),"PROBLEMAAAAAA",VLOOKUP(E829,Nombres!A:D,2,FALSE)) -> Alexis | C829: =IF(ISERROR(VLOOKUP(E829,Nombres!A:D,4,FALSE)),"PROBLEMAAAAAA",VLOOKUP(E829,Nombres!A:D,4,FALSE)) -> DEL | D829: =IF(ISERROR(VLOOKUP(E829,Nombres!A:D,3,FALSE)),"PROBLEMAAAAAA",VLOOKUP(E829,Nombres!A:D,3,FALSE)) -> Sevilla | E829: Alexis Sanchez | F829: 45944 | G829: davidcdl10 | H829: FC Recreativo de Juerga | I829: 20677441
... A1060: 1059 | B1060: =IF(ISERROR(VLOOKUP(E1060,Nombres!A:D,2,FALSE)),"PROBLEMAAAAAA",VLOOKUP(E1060,Nombres!A:D,2,FALSE)) -> Abde | C1060: =IF(ISERROR(VLOOKUP(E1060,Nombres!A:D,4,FALSE)),"PROBLEMAAAAAA",VLOOKUP(E1060,Nombres!A:D,4,FALSE)) -> DEL | D1060: =IF(ISERROR(VLOOKUP(E1060,Nombres!A:D,3,FALSE)),"PROBLEMAAAAAA",VLOOKUP(E1060,Nombres!A:D,3,FALSE)) -> Betis | E1060: Ez Abde | F1060: 45974 | G1060: AdolfitoFlick | H1060: Reivaj95 | I1060: 43309964

Sheet Premios
A1: Equipo | B1: Jornada | C1: Posicion | D1: Puntos | E1: Premio
A2: davidcdl10 | B2: 1 | C2: =_xlfn.RANK.EQ(D2,D2:D11,0)+COUNTIF(D2:D2,D2)-1 -> 1 | D2: 68 | E2: 6800000
A3: Desteban19 | B3: 1 | C3: =_xlfn.RANK.EQ(D3,D2:D11,0)+COUNTIF(D2:D3,D3)-1 -> 2 | D3: 60 | E3: 6000000
A4: Reivaj95 | B4: 1 | C4: =_xlfn.RANK.EQ(D4,D2:D11,0)+COUNTIF(D2:D4,D4)-1 -> 3 | D4: 59 | E4: 5900000
A5: yandrak | B5: 1 | C5: =_xlfn.RANK.EQ(D5,D2:D11,0)+COUNTIF(D2:D5,D5)-1 -> 4 | D5: 54 | E5: 5400000
A6: AdolfitoFlick | B6: 1 | C6: =_xlfn.RANK.EQ(D6,D2:D11,0)+COUNTIF(D2:D6,D6)-1 -> 5 | D6: 53 | E6: 5300000
A7: Shiquetito 9 | B7: 1 | C7: =_xlfn.RANK.EQ(D7,D2:D11,0)+COUNTIF(D2:D7,D7)-1 -> 6 | D7: 49 | E7: 4900000
A8: JMGuti14 | B8: 1 | C8: =_xlfn.RANK.EQ(D8,D2:D11,0)+COUNTIF(D2:D8,D8)-1 -> 7 | D8: 46 | E8: 4600000
A9: CrisGC14 | B9: 1 | C9: =_xlfn.RANK.EQ(D9,D2:D11,0)+COUNTIF(D2:D9,D9)-1 -> 8 | D9: 36 | E9: 3600000
A10: FC Capitan | B10: 1 | C10: =_xlfn.RANK.EQ(D10,D2:D11,0)+COUNTIF(D2:D10,D10)-1 -> 9 | D10: 34 | E10: 3400000
A11: FC Recreativo de Juerga | B11: 1 | C11: =_xlfn.RANK.EQ(D11,D2:D11,0)+COUNTIF(D2:D11,D11)-1 -> 10 | D11: 22 | E11: 2200000
A12: FC Recreativo de Juerga | B12: 2 | C12: =_xlfn.RANK.EQ(D12,D12:D21,0)+COUNTIF(D12:D12,D12)-1 -> 6 | D12: 50 | E12: =D12*100000 -> 5000000
A13: yandrak | B13: 2 | C13: =_xlfn.RANK.EQ(D13,D12:D21,0)+COUNTIF(D12:D13,D13)-1 -> 7 | D13: 50 | E13: 5000000
A14: Shiquetito 9 | B14: 2 | C14: =_xlfn.RANK.EQ(D14,D12:D21,0)+COUNTIF(D12:D14,D14)-1 -> 9 | D14: 37 | E14: 3700000
A15: davidcdl10 | B15: 2 | C15: =_xlfn.RANK.EQ(D15,D12:D21,0)+COUNTIF(D12:D15,D15)-1 -> 2 | D15: 77 | E15: 7700000
A16: JMGuti14 | B16: 2 | C16: =_xlfn.RANK.EQ(D16,D12:D21,0)+COUNTIF(D12:D16,D16)-1 -> 10 | D16: 37 | E16: 3700000
A17: AdolfitoFlick | B17: 2 | C17: =_xlfn.RANK.EQ(D17,D12:D21,0)+COUNTIF(D12:D17,D17)-1 -> 8 | D17: 40 | E17: 4000000
A18: Desteban19 | B18: 2 | C18: =_xlfn.RANK.EQ(D18,D12:D21,0)+COUNTIF(D12:D18,D18)-1 -> 5 | D18: 52 | E18: 5200000
A19: FC Capitan | B19: 2 | C19: =_xlfn.RANK.EQ(D19,D12:D21,0)+COUNTIF(D12:D19,D19)-1 -> 4 | D19: 53 | E19: 5300000
A20: Reivaj95 | B20: 2 | C20: =_xlfn.RANK.EQ(D20,D12:D21,0)+COUNTIF(D12:D20,D20)-1 -> 1 | D20: 85 | E20: 8500000
A21: CrisGC14 | B21: 2 | C21: =_xlfn.RANK.EQ(D21,D12:D21,0)+COUNTIF(D12:D21,D21)-1 -> 3 | D21: 68 | E21: 6800000
A22: FC Recreativo de Juerga | B22: 3 | C22: =_xlfn.RANK.EQ(D22,D22:D31,0)+COUNTIF(D22:D22,D22)-1 -> 6 | D22: 48 | E22: 4800000
A23: yandrak | B23: 3 | C23: =_xlfn.RANK.EQ(D23,D22:D31,0)+COUNTIF(D22:D23,D23)-1 -> 3 | D23: 58 | E23: 5800000
A24: Shiquetito 9 | B24: 3 | C24: =_xlfn.RANK.EQ(D24,D22:D31,0)+COUNTIF(D22:D24,D24)-1 -> 4 | D24: 58 | E24: 5800000
A25: davidcdl10 | B25: 3 | C25: =_xlfn.RANK.EQ(D25,D22:D31,0)+COUNTIF(D22:D25,D25)-1 -> 10 | D25: 34 | E25: 3400000
A26: JMGuti14 | B26: 3 | C26: =_xlfn.RANK.EQ(D26,D22:D31,0)+COUNTIF(D22:D26,D26)-1 -> 1 | D26: 66 | E26: 6600000
A27: AdolfitoFlick | B27: 3 | C27: =_xlfn.RANK.EQ(D27,D22:D31,0)+COUNTIF(D22:D27,D27)-1 -> 5 | D27: 57 | E27: 5700000
A28: Desteban19 | B28: 3 | C28: =_xlfn.RANK.EQ(D28,D22:D31,0)+COUNTIF(D22:D28,D28)-1 -> 9 | D28: 38 | E28: 3800000
A29: FC Capitan | B29: 3 | C29: =_xlfn.RANK.EQ(D29,D22:D31,0)+COUNTIF(D22:D29,D29)-1 -> 7 | D29: 42 | E29: 4200000
A30: Reivaj95 | B30: 3 | C30: =_xlfn.RANK.EQ(D30,D22:D31,0)+COUNTIF(D22:D30,D30)-1 -> 2 | D30: 61 | E30: 6100000
A31: CrisGC14 | B31: 3 | C31: =_xlfn.RANK.EQ(D31,D22:D31,0)+COUNTIF(D22:D31,D31)-1 -> 8 | D31: 41 | E31: 4100000
A32: FC Recreativo de Juerga | B32: 4 | C32: =_xlfn.RANK.EQ(D32,D32:D41,0)+COUNTIF(D32:D32,D32)-1 -> 2 | D32: 67 | E32: 6700000
A33: yandrak | B33: 4 | C33: =_xlfn.RANK.EQ(D33,D32:D41,0)+COUNTIF(D32:D33,D33)-1 -> 3 | D33: 58 | E33: 5800000
A34: Shiquetito 9 | B34: 4 | C34: =_xlfn.RANK.EQ(D34,D32:D41,0)+COUNTIF(D32:D34,D34)-1 -> 9 | D34: 25 | E34: 2500000
A35: davidcdl10 | B35: 4 | C35: =_xlfn.RANK.EQ(D35,D32:D41,0)+COUNTIF(D32:D35,D35)-1 -> 6 | D35: 49 | E35: 4900000
A36: JMGuti14 | B36: 4 | C36: =_xlfn.RANK.EQ(D36,D32:D41,0)+COUNTIF(D32:D36,D36)-1 -> 5 | D36: 56 | E36: 5600000
A37: AdolfitoFlick | B37: 4 | C37: =_xlfn.RANK.EQ(D37,D32:D41,0)+COUNTIF(D32:D37,D37)-1 -> 8 | D37: 27 | E37: 2700000
A38: Desteban19 | B38: 4 | C38: =_xlfn.RANK.EQ(D38,D32:D41,0)+COUNTIF(D32:D38,D38)-1 -> 4 | D38: 57 | E38: 5700000
A39: FC Capitan | B39: 4 | C39: =_xlfn.RANK.EQ(D39,D32:D41,0)+COUNTIF(D32:D39,D39)-1 -> 7 | D39: 48 | E39: 4800000
A40: Reivaj95 | B40: 4 | C40: =_xlfn.RANK.EQ(D40,D32:D41,0)+COUNTIF(D32:D40,D40)-1 -> 1 | D40: 73 | E40: 7300000
A41: CrisGC14 | B41: 4 | C41: =_xlfn.RANK.EQ(D41,D32:D41,0)+COUNTIF(D32:D41,D41)-1 -> 10 | D41: 24 | E41: 2400000
A42: FC Recreativo de Juerga | B42: 5 | C42: =_xlfn.RANK.EQ(D42,D42:D51,0)+COUNTIF(D42:D42,D42)-1 -> 5 | D42: 59 | E42: 5900000
A43: yandrak | B43: 5 | C43: =_xlfn.RANK.EQ(D43,D42:D51,0)+COUNTIF(D42:D43,D43)-1 -> 6 | D43: 58 | E43: 5800000
A44: Shiquetito 9 | B44: 5 | C44: =_xlfn.RANK.EQ(D44,D42:D51,0)+COUNTIF(D42:D44,D44)-1 -> 10 | D44: 18 | E44: 1800000
A45: davidcdl10 | B45: 5 | C45: =_xlfn.RANK.EQ(D45,D42:D51,0)+COUNTIF(D42:D45,D45)-1 -> 7 | D45: 53 | E45: 5300000
A46: JMGuti14 | B46: 5 | C46: =_xlfn.RANK.EQ(D46,D42:D51,0)+COUNTIF(D42:D46,D46)-1 -> 9 | D46: 38 | E46: 3800000
A47: AdolfitoFlick | B47: 5 | C47: =_xlfn.RANK.EQ(D47,D42:D51,0)+COUNTIF(D42:D47,D47)-1 -> 3 | D47: 72 | E47: 7200000
A48: Desteban19 | B48: 5 | C48: =_xlfn.RANK.EQ(D48,D42:D51,0)+COUNTIF(D42:D48,D48)-1 -> 8 | D48: =SUMIFS(Tabla2[Puntos],Tabla2[Equipo],Premios!A48,Tabla2[Jornada],Premios!B48) -> 50 | E48: 5000000
A49: FC Capitan | B49: 5 | C49: =_xlfn.RANK.EQ(D49,D42:D51,0)+COUNTIF(D42:D49,D49)-1 -> 2 | D49: =SUMIFS(Tabla2[Puntos],Tabla2[Equipo],Premios!A49,Tabla2[Jornada],Premios!B49) -> 75 | E49: 7500000
A50: Reivaj95 | B50: 5 | C50: =_xlfn.RANK.EQ(D50,D42:D51,0)+COUNTIF(D42:D50,D50)-1 -> 1 | D50: =SUMIFS(Tabla2[Puntos],Tabla2[Equipo],Premios!A50,Tabla2[Jornada],Premios!B50) -> 77 | E50: 7700000
A51: CrisGC14 | B51: 5 | C51: =_xlfn.RANK.EQ(D51,D42:D51,0)+COUNTIF(D42:D51,D51)-1 -> 4 | D51: =SUMIFS(Tabla2[Puntos],Tabla2[Equipo],Premios!A51,Tabla2[Jornada],Premios!B51) -> 61 | E51: 6100000
A52: FC Recreativo de Juerga | B52: 6 | C52: =_xlfn.RANK.EQ(D52,D52:D61,0)+COUNTIF(D52:D52,D52)-1 -> 7 | D52: =SUMIFS(Tabla2[Puntos],Tabla2[Equipo],Premios!A52,Tabla2[Jornada],Premios!B52) -> 43 | E52: 4300000
A53: yandrak | B53: 6 | C53: =_xlfn.RANK.EQ(D53,D52:D61,0)+COUNTIF(D52:D53,D53)-1 -> 10 | D53: =SUMIFS(Tabla2[Puntos],Tabla2[Equipo],Premios!A53,Tabla2[Jornada],Premios!B53) -> 0 | E53: 0
A54: Shiquetito 9 | B54: 6 | C54: =_xlfn.RANK.EQ(D54,D52:D61,0)+COUNTIF(D52:D54,D54)-1 -> 9 | D54: =SUMIFS(Tabla2[Puntos],Tabla2[Equipo],Premios!A54,Tabla2[Jornada],Premios!B54) -> 35 | E54: 3500000
A55: davidcdl10 | B55: 6 | C55: =_xlfn.RANK.EQ(D55,D52:D61,0)+COUNTIF(D52:D55,D55)-1 -> 3 | D55: =SUMIFS(Tabla2[Puntos],Tabla2[Equipo],Premios!A55,Tabla2[Jornada],Premios!B55) -> 52 | E55: 5200000
A56: JMGuti14 | B56: 6 | C56: =_xlfn.RANK.EQ(D56,D52:D61,0)+COUNTIF(D52:D56,D56)-1 -> 5 | D56: =SUMIFS(Tabla2[Puntos],Tabla2[Equipo],Premios!A56,Tabla2[Jornada],Premios!B56) -> 49 | E56: 4900000
A57: AdolfitoFlick | B57: 6 | C57: =_xlfn.RANK.EQ(D57,D52:D61,0)+COUNTIF(D52:D57,D57)-1 -> 4 | D57: =SUMIFS(Tabla2[Puntos],Tabla2[Equipo],Premios!A57,Tabla2[Jornada],Premios!B57) -> 51 | E57: 5100000
A58: Desteban19 | B58: 6 | C58: =_xlfn.RANK.EQ(D58,D52:D61,0)+COUNTIF(D52:D58,D58)-1 -> 2 | D58: =SUMIFS(Tabla2[Puntos],Tabla2[Equipo],Premios!A58,Tabla2[Jornada],Premios!B58) -> 53 | E58: 5300000
A59: FC Capitan | B59: 6 | C59: =_xlfn.RANK.EQ(D59,D52:D61,0)+COUNTIF(D52:D59,D59)-1 -> 8 | D59: =SUMIFS(Tabla2[Puntos],Tabla2[Equipo],Premios!A59,Tabla2[Jornada],Premios!B59) -> 37 | E59: 3700000
A60: Reivaj95 | B60: 6 | C60: =_xlfn.RANK.EQ(D60,D52:D61,0)+COUNTIF(D52:D60,D60)-1 -> 1 | D60: =SUMIFS(Tabla2[Puntos],Tabla2[Equipo],Premios!A60,Tabla2[Jornada],Premios!B60) -> 73 | E60: 7300000
A61: CrisGC14 | B61: 6 | C61: =_xlfn.RANK.EQ(D61,D52:D61,0)+COUNTIF(D52:D61,D61)-1 -> 6 | D61: =SUMIFS(Tabla2[Puntos],Tabla2[Equipo],Premios!A61,Tabla2[Jornada],Premios!B61) -> 45 | E61: 4500000
A62: FC Recreativo de Juerga | B62: 7 | C62: =_xlfn.RANK.EQ(D62,D62:D71,0)+COUNTIF(D62:D62,D62)-1 -> 2 | D62: =SUMIFS(Tabla2[Puntos],Tabla2[Equipo],Premios!A62,Tabla2[Jornada],Premios!B62) -> 67 | E62: 6700000
A63: yandrak | B63: 7 | C63: =_xlfn.RANK.EQ(D63,D62:D71,0)+COUNTIF(D62:D63,D63)-1 -> 10 | D63: =SUMIFS(Tabla2[Puntos],Tabla2[Equipo],Premios!A63,Tabla2[Jornada],Premios!B63) -> 34 | E63: 3400000
A64: Shiquetito 9 | B64: 7 | C64: =_xlfn.RANK.EQ(D64,D62:D71,0)+COUNTIF(D62:D64,D64)-1 -> 4 | D64: =SUMIFS(Tabla2[Puntos],Tabla2[Equipo],Premios!A64,Tabla2[Jornada],Premios!B64) -> 62 | E64: 6200000
A65: davidcdl10 | B65: 7 | C65: =_xlfn.RANK.EQ(D65,D62:D71,0)+COUNTIF(D62:D65,D65)-1 -> 5 | D65: =SUMIFS(Tabla2[Puntos],Tabla2[Equipo],Premios!A65,Tabla2[Jornada],Premios!B65) -> 56 | E65: 5600000
A66: JMGuti14 | B66: 7 | C66: =_xlfn.RANK.EQ(D66,D62:D71,0)+COUNTIF(D62:D66,D66)-1 -> 9 | D66: =SUMIFS(Tabla2[Puntos],Tabla2[Equipo],Premios!A66,Tabla2[Jornada],Premios!B66) -> 37 | E66: 3700000
A67: AdolfitoFlick | B67: 7 | C67: =_xlfn.RANK.EQ(D67,D62:D71,0)+COUNTIF(D62:D67,D67)-1 -> 6 | D67: =SUMIFS(Tabla2[Puntos],Tabla2[Equipo],Premios!A67,Tabla2[Jornada],Premios!B67) -> 52 | E67: 5200000
A68: Desteban19 | B68: 7 | C68: =_xlfn.RANK.EQ(D68,D62:D71,0)+COUNTIF(D62:D68,D68)-1 -> 1 | D68: =SUMIFS(Tabla2[Puntos],Tabla2[Equipo],Premios!A68,Tabla2[Jornada],Premios!B68) -> 71 | E68: 7100000
A69: FC Capitan | B69: 7 | C69: =_xlfn.RANK.EQ(D69,D62:D71,0)+COUNTIF(D62:D69,D69)-1 -> 3 | D69: =SUMIFS(Tabla2[Puntos],Tabla2[Equipo],Premios!A69,Tabla2[Jornada],Premios!B69) -> 66 | E69: 6600000
A70: Reivaj95 | B70: 7 | C70: =_xlfn.RANK.EQ(D70,D62:D71,0)+COUNTIF(D62:D70,D70)-1 -> 7 | D70: =SUMIFS(Tabla2[Puntos],Tabla2[Equipo],Premios!A70,Tabla2[Jornada],Premios!B70) -> 46 | E70: 4600000
A71: CrisGC14 | B71: 7 | C71: =_xlfn.RANK.EQ(D71,D62:D71,0)+COUNTIF(D62:D71,D71)-1 -> 8 | D71: =SUMIFS(Tabla2[Puntos],Tabla2[Equipo],Premios!A71,Tabla2[Jornada],Premios!B71) -> 41 | E71: 4100000
A72: FC Recreativo de Juerga | B72: 8 | C72: =_xlfn.RANK.EQ(D72,D72:D81,0)+COUNTIF(D72:D72,D72)-1 -> 2 | D72: =SUMIFS(Tabla2[Puntos],Tabla2[Equipo],Premios!A72,Tabla2[Jornada],Premios!B72) -> 64 | E72: 6400000
A73: yandrak | B73: 8 | C73: =_xlfn.RANK.EQ(D73,D72:D81,0)+COUNTIF(D72:D73,D73)-1 -> 4 | D73: =SUMIFS(Tabla2[Puntos],Tabla2[Equipo],Premios!A73,Tabla2[Jornada],Premios!B73) -> 57 | E73: 5700000
A74: Shiquetito 9 | B74: 8 | C74: =_xlfn.RANK.EQ(D74,D72:D81,0)+COUNTIF(D72:D74,D74)-1 -> 7 | D74: =SUMIFS(Tabla2[Puntos],Tabla2[Equipo],Premios!A74,Tabla2[Jornada],Premios!B74) -> 46 | E74: 4600000
A75: davidcdl10 | B75: 8 | C75: =_xlfn.RANK.EQ(D75,D72:D81,0)+COUNTIF(D72:D75,D75)-1 -> 8 | D75: =SUMIFS(Tabla2[Puntos],Tabla2[Equipo],Premios!A75,Tabla2[Jornada],Premios!B75) -> 45 | E75: 4500000
A76: JMGuti14 | B76: 8 | C76: =_xlfn.RANK.EQ(D76,D72:D81,0)+COUNTIF(D72:D76,D76)-1 -> 5 | D76: =SUMIFS(Tabla2[Puntos],Tabla2[Equipo],Premios!A76,Tabla2[Jornada],Premios!B76) -> 51 | E76: 5100000
A77: AdolfitoFlick | B77: 8 | C77: =_xlfn.RANK.EQ(D77,D72:D81,0)+COUNTIF(D72:D77,D77)-1 -> 1 | D77: =SUMIFS(Tabla2[Puntos],Tabla2[Equipo],Premios!A77,Tabla2[Jornada],Premios!B77) -> 77 | E77: 7700000
A78: Desteban19 | B78: 8 | C78: =_xlfn.RANK.EQ(D78,D72:D81,0)+COUNTIF(D72:D78,D78)-1 -> 6 | D78: =SUMIFS(Tabla2[Puntos],Tabla2[Equipo],Premios!A78,Tabla2[Jornada],Premios!B78) -> 48 | E78: 4800000
A79: FC Capitan | B79: 8 | C79: =_xlfn.RANK.EQ(D79,D72:D81,0)+COUNTIF(D72:D79,D79)-1 -> 10 | D79: =SUMIFS(Tabla2[Puntos],Tabla2[Equipo],Premios!A79,Tabla2[Jornada],Premios!B79) -> 34 | E79: 3400000
A80: Reivaj95 | B80: 8 | C80: =_xlfn.RANK.EQ(D80,D72:D81,0)+COUNTIF(D72:D80,D80)-1 -> 3 | D80: =SUMIFS(Tabla2[Puntos],Tabla2[Equipo],Premios!A80,Tabla2[Jornada],Premios!B80) -> 60 | E80: 6000000
A81: CrisGC14 | B81: 8 | C81: =_xlfn.RANK.EQ(D81,D72:D81,0)+COUNTIF(D72:D81,D81)-1 -> 9 | D81: =SUMIFS(Tabla2[Puntos],Tabla2[Equipo],Premios!A81,Tabla2[Jornada],Premios!B81) -> 36 | E81: 3600000
A82: FC Recreativo de Juerga | B82: 9 | C82: =_xlfn.RANK.EQ(D82,D82:D91,0)+COUNTIF(D82:D82,D82)-1 -> 8 | D82: =SUMIFS(Tabla2[Puntos],Tabla2[Equipo],Premios!A82,Tabla2[Jornada],Premios!B82) -> 53 | E82: =SUMIFS(Tabla2[Premio],Tabla2[Equipo],Premios!A82,Tabla2[Jornada],Premios!B82) -> 5300000
A83: yandrak | B83: 9 | C83: =_xlfn.RANK.EQ(D83,D82:D91,0)+COUNTIF(D82:D83,D83)-1 -> 3 | D83: =SUMIFS(Tabla2[Puntos],Tabla2[Equipo],Premios!A83,Tabla2[Jornada],Premios!B83) -> 74 | E83: =SUMIFS(Tabla2[Premio],Tabla2[Equipo],Premios!A83,Tabla2[Jornada],Premios!B83) -> 7400000
A84: Shiquetito 9 | B84: 9 | C84: =_xlfn.RANK.EQ(D84,D82:D91,0)+COUNTIF(D82:D84,D84)-1 -> 10 | D84: =SUMIFS(Tabla2[Puntos],Tabla2[Equipo],Premios!A84,Tabla2[Jornada],Premios!B84) -> 42 | E84: =SUMIFS(Tabla2[Premio],Tabla2[Equipo],Premios!A84,Tabla2[Jornada],Premios!B84) -> 4200000
A85: davidcdl10 | B85: 9 | C85: =_xlfn.RANK.EQ(D85,D82:D91,0)+COUNTIF(D82:D85,D85)-1 -> 6 | D85: =SUMIFS(Tabla2[Puntos],Tabla2[Equipo],Premios!A85,Tabla2[Jornada],Premios!B85) -> 59 | E85: =SUMIFS(Tabla2[Premio],Tabla2[Equipo],Premios!A85,Tabla2[Jornada],Premios!B85) -> 5900000
A86: JMGuti14 | B86: 9 | C86: =_xlfn.RANK.EQ(D86,D82:D91,0)+COUNTIF(D82:D86,D86)-1 -> 2 | D86: =SUMIFS(Tabla2[Puntos],Tabla2[Equipo],Premios!A86,Tabla2[Jornada],Premios!B86) -> 77 | E86: =SUMIFS(Tabla2[Premio],Tabla2[Equipo],Premios!A86,Tabla2[Jornada],Premios!B86) -> 7700000
A87: AdolfitoFlick | B87: 9 | C87: =_xlfn.RANK.EQ(D87,D82:D91,0)+COUNTIF(D82:D87,D87)-1 -> 4 | D87: =SUMIFS(Tabla2[Puntos],Tabla2[Equipo],Premios!A87,Tabla2[Jornada],Premios!B87) -> 67 | E87: =SUMIFS(Tabla2[Premio],Tabla2[Equipo],Premios!A87,Tabla2[Jornada],Premios!B87) -> 6700000
A88: Desteban19 | B88: 9 | C88: =_xlfn.RANK.EQ(D88,D82:D91,0)+COUNTIF(D82:D88,D88)-1 -> 5 | D88: =SUMIFS(Tabla2[Puntos],Tabla2[Equipo],Premios!A88,Tabla2[Jornada],Premios!B88) -> 62 | E88: =SUMIFS(Tabla2[Premio],Tabla2[Equipo],Premios!A88,Tabla2[Jornada],Premios!B88) -> 6200000
A89: FC Capitan | B89: 9 | C89: =_xlfn.RANK.EQ(D89,D82:D91,0)+COUNTIF(D82:D89,D89)-1 -> 7 | D89: =SUMIFS(Tabla2[Puntos],Tabla2[Equipo],Premios!A89,Tabla2[Jornada],Premios!B89) -> 55 | E89: =SUMIFS(Tabla2[Premio],Tabla2[Equipo],Premios!A89,Tabla2[Jornada],Premios!B89) -> 5500000
A90: Reivaj95 | B90: 9 | C90: =_xlfn.RANK.EQ(D90,D82:D91,0)+COUNTIF(D82:D90,D90)-1 -> 1 | D90: =SUMIFS(Tabla2[Puntos],Tabla2[Equipo],Premios!A90,Tabla2[Jornada],Premios!B90) -> 86 | E90: =SUMIFS(Tabla2[Premio],Tabla2[Equipo],Premios!A90,Tabla2[Jornada],Premios!B90) -> 8600000
A91: CrisGC14 | B91: 9 | C91: =_xlfn.RANK.EQ(D91,D82:D91,0)+COUNTIF(D82:D91,D91)-1 -> 9 | D91: =SUMIFS(Tabla2[Puntos],Tabla2[Equipo],Premios!A91,Tabla2[Jornada],Premios!B91) -> 43 | E91: =SUMIFS(Tabla2[Premio],Tabla2[Equipo],Premios!A91,Tabla2[Jornada],Premios!B91) -> 4300000
A92: FC Recreativo de Juerga | B92: 10 | C92: =_xlfn.RANK.EQ(D92,D92:D101,0)+COUNTIF(D92:D92,D92)-1 -> 4 | D92: =SUMIFS(Tabla2[Puntos],Tabla2[Equipo],Premios!A92,Tabla2[Jornada],Premios!B92) -> 61 | E92: =SUMIFS(Tabla2[Premio],Tabla2[Equipo],Premios!A92,Tabla2[Jornada],Premios!B92) -> 6100000
A93: yandrak | B93: 10 | C93: =_xlfn.RANK.EQ(D93,D92:D101,0)+COUNTIF(D92:D93,D93)-1 -> 3 | D93: =SUMIFS(Tabla2[Puntos],Tabla2[Equipo],Premios!A93,Tabla2[Jornada],Premios!B93) -> 62 | E93: =SUMIFS(Tabla2[Premio],Tabla2[Equipo],Premios!A93,Tabla2[Jornada],Premios!B93) -> 6200000
A94: Shiquetito 9 | B94: 10 | C94: =_xlfn.RANK.EQ(D94,D92:D101,0)+COUNTIF(D92:D94,D94)-1 -> 9 | D94: =SUMIFS(Tabla2[Puntos],Tabla2[Equipo],Premios!A94,Tabla2[Jornada],Premios!B94) -> 38 | E94: =SUMIFS(Tabla2[Premio],Tabla2[Equipo],Premios!A94,Tabla2[Jornada],Premios!B94) -> 3800000
A95: davidcdl10 | B95: 10 | C95: =_xlfn.RANK.EQ(D95,D92:D101,0)+COUNTIF(D92:D95,D95)-1 -> 6 | D95: =SUMIFS(Tabla2[Puntos],Tabla2[Equipo],Premios!A95,Tabla2[Jornada],Premios!B95) -> 58 | E95: =SUMIFS(Tabla2[Premio],Tabla2[Equipo],Premios!A95,Tabla2[Jornada],Premios!B95) -> 5800000
A96: JMGuti14 | B96: 10 | C96: =_xlfn.RANK.EQ(D96,D92:D101,0)+COUNTIF(D92:D96,D96)-1 -> 2 | D96: =SUMIFS(Tabla2[Puntos],Tabla2[Equipo],Premios!A96,Tabla2[Jornada],Premios!B96) -> 64 | E96: =SUMIFS(Tabla2[Premio],Tabla2[Equipo],Premios!A96,Tabla2[Jornada],Premios!B96) -> 6400000
A97: AdolfitoFlick | B97: 10 | C97: =_xlfn.RANK.EQ(D97,D92:D101,0)+COUNTIF(D92:D97,D97)-1 -> 7 | D97: =SUMIFS(Tabla2[Puntos],Tabla2[Equipo],Premios!A97,Tabla2[Jornada],Premios!B97) -> 52 | E97: =SUMIFS(Tabla2[Premio],Tabla2[Equipo],Premios!A97,Tabla2[Jornada],Premios!B97) -> 5200000
A98: Desteban19 | B98: 10 | C98: =_xlfn.RANK.EQ(D98,D92:D101,0)+COUNTIF(D92:D98,D98)-1 -> 1 | D98: =SUMIFS(Tabla2[Puntos],Tabla2[Equipo],Premios!A98,Tabla2[Jornada],Premios!B98) -> 71 | E98: =SUMIFS(Tabla2[Premio],Tabla2[Equipo],Premios!A98,Tabla2[Jornada],Premios!B98) -> 7100000
A99: FC Capitan | B99: 10 | C99: =_xlfn.RANK.EQ(D99,D92:D101,0)+COUNTIF(D92:D99,D99)-1 -> 8 | D99: =SUMIFS(Tabla2[Puntos],Tabla2[Equipo],Premios!A99,Tabla2[Jornada],Premios!B99) -> 50 | E99: =SUMIFS(Tabla2[Premio],Tabla2[Equipo],Premios!A99,Tabla2[Jornada],Premios!B99) -> 5000000
A100: Reivaj95 | B100: 10 | C100: =_xlfn.RANK.EQ(D100,D92:D101,0)+COUNTIF(D92:D100,D100)-1 -> 10 | D100: =SUMIFS(Tabla2[Puntos],Tabla2[Equipo],Premios!A100,Tabla2[Jornada],Premios!B100) -> 36 | E100: =SUMIFS(Tabla2[Premio],Tabla2[Equipo],Premios!A100,Tabla2[Jornada],Premios!B100) -> 3600000
...

Sheet Puntos
A1: Jornada | B1: Fecha | C1: Equipo | D1: Jugador | E1: Posicion | F1: Equipo Real | G1: Puntos | H1: Premio | I1: Posicion2 | J1: Jugador Fantasy
A2: 1 | B2: 45884 | C2: AdolfitoFlick | D2: Sivera | E2: POR | F2: Alavés | G2: 5 | H2: 500000 | I2: 1 | J2: Sivera
A3: 1 | B3: 45884 | C3: AdolfitoFlick | D3: Affengruber | E3: DEF | F3: Elche | G3: 7 | H3: 700000 | I3: 2 | J3: Affengruber
A4: 1 | B4: 45884 | C4: AdolfitoFlick | D4: Alex Balde | E4: DEF | F4: Barcelona | G4: 7 | H4: 700000 | I4: 2 | J4: Balde
A5: 1 | B5: 45884 | C5: AdolfitoFlick | D5: Alvaro Nuñez | E5: DEF | F5: Elche | G5: 6 | H5: 600000 | I5: 2 | J5: Á. Núñez
A6: 1 | B6: 45884 | C6: AdolfitoFlick | D6: Daley Blind | E6: DEF | F6: Girona | G6: 1 | H6: 100000 | I6: 2 | J6: Blind
A7: 1 | B7: 45884 | C7: AdolfitoFlick | D7: Luiz Felipe | E7: DEF | F7: Rayo | G7: 1 | H7: 100000 | I7: 2 | J7: Luiz Felipe
A8: 1 | B8: 45884 | C8: AdolfitoFlick | D8: Aimar | E8: MED | F8: Osasuna | G8: 3 | H8: 300000 | I8: 3 | J8: Oroz
A9: 1 | B9: 45884 | C9: AdolfitoFlick | D9: Darder | E9: MED | F9: Mallorca | G9: 3 | H9: 300000 | I9: 3 | J9: Darder
A10: 1 | B10: 45884 | C10: AdolfitoFlick | D10: Gueye | E10: MED | F10: Villarreal | G10: 15 | H10: 1500000 | I10: 3 | J10: P. Gueye
A11: 1 | B11: 45884 | C11: AdolfitoFlick | D11: Ivan Martin | E11: MED | F11: Girona | G11: 0 | H11: 0 | I11: 3 | J11: Iván Martín
A12: 1 | B12: 45884 | C12: AdolfitoFlick | D12: Gerard | E12: DEL | F12: Villarreal | G12: 6 | H12: 600000 | I12: 4 | J12: Gerard
A13: 1 | B13: 45884 | C13: CrisGC14 | D13: Unai Simon | E13: POR | F13: Athletic | G13: 3 | H13: 300000 | I13: 1 | J13: Unai Simón
... A881: 8 | B881: 45933 | C881: yandrak | D881: Vini Jr | E881: DEL | F881: Real Madrid | G881: 22 | H881: 2200000 | I881: 4 | J881: Vinicius
A882: 9 | B882: 45947 | C882: AdolfitoFlick | D882: Aarón | E882: =IF(ISERROR(VLOOKUP(D882,Nombres!A:D,4,FALSE)),"PROBLEMAAAAAA",VLOOKUP(D882,Nombres!A:D,4,FALSE)) -> POR | F882: =IF(ISERROR(VLOOKUP(D882,Nombres!A:D,3,FALSE)),"PROBLEMAAAAAA",VLOOKUP(D882,Nombres!A:D,3,FALSE)) -> Real Oviedo | G882: 9 | H882: =G882*100000 -> 900000 | I882: =IF(E882="POR",1,IF(E882="DEF",2,IF(E882="MED",3,4))) -> 1 | J882: =IF(ISERROR(VLOOKUP(D882,Nombres!A:D,2,FALSE)),"PROBLEMAAAAAA",VLOOKUP(D882,Nombres!A:D,2,FALSE)) -> Aarón
A883: 9 | B883: 45947 | C883: AdolfitoFlick | D883: Jeremy Toljan | E883: =IF(ISERROR(VLOOKUP(D883,Nombres!A:D,4,FALSE)),"PROBLEMAAAAAA",VLOOKUP(D883,Nombres!A:D,4,FALSE)) -> DEF | F883: =IF(ISERROR(VLOOKUP(D883,Nombres!A:D,3,FALSE)),"PROBLEMAAAAAA",VLOOKUP(D883,Nombres!A:D,3,FALSE)) -> Levante | G883: -2 | H883: =G883*100000 -> -200000 | I883: =IF(E883="POR",1,IF(E883="DEF",2,IF(E883="MED",3,4))) -> 2 | J883: =IF(ISERROR(VLOOKUP(D883,Nombres!A:D,2,FALSE)),"PROBLEMAAAAAA",VLOOKUP(D883,Nombres!A:D,2,FALSE)) -> Toljan
A884: 9 | B884: 45947 | C884: AdolfitoFlick | D884: Riedel | E884: =IF(ISERROR(VLOOKUP(D884,Nombres!A:D,4,FALSE)),"PROBLEMAAAAAA",VLOOKUP(D884,Nombres!A:D,4,FALSE)) -> DEF | F884: =IF(ISERROR(VLOOKUP(D884,Nombres!A:D,3,FALSE)),"PROBLEMAAAAAA",VLOOKUP(D884,Nombres!A:D,3,FALSE)) -> Espanyol | G884: 8 | H884: =G884*100000 -> 800000 | I884: =IF(E884="POR",1,IF(E884="DEF",2,IF(E884="MED",3,4))) -> 2 | J884: =IF(ISERROR(VLOOKUP(D884,Nombres!A:D,2,FALSE)),"PROBLEMAAAAAA",VLOOKUP(D884,Nombres!A:D,2,FALSE)) -> Riedel
A885: 9 | B885: 45947 | C885: AdolfitoFlick | D885: Carmona | E885: =IF(ISERROR(VLOOKUP(D885,Nombres!A:D,4,FALSE)),"PROBLEMAAAAAA",VLOOKUP(D885,Nombres!A:D,4,FALSE)) -> DEF | F885: =IF(ISERROR(VLOOKUP(D885,Nombres!A:D,3,FALSE)),"PROBLEMAAAAAA",VLOOKUP(D885,Nombres!A:D,3,FALSE)) -> Sevilla | G885: 6 | H885: =G885*100000 -> 600000 | I885: =IF(E885="POR",1,IF(E885="DEF",2,IF(E885="MED",3,4))) -> 2 | J885: =IF(ISERROR(VLOOKUP(D885,Nombres!A:D,2,FALSE)),"PROBLEMAAAAAA",VLOOKUP(D885,Nombres!A:D,2,FALSE)) -> Carmona
A886: 9 | B886: 45947 | C886: AdolfitoFlick | D886: Pacheco | E886: =IF(ISERROR(VLOOKUP(D886,Nombres!A:D,4,FALSE)),"PROBLEMAAAAAA",VLOOKUP(D886,Nombres!A:D,4,FALSE)) -> DEF | F886: =IF(ISERROR(VLOOKUP(D886,Nombres!A:D,3,FALSE)),"PROBLEMAAAAAA",VLOOKUP(D886,Nombres!A:D,3,FALSE)) -> Alavés | G886: 9 | H886: =G886*100000 -> 900000 | I886: =IF(E886="POR",1,IF(E886="DEF",2,IF(E886="MED",3,4))) -> 2 | J886: =IF(ISERROR(VLOOKUP(D886,Nombres!A:D,2,FALSE)),"PROBLEMAAAAAA",VLOOKUP(D886,Nombres!A:D,2,FALSE)) -> Pacheco
A887: 9 | B887: 45947 | C887: AdolfitoFlick | D887: German V | E887: =IF(ISERROR(VLOOKUP(D887,Nombres!A:D,4,FALSE)),"PROBLEMAAAAAA",VLOOKUP(D887,Nombres!A:D,4,FALSE)) -> MED | F887: =IF(ISERROR(VLOOKUP(D887,Nombres!A:D,3,FALSE)),"PROBLEMAAAAAA",VLOOKUP(D887,Nombres!A:D,3,FALSE)) -> Elche | G887: 5 | H887: =G887*100000 -> 500000 | I887: =IF(E887="POR",1,IF(E887="DEF",2,IF(E887="MED",3,4))) -> 3 | J887: =IF(ISERROR(VLOOKUP(D887,Nombres!A:D,2,FALSE)),"PROBLEMAAAAAA",VLOOKUP(D887,Nombres!A:D,2,FALSE)) -> Valera
A888: 9 | B888: 45947 | C888: AdolfitoFlick | D888: Samu Costa | E888: =IF(ISERROR(VLOOKUP(D888,Nombres!A:D,4,FALSE)),"PROBLEMAAAAAA",VLOOKUP(D888,Nombres!A:D,4,FALSE)) -> MED | F888: =IF(ISERROR(VLOOKUP(D888,Nombres!A:D,3,FALSE)),"PROBLEMAAAAAA",VLOOKUP(D888,Nombres!A:D,3,FALSE)) -> Mallorca | G888: 5 | H888: =G888*100000 -> 500000 | I888: =IF(E888="POR",1,IF(E888="DEF",2,IF(E888="MED",3,4))) -> 3 | J888: =IF(ISERROR(VLOOKUP(D888,Nombres!A:D,2,FALSE)),"PROBLEMAAAAAA",VLOOKUP(D888,Nombres!A:D,2,FALSE)) -> Samú
A889: 9 | B889: 45947 | C889: AdolfitoFlick | D889: Unai Lopez | E889: =IF(ISERROR(VLOOKUP(D889,Nombres!A:D,4,FALSE)),"PROBLEMAAAAAA",VLOOKUP(D889,Nombres!A:D,4,FALSE)) -> MED | F889: =IF(ISERROR(VLOOKUP(D889,Nombres!A:D,3,FALSE)),"PROBLEMAAAAAA",VLOOKUP(D889,Nombres!A:D,3,FALSE)) -> Rayo | G889: 11 | H889: =G889*100000 -> 1100000 | I889: =IF(E889="POR",1,IF(E889="DEF",2,IF(E889="MED",3,4))) -> 3 | J889: =IF(ISERROR(VLOOKUP(D889,Nombres!A:D,2,FALSE)),"PROBLEMAAAAAA",VLOOKUP(D889,Nombres!A:D,2,FALSE)) -> Unai López
A890: 9 | B890: 45947 | C890: AdolfitoFlick | D890: Lamine Yamal | E890: =IF(ISERROR(VLOOKUP(D890,Nombres!A:D,4,FALSE)),"PROBLEMAAAAAA",VLOOKUP(D890,Nombres!A:D,4,FALSE)) -> DEL | F890: =IF(ISERROR(VLOOKUP(D890,Nombres!A:D,3,FALSE)),"PROBLEMAAAAAA",VLOOKUP(D890,Nombres!A:D,3,FALSE)) -> Barcelona | G890: 10 | H890: =G890*100000 -> 1000000 | I890: =IF(E890="POR",1,IF(E890="DEF",2,IF(E890="MED",3,4))) -> 4 | J890: =IF(ISERROR(VLOOKUP(D890,Nombres!A:D,2,FALSE)),"PROBLEMAAAAAA",VLOOKUP(D890,Nombres!A:D,2,FALSE)) -> Yamal
A891: 9 | B891: 45947 | C891: AdolfitoFlick | D891: Danjuma | E891: =IF(ISERROR(VLOOKUP(D891,Nombres!A:D,4,FALSE)),"PROBLEMAAAAAA",VLOOKUP(D891,Nombres!A:D,4,FALSE)) -> DEL | F891: =IF(ISERROR(VLOOKUP(D891,Nombres!A:D,3,FALSE)),"PROBLEMAAAAAA",VLOOKUP(D891,Nombres!A:D,3,FALSE)) -> Valencia | G891: 6 | H891: =G891*100000 -> 600000 | I891: =IF(E891="POR",1,IF(E891="DEF",2,IF(E891="MED",3,4))) -> 4 | J891: =IF(ISERROR(VLOOKUP(D891,Nombres!A:D,2,FALSE)),"PROBLEMAAAAAA",VLOOKUP(D891,Nombres!A:D,2,FALSE)) -> Danjuma
A892: 9 | B892: 45947 | C892: AdolfitoFlick | D892: Cucho | E892: =IF(ISERROR(VLOOKUP(D892,Nombres!A:D,4,FALSE)),"PROBLEMAAAAAA",VLOOKUP(D892,Nombres!A:D,4,FALSE)) -> DEL | F892: =IF(ISERROR(VLOOKUP(D892,Nombres!A:D,3,FALSE)),"PROBLEMAAAAAA",VLOOKUP(D892,Nombres!A:D,3,FALSE)) -> Betis | G892: 0 | H892: =G892*100000 -> 0 | I892: =IF(E892="POR",1,IF(E892="DEF",2,IF(E892="MED",3,4))) -> 4 | J892: =IF(ISERROR(VLOOKUP(D892,Nombres!A:D,2,FALSE)),"PROBLEMAAAAAA",VLOOKUP(D892,Nombres!A:D,2,FALSE)) -> Cucho
A893: 10 | B893: 45947 | C893: AdolfitoFlick | D893: Radu | E893: =IF(ISERROR(VLOOKUP(D893,Nombres!A:D,4,FALSE)),"PROBLEMAAAAAA",VLOOKUP(D893,Nombres!A:D,4,FALSE)) -> POR | F893: =IF(ISERROR(VLOOKUP(D893,Nombres!A:D,3,FALSE)),"PROBLEMAAAAAA",VLOOKUP(D893,Nombres!A:D,3,FALSE)) -> Celta | G893: 5 | H893: =G893*100000 -> 500000 | I893: =IF(E893="POR",1,IF(E893="DEF",2,IF(E893="MED",3,4))) -> 1 | J893: =IF(ISERROR(VLOOKUP(D893,Nombres!A:D,2,FALSE)),"PROBLEMAAAAAA",VLOOKUP(D893,Nombres!A:D,2,FALSE)) -> Radu
... A1321: 12 | B1321: 45968 | C1321: yandrak | D1321: Pere Milla | E1321: =IF(ISERROR(VLOOKUP(D1321,Nombres!A:D,4,FALSE)),"PROBLEMAAAAAA",VLOOKUP(D1321,Nombres!A:D,4,FALSE)) -> DEL | F1321: =IF(ISERROR(VLOOKUP(D1321,Nombres!A:D,3,FALSE)),"PROBLEMAAAAAA",VLOOKUP(D1321,Nombres!A:D,3,FALSE)) -> Espanyol | G1321: 1 | H1321: =G1321*100000 -> 100000 | I1321: =IF(E1321="POR",1,IF(E1321="DEF",2,IF(E1321="MED",3,4))) -> 4 | J1321: =IF(ISERROR(VLOOKUP(D1321,Nombres!A:D,2,FALSE)),"PROBLEMAAAAAA",VLOOKUP(D1321,Nombres!A:D,2,FALSE)) -> Pere Milla

Sheet FC Recreativo de Juerga
A1: Indice | B1: FC Recreativo de Juerga
A2: Fichajes | K2: Ventas
A3: Posicion | B3: Jugador | C3: Fecha Compra | D3: Precio Compra | E3: Plantilla | K3: Posicion | L3: Jugador | M3: Fecha Venta | N3: Precio Venta | O3: Precio Compra | P3: Rentabilidad
A4: {=_xlfn._xlws.FILTER(Fichajes!C:C,Fichajes!G:G=B1)} -> DEF | B4: {=_xlfn._xlws.FILTER(Fichajes!B:B,Fichajes!G:G=B1)} -> Alderete | C4: {=_xlfn._xlws.FILTER(Fichajes!F:F,Fichajes!$G:$G=$B1)} -> 45872 | D4: {=_xlfn._xlws.FILTER(Fichajes!I:I,Fichajes!$G:$G=$B1)} -> 0 | E4: =IF(B4="","",IFERROR( IF( (VLOOKUP(B4,K:N,3,FALSE)) < C4, "X", "" ), "X") ) | K4: {=_xlfn._xlws.FILTER(Fichajes!B:B,Fichajes!$H:$H=B$1)} -> Carvajal | L4: {=_xlfn._xlws.FILTER(Fichajes!C:C,Fichajes!$H:$H=B$1)} -> DEF | M4: {=_xlfn._xlws.FILTER(Fichajes!F:F,Fichajes!$H:$H=B$1)} -> 45878 | N4: {=_xlfn._xlws.FILTER(Fichajes!I:I,Fichajes!$H:$H=B$1)} -> 27257064 | O4: =IF(ISBLANK(N4),"",VLOOKUP(K4,B:D,3,FALSE)) -> 0 | P4: =IF(ISBLANK(N4),"",N4-O4) -> 27257064
A5: DEL | B5: Asano | C5: 45872 | D5: 0 | E5: =IF(B5="","",IFERROR( IF( (VLOOKUP(B5,K:N,3,FALSE)) < C5, "X", "" ), "X") ) | K5: D. Llorente | L5: DEF | M5: 45878 | N5: 8482120 | O5: =IF(ISBLANK(N5),"",VLOOKUP(K5,B:D,3,FALSE)) -> 0 | P5: =IF(ISBLANK(N5),"",N5-O5) -> 8482120
A6: DEL | B6: Bakambu | C6: 45872 | D6: 0 | E6: =IF(B6="","",IFERROR( IF( (VLOOKUP(B6,K:N,3,FALSE)) < C6, "X", "" ), "X") ) | K6: Alderete | L6: DEF | M6: 45879 | N6: 10527479 | O6: =IF(ISBLANK(N6),"",VLOOKUP(K6,B:D,3,FALSE)) -> 0 | P6: =IF(ISBLANK(N6),"",N6-O6) -> 10527479
A7: DEF | B7: Carvajal | C7: 45872 | D7: 0 | E7: =IF(B7="","",IFERROR( IF( (VLOOKUP(B7,K:N,3,FALSE)) < C7, "X", "" ), "X") ) | K7: Van de Beek | L7: MED | M7: 45879 | N7: 3909069 | O7: =IF(ISBLANK(N7),"",VLOOKUP(K7,B:D,3,FALSE)) -> 0 | P7: =IF(ISBLANK(N7),"",N7-O7) -> 3909069
A8: DEF | B8: David López | C8: 45872 | D8: 0 | E8: =IF(B8="","",IFERROR( IF( (VLOOKUP(B8,K:N,3,FALSE)) < C8, "X", "" ), "X") ) | K8: Ejuke | L8: DEL | M8: 45881 | N8: 4000000 | O8: =IF(ISBLANK(N8),"",VLOOKUP(K8,B:D,3,FALSE)) -> 0 | P8: =IF(ISBLANK(N8),"",N8-O8) -> 4000000
A9: DEL | B9: Ejuke | C9: 45872 | D9: 0 | E9: =IF(B9="","",IFERROR( IF( (VLOOKUP(B9,K:N,3,FALSE)) < C9, "X", "" ), "X") ) | K9: Bakambu | L9: DEL | M9: 45883 | N9: 3345761 | O9: =IF(ISBLANK(N9),"",VLOOKUP(K9,B:D,3,FALSE)) -> 0 | P9: =IF(ISBLANK(N9),"",N9-O9) -> 3345761
A10: MED | B10: Guridi | C10: 45872 | D10: 0 | E10: =IF(B10="","",IFERROR( IF( (VLOOKUP(B10,K:N,3,FALSE)) < C10, "X", "" ), "X") ) | K10: Traore | L10: DEF | M10: 45883 | N10: 7269464 | O10: =IF(ISBLANK(N10),"",VLOOKUP(K10,B:D,3,FALSE)) -> 0 | P10: =IF(ISBLANK(N10),"",N10-O10) -> 7269464
A11: POR | B11: Leo Román | C11: 45872 | D11: 0 | E11: =IF(B11="","",IFERROR( IF( (VLOOKUP(B11,K:N,3,FALSE)) < C11, "X", "" ), "X") ) | K11: Leo Román | L11: POR | M11: 45887 | N11: 10938553 | O11: =IF(ISBLANK(N11),"",VLOOKUP(K11,B:D,3,FALSE)) -> 0 | P11: =IF(ISBLANK(N11),"",N11-O11) -> 10938553
A12: DEF | B12: D. Llorente | C12: 45872 | D12: 0 | E12: =IF(B12="","",IFERROR( IF( (VLOOKUP(B12,K:N,3,FALSE)) < C12, "X", "" ), "X") ) | K12: Muriqi | L12: DEL | M12: 45887 | N12: 27117936 | O12: =IF(ISBLANK(N12),"",VLOOKUP(K12,B:D,3,FALSE)) -> 36787048 | P12: =IF(ISBLANK(N12),"",N12-O12) -> -9669112
A13: MED | B13: Moncayola | C13: 45872 | D13: 0 | E13: =IF(B13="","",IFERROR( IF( (VLOOKUP(B13,K:N,3,FALSE)) < C13, "X", "" ), "X") ) | K13: Terrats | L13: MED | M13: 45887 | N13: 8502173 | O13: =IF(ISBLANK(N13),"",VLOOKUP(K13,B:D,3,FALSE)) -> 0 | P13: =IF(ISBLANK(N13),"",N13-O13) -> 8502173
A14: MED | B14: Terrats | C14: 45872 | D14: 0 | E14: =IF(B14="","",IFERROR( IF( (VLOOKUP(B14,K:N,3,FALSE)) < C14, "X", "" ), "X") ) | K14: Thomas | L14: MED | M14: 45889 | N14: 13815509 | O14: =IF(ISBLANK(N14),"",VLOOKUP(K14,B:D,3,FALSE)) -> 20000001 | P14: =IF(ISBLANK(N14),"",N14-O14) -> -6184492
A15: MED | B15: Torró | C15: 45872 | D15: 0 | E15: =IF(B15="","",IFERROR( IF( (VLOOKUP(B15,K:N,3,FALSE)) < C15, "X", "" ), "X") ) | K15: Balliu | L15: DEF | M15: 45891 | N15: 3427255 | O15: =IF(ISBLANK(N15),"",VLOOKUP(K15,B:D,3,FALSE)) -> 9500010 | P15: =IF(ISBLANK(N15),"",N15-O15) -> -6072755
A16: DEF | B16: Traore | C16: 45872 | D16: 0 | E16: =IF(B16="","",IFERROR( IF( (VLOOKUP(B16,K:N,3,FALSE)) < C16, "X", "" ), "X") ) | K16: Asano | L16: DEL | M16: 45895 | N16: 2247494 | O16: =IF(ISBLANK(N16),"",VLOOKUP(K16,B:D,3,FALSE)) -> 0 | P16: =IF(ISBLANK(N16),"",N16-O16) -> 2247494
... A48: MED | B48: R. de Galarreta | C48: 45917 | D48: 15593430 | E48: =IF(B48="","",IFERROR( IF( (VLOOKUP(B48,K:N,3,FALSE)) < C48, "X", "" ), "X") ) -> X | K48: Barrenetxea | L48: MED | M48: 45938 | N48: 32736001 | O48: =IF(ISBLANK(N48),"",VLOOKUP(K48,B:D,3,FALSE)) -> 5678911 | P48: =IF(ISBLANK(N48),"",N48-O48) -> 27057090
A49: MED | B49: Juanlu | C49: 45918 | D49: 6542165 | E49: =IF(B49="","",IFERROR( IF( (VLOOKUP(B49,K:N,3,FALSE)) < C49, "X", "" ), "X") ) | K49: Iván Martín | L49: MED | M49: 45940 | N49: 3834030
A50: DEL | B50: Víctor Muñoz | C50: 45918 | D50: 3987785 | E50: =IF(B50="","",IFERROR( IF( (VLOOKUP(B50,K:N,3,FALSE)) < C50, "X", "" ), "X") ) | K50: Alexis | L50: DEL | M50: 45944 | N50: 20677441
A51: DEF | B51: Militão | C51: 45919 | D51: 45865641 | E51: =IF(B51="","",IFERROR( IF( (VLOOKUP(B51,K:N,3,FALSE)) < C51, "X", "" ), "X") ) | K51: Etta Eyong | L51: DEL | M51: 45945 | N51: 110031134
A52: MED | B52: Febas | C52: 45922 | D52: 8210100 | E52: =IF(B52="","",IFERROR( IF( (VLOOKUP(B52,K:N,3,FALSE)) < C52, "X", "" ), "X") ) | K52: Azpilicueta | L52: DEF | M52: 45948 | N52: 5692561
A53: MED | B53: Lozano | C53: 45922 | D53: 3210000 | E53: =IF(B53="","",IFERROR( IF( (VLOOKUP(B53,K:N,3,FALSE)) < C53, "X", "" ), "X") ) | K53: Torró | L53: MED | M53: 45948 | N53: 2823674
A54: MED | B54: Barrenetxea | C54: 45924 | D54: 19369067 | E54: =IF(B54="","",IFERROR( IF( (VLOOKUP(B54,K:N,3,FALSE)) < C54, "X", "" ), "X") ) -> X | K54: Pépé | L54: DEL | M54: 45950 | N54: 91241452
A55: DEF | B55: Veiga | C55: 45924 | D55: 16128445 | E55: =IF(B55="","",IFERROR( IF( (VLOOKUP(B55,K:N,3,FALSE)) < C55, "X", "" ), "X") ) -> X | K55: Lozano | L55: MED | M55: 45953 | N55: 10014326
A56: DEF | B56: Vertrouwd | C56: 45924 | D56: 625059 | E56: =IF(B56="","",IFERROR( IF( (VLOOKUP(B56,K:N,3,FALSE)) < C56, "X", "" ), "X") ) -> X | K56: Febas | L56: MED | M56: 45953 | N56: 23210100
A57: DEL | B57: Etta Eyong | C57: 45928 | D57: 65117539 | E57: =IF(B57="","",IFERROR( IF( (VLOOKUP(B57,K:N,3,FALSE)) < C57, "X", "" ), "X") ) -> X | K57: N. Williams | L57: DEL | M57: 45957 | N57: 89423295
A58: DEL | B58: I. Williams | C58: 45928 | D58: 34309065 | E58: =IF(B58="","",IFERROR( IF( (VLOOKUP(B58,K:N,3,FALSE)) < C58, "X", "" ), "X") ) | K58: Luis Milla | L58: MED | M58: 45959 | N58: 90222396
A59: DEF | B59: Tenaglia | C59: 45916 | D59: 17000000 | E59: =IF(B59="","",IFERROR( IF( (VLOOKUP(B59,K:N,3,FALSE)) < C59, "X", "" ), "X") ) | K59: Manu Sánchez | L59: DEF | M59: 45960 | N59: 2160657
A60: MED | B60: Luis Milla | C60: 45930 | D60: 45988103 | E60: =IF(B60="","",IFERROR( IF( (VLOOKUP(B60,K:N,3,FALSE)) < C60, "X", "" ), "X") ) | K60: C. Álvarez | L60: MED | M60: 45960 | N60: 26980873
... A64: MED | B64: C. Álvarez | C64: 45934 | D64: 15411401 | E64: =IF(B64="","",IFERROR( IF( (VLOOKUP(B64,K:N,3,FALSE)) < C64, "X", "" ), "X") ) | K64: Natan | L64: DEF | M64: 45973 | N64: 44480506
A65: DEL | B65: Roberto | C65: 45936 | D65: 11087545 | E65: =IF(B65="","",IFERROR( IF( (VLOOKUP(B65,K:N,3,FALSE)) < C65, "X", "" ), "X") ) -> X
A66: DEF | B66: Valentín Gómez | C66: 45939 | D66: 2863699 | E66: =IF(B66="","",IFERROR( IF( (VLOOKUP(B66,K:N,3,FALSE)) < C66, "X", "" ), "X") )
A67: DEF | B67: Yuri | C67: 45942 | D67: 0 | E67: =IF(B67="","",IFERROR( IF( (VLOOKUP(B67,K:N,3,FALSE)) < C67, "X", "" ), "X") ) -> X
A68: MED | B68: Herrera | C68: 45944 | D68: 2651124 | E68: =IF(B68="","",IFERROR( IF( (VLOOKUP(B68,K:N,3,FALSE)) < C68, "X", "" ), "X") )
A69: DEL | B69: Boyé | C69: 45945 | D69: 2506689 | E69: =IF(B69="","",IFERROR( IF( (VLOOKUP(B69,K:N,3,FALSE)) < C69, "X", "" ), "X") ) -> X
A70: DEL | B70: Pépé | C70: 45945 | D70: 91296567 | E70: =IF(B70="","",IFERROR( IF( (VLOOKUP(B70,K:N,3,FALSE)) < C70, "X", "" ), "X") )
A71: DEF | B71: Manu Sánchez | C71: 45946 | D71: 2160657 | E71: =IF(B71="","",IFERROR( IF( (VLOOKUP(B71,K:N,3,FALSE)) < C71, "X", "" ), "X") )
A72: DEF | B72: Jonny | C72: 45948 | D72: 7045151 | E72: =IF(B72="","",IFERROR( IF( (VLOOKUP(B72,K:N,3,FALSE)) < C72, "X", "" ), "X") ) -> X
A73: DEL | B73: N. Williams | C73: 45949 | D73: 98000052 | E73: =IF(B73="","",IFERROR( IF( (VLOOKUP(B73,K:N,3,FALSE)) < C73, "X", "" ), "X") )
A74: DEL | B74: Brugui | C74: 45949 | D74: 1500001 | E74: =IF(B74="","",IFERROR( IF( (VLOOKUP(B74,K:N,3,FALSE)) < C74, "X", "" ), "X") ) -> X
A75: MED | B75: Witsel | C75: 45952 | D75: 5217424 | E75: =IF(B75="","",IFERROR( IF( (VLOOKUP(B75,K:N,3,FALSE)) < C75, "X", "" ), "X") ) -> X
A76: DEF | B76: Maffeo | C76: 45952 | D76: 9932929 | E76: =IF(B76="","",IFERROR( IF( (VLOOKUP(B76,K:N,3,FALSE)) < C76, "X", "" ), "X") ) -> X
... A85: DEL | B85: Gerard | C85: 45973 | D85: 16610101 | E85: =IF(B85="","",IFERROR( IF( (VLOOKUP(B85,K:N,3,FALSE)) < C85, "X", "" ), "X") ) -> X
E86: =IF(B86="","",IFERROR( IF( (VLOOKUP(B86,K:N,3,FALSE)) < C86, "X", "" ), "X") )
E87: =IF(B87="","",IFERROR( IF( (VLOOKUP(B87,K:N,3,FALSE)) < C87, "X", "" ), "X") )
E88: =IF(B88="","",IFERROR( IF( (VLOOKUP(B88,K:N,3,FALSE)) < C88, "X", "" ), "X") )
E89: =IF(B89="","",IFERROR( IF( (VLOOKUP(B89,K:N,3,FALSE)) < C89, "X", "" ), "X") )
E90: =IF(B90="","",IFERROR( IF( (VLOOKUP(B90,K:N,3,FALSE)) < C90, "X", "" ), "X") )
E91: =IF(B91="","",IFERROR( IF( (VLOOKUP(B91,K:N,3,FALSE)) < C91, "X", "" ), "X") )
E92: =IF(B92="","",IFERROR( IF( (VLOOKUP(B92,K:N,3,FALSE)) < C92, "X", "" ), "X") )
E93: =IF(B93="","",IFERROR( IF( (VLOOKUP(B93,K:N,3,FALSE)) < C93, "X", "" ), "X") )
E94: =IF(B94="","",IFERROR( IF( (VLOOKUP(B94,K:N,3,FALSE)) < C94, "X", "" ), "X") )
E95: =IF(B95="","",IFERROR( IF( (VLOOKUP(B95,K:N,3,FALSE)) < C95, "X", "" ), "X") )
E96: =IF(B96="","",IFERROR( IF( (VLOOKUP(B96,K:N,3,FALSE)) < C96, "X", "" ), "X") )
E97: =IF(B97="","",IFERROR( IF( (VLOOKUP(B97,K:N,3,FALSE)) < C97, "X", "" ), "X") )
... E152: =IF(B152="","",IFERROR( IF( (VLOOKUP(B152,K:N,3,FALSE)) < C152, "X", "" ), "X") )

Sheet yandrak
A1: Indice | B1: yandrak
A2: Fichajes | K2: Ventas
A3: Posicion | B3: Jugador | C3: Fecha Compra | D3: Precio Compra | E3: Plantilla | K3: Posicion | L3: Jugador | M3: Fecha Venta | N3: Precio Venta | O3: Precio Compra | P3: Rentabilidad
A4: {=_xlfn._xlws.FILTER(Fichajes!C:C,Fichajes!G:G=B1)} -> DEF | B4: {=_xlfn._xlws.FILTER(Fichajes!B:B,Fichajes!G:G=B1)} -> Andrei | C4: {=_xlfn._xlws.FILTER(Fichajes!F:F,Fichajes!$G:$G=$B1)} -> 45872 | D4: {=_xlfn._xlws.FILTER(Fichajes!I:I,Fichajes!$G:$G=$B1)} -> 0 | E4: =IF(B4="","",IFERROR( IF( (VLOOKUP(B4,K:N,3,FALSE)) < C4, "X", "" ), "X") ) | K4: {=_xlfn._xlws.FILTER(Fichajes!B:B,Fichajes!$H:$H=B$1)} -> D. Duarte | L4: {=_xlfn._xlws.FILTER(Fichajes!C:C,Fichajes!$H:$H=B$1)} -> DEF | M4: {=_xlfn._xlws.FILTER(Fichajes!F:F,Fichajes!$H:$H=B$1)} -> 45874 | N4: {=_xlfn._xlws.FILTER(Fichajes!I:I,Fichajes!$H:$H=B$1)} -> 1167041 | O4: =IF(ISBLANK(N4),"",VLOOKUP(K4,B:D,3,FALSE)) -> 0 | P4: =IF(ISBLANK(N4),"",N4-O4) -> 1167041
A5: MED | B5: Blanco | C5: 45872 | D5: 0 | E5: =IF(B5="","",IFERROR( IF( (VLOOKUP(B5,K:N,3,FALSE)) < C5, "X", "" ), "X") ) | K5: Andrei | L5: DEF | M5: 45876 | N5: 14500000 | O5: =IF(ISBLANK(N5),"",VLOOKUP(K5,B:D,3,FALSE)) -> 0 | P5: =IF(ISBLANK(N5),"",N5-O5) -> 14500000
A6: POR | B6: Dimitrievski | C6: 45872 | D6: 0 | E6: =IF(B6="","",IFERROR( IF( (VLOOKUP(B6,K:N,3,FALSE)) < C6, "X", "" ), "X") ) | K6: Pablo Torre | L6: MED | M6: 45877 | N6: 10000000 | O6: =IF(ISBLANK(N6),"",VLOOKUP(K6,B:D,3,FALSE)) -> 0 | P6: =IF(ISBLANK(N6),"",N6-O6) -> 10000000
A7: DEF | B7: D. Duarte | C7: 45872 | D7: 0 | E7: =IF(B7="","",IFERROR( IF( (VLOOKUP(B7,K:N,3,FALSE)) < C7, "X", "" ), "X") ) | K7: Tsygankov | L7: DEL | M7: 45877 | N7: 18143367 | O7: =IF(ISBLANK(N7),"",VLOOKUP(K7,B:D,3,FALSE)) -> 0 | P7: =IF(ISBLANK(N7),"",N7-O7) -> 18143367
A8: DEF | B8: Foyth | C8: 45872 | D8: 0 | E8: =IF(B8="","",IFERROR( IF( (VLOOKUP(B8,K:N,3,FALSE)) < C8, "X", "" ), "X") ) | K8: Dimitrievski | L8: POR | M8: 45879 | N8: 6540521 | O8: =IF(ISBLANK(N8),"",VLOOKUP(K8,B:D,3,FALSE)) -> 0 | P8: =IF(ISBLANK(N8),"",N8-O8) -> 6540521
A9: DEL | B9: Giuliano | C9: 45872 | D9: 0 | E9: =IF(B9="","",IFERROR( IF( (VLOOKUP(B9,K:N,3,FALSE)) < C9, "X", "" ), "X") ) | K9: Moi Gómez | L9: MED | M9: 45879 | N9: 5807847 | O9: =IF(ISBLANK(N9),"",VLOOKUP(K9,B:D,3,FALSE)) -> 0 | P9: =IF(ISBLANK(N9),"",N9-O9) -> 5807847
A10: MED | B10: Javi Guerra | C10: 45872 | D10: 0 | E10: =IF(B10="","",IFERROR( IF( (VLOOKUP(B10,K:N,3,FALSE)) < C10, "X", "" ), "X") ) | K10: Pépé | L10: DEL | M10: 45886 | N10: 19282733 | O10: =IF(ISBLANK(N10),"",VLOOKUP(K10,B:D,3,FALSE)) -> 0 | P10: =IF(ISBLANK(N10),"",N10-O10) -> 19282733
A11: DEF | B11: Krejci | C11: 45872 | D11: 0 | E11: =IF(B11="","",IFERROR( IF( (VLOOKUP(B11,K:N,3,FALSE)) < C11, "X", "" ), "X") ) | K11: Blanco | L11: MED | M11: 45887 | N11: 11636446 | O11: =IF(ISBLANK(N11),"",VLOOKUP(K11,B:D,3,FALSE)) -> 0 | P11: =IF(ISBLANK(N11),"",N11-O11) -> 11636446
A12: MED | B12: Moi Gómez | C12: 45872 | D12: 0 | E12: =IF(B12="","",IFERROR( IF( (VLOOKUP(B12,K:N,3,FALSE)) < C12, "X", "" ), "X") ) | K12: Krejci | L12: DEF | M12: 45890 | N12: 6547216 | O12: =IF(ISBLANK(N12),"",VLOOKUP(K12,B:D,3,FALSE)) -> 0 | P12: =IF(ISBLANK(N12),"",N12-O12) -> 6547216
A13: MED | B13: Pablo Torre | C13: 45872 | D13: 0 | E13: =IF(B13="","",IFERROR( IF( (VLOOKUP(B13,K:N,3,FALSE)) < C13, "X", "" ), "X") ) | K13: Foyth | L13: DEF | M13: 45897 | N13: 27796533 | O13: =IF(ISBLANK(N13),"",VLOOKUP(K13,B:D,3,FALSE)) -> 0 | P13: =IF(ISBLANK(N13),"",N13-O13) -> 27796533
A14: DEL | B14: Pépé | C14: 45872 | D14: 0 | E14: =IF(B14="","",IFERROR( IF( (VLOOKUP(B14,K:N,3,FALSE)) < C14, "X", "" ), "X") ) | K14: Buchanan | L14: MED | M14: 45900 | N14: 10108420 | O14: =IF(ISBLANK(N14),"",VLOOKUP(K14,B:D,3,FALSE)) -> 5158826 | P14: =IF(ISBLANK(N14),"",N14-O14) -> 4949594
A15: MED | B15: Rioja | C15: 45872 | D15: 0 | E15: =IF(B15="","",IFERROR( IF( (VLOOKUP(B15,K:N,3,FALSE)) < C15, "X", "" ), "X") ) | K15: Giuliano | L15: DEL | M15: 45908 | N15: 40021696 | O15: =IF(ISBLANK(N15),"",VLOOKUP(K15,B:D,3,FALSE)) -> 0 | P15: =IF(ISBLANK(N15),"",N15-O15) -> 40021696
A16: DEF | B16: Ruggeri | C16: 45872 | D16: 0 | E16: =IF(B16="","",IFERROR( IF( (VLOOKUP(B16,K:N,3,FALSE)) < C16, "X", "" ), "X") ) | K16: Portu | L16: DEL | M16: 45910 | N16: 1306600 | O16: =IF(ISBLANK(N16),"",VLOOKUP(K16,B:D,3,FALSE)) -> 3212503 | P16: =IF(ISBLANK(N16),"",N16-O16) -> -1905903
... A35: MED | B35: Altimira | C35: 45916 | D35: 14285808 | E35: =IF(B35="","",IFERROR( IF( (VLOOKUP(B35,K:N,3,FALSE)) < C35, "X", "" ), "X") ) | K35: Peña | L35: POR | M35: 45931 | N35: 2259813 | O35: =IF(ISBLANK(N35),"",VLOOKUP(K35,B:D,3,FALSE)) -> 2225124 | P35: =IF(ISBLANK(N35),"",N35-O35) -> 34689
A36: DEF | B36: Ristic | C36: 45916 | D36: 1000000 | K36: Oluwaseyi | L36: DEL | M36: 45931 | N36: 2929819 | O36: =IF(ISBLANK(N36),"",VLOOKUP(K36,B:D,3,FALSE)) -> 2856286 | P36: =IF(ISBLANK(N36),"",N36-O36) -> 73533
A37: DEF | B37: Boyomo | C37: 45917 | D37: 19778592 | K37: Koundé | L37: DEF | M37: 45933 | N37: 53854422 | O37: =IF(ISBLANK(N37),"",VLOOKUP(K37,B:D,3,FALSE)) -> 63323263 | P37: =IF(ISBLANK(N37),"",N37-O37) -> -9468841
A38: DEL | B38: Giuliano | C38: 45920 | D38: 42151996 | K38: Bellingham | L38: MED | M38: 45937 | N38: 81008927 | O38: =IF(ISBLANK(N38),"",VLOOKUP(K38,B:D,3,FALSE)) -> 78247575 | P38: =IF(ISBLANK(N38),"",N38-O38) -> 2761352
A39: MED | B39: Tchouaméni | C39: 45921 | D39: 60976487 | K39: Romero | L39: DEL | M39: 45938 | N39: 13987987 | O39: =IF(ISBLANK(N39),"",VLOOKUP(K39,B:D,3,FALSE)) -> 13987987 | P39: =IF(ISBLANK(N39),"",N39-O39) -> 0
A40: MED | B40: Guridi | C40: 45922 | D40: 2499999 | K40: Vinicius | L40: DEL | M40: 45945 | N40: 152239079 | O40: =IF(ISBLANK(N40),"",VLOOKUP(K40,B:D,3,FALSE)) -> 130000001 | P40: =IF(ISBLANK(N40),"",N40-O40) -> 22239078
A41: DEL | B41: Romero | C41: 45922 | D41: 13987987 | K41: Jauregizar | L41: MED | M41: 45949 | N41: 24476604 | O41: =IF(ISBLANK(N41),"",VLOOKUP(K41,B:D,3,FALSE)) -> 18099036 | P41: =IF(ISBLANK(N41),"",N41-O41) -> 6377568
A42: DEL | B42: Durán | C42: 45922 | D42: 1600000 | K42: Durán | L42: DEL | M42: 45952 | N42: 1600000 | O42: =IF(ISBLANK(N42),"",VLOOKUP(K42,B:D,3,FALSE)) -> 1600000 | P42: =IF(ISBLANK(N42),"",N42-O42) -> 0
A43: MED | B43: Bellingham | C43: 45923 | D43: 78247575 | K43: Juan Cruz | L43: DEF | M43: 45952 | N43: 2243833 | O43: =IF(ISBLANK(N43),"",VLOOKUP(K43,B:D,3,FALSE)) -> 2090983 | P43: =IF(ISBLANK(N43),"",N43-O43) -> 152850
A44: DEF | B44: A. Christensen | C44: 45924 | D44: 4110892 | K44: Romero | L44: DEF | M44: 45955 | N44: 16000000 | O44: =IF(ISBLANK(N44),"",VLOOKUP(K44,B:D,3,FALSE)) -> 13987987 | P44: =IF(ISBLANK(N44),"",N44-O44) -> 2012013
A45: POR | B45: Peña | C45: 45929 | D45: 2225124 | K45: Abde | L45: DEL | M45: 45959 | N45: 32239613 | O45: =IF(ISBLANK(N45),"",VLOOKUP(K45,B:D,3,FALSE)) -> 32239613 | P45: =IF(ISBLANK(N45),"",N45-O45) -> 0
A46: DEF | B46: Francés | C46: 45930 | D46: 1704077 | K46: Alejandro Rego | L46: DEF | M46: 45959 | N46: 526248 | O46: =IF(ISBLANK(N46),"",VLOOKUP(K46,B:D,3,FALSE)) -> 512739 | P46: =IF(ISBLANK(N46),"",N46-O46) -> 13509
A47: MED | B47: Jauregizar | C47: 45930 | D47: 18099036 | K47: Oyarzabal | L47: DEL | M47: 45959 | N47: 43160079 | O47: =IF(ISBLANK(N47),"",VLOOKUP(K47,B:D,3,FALSE)) -> 38294813 | P47: =IF(ISBLANK(N47),"",N47-O47) -> 4865266
A48: DEL | B48: Oluwaseyi | C48: 45930 | D48: 2856286 | K48: M. Alonso | L48: DEF | M48: 45960 | N48: 18644883 | O48: =IF(ISBLANK(N48),"",VLOOKUP(K48,B:D,3,FALSE)) -> 18644883 | P48: =IF(ISBLANK(N48),"",N48-O48) -> 0
A49: MED | B49: Roca | C49: 45930 | D49: 379084 | K49: Güler | L49: MED | M49: 45960 | N49: 122854925
A50: MED | B50: Guevara | C50: 45932 | D50: 896928 | K50: Aguado | L50: MED | M50: 45964 | N50: 1286806
A51: DEL | B51: Vinicius | C51: 45933 | D51: 130000001 | K51: Hancko | L51: DEF | M51: 45966 | N51: 20000000
A52: DEF | B52: Romero | C52: 45933 | D52: 16000000 | K52: Valjent | L52: DEF | M52: 45966 | N52: 7108000
A53: DEF | B53: Paredes | C53: 45935 | D53: 28504496 | K53: Eric García | L53: DEF | M53: 45967 | N53: 43923813
A54: DEF | B54: Alejandro Rego | C54: 45935 | D54: 512739 | K54: Romero | L54: DEL | M54: 45968 | N54: 7974814
A55: DEF | B55: Juan Cruz | C55: 45936 | D55: 2806143 | K55: Iglesias | L55: DEL | M55: 45973 | N55: 19552500
A56: DEF | B56: Sergio Gómez | C56: 45944 | D56: 6195456
A57: MED | B57: Güler | C57: 45945 | D57: 122854925
A58: DEL | B58: Abde | C58: 45945 | D58: 32239613
A59: MED | B59: Aguado | C59: 45945 | D59: 1151818
A60: DEL | B60: Oyarzabal | C60: 45945 | D60: 38294813
A61: DEF | B61: Caleta-Car | C61: 45947 | D61: 3596609
A62: MED | B62: Marc Roca | C62: 45949 | D62: 1409336
A63: DEF | B63: Valjent | C63: 45952 | D63: 7108000
A64: DEF | B64: Hancko | C64: 45952 | D64: 20000000
A65: DEL | B65: Romero | C65: 45952 | D65: 13987987
A66: MED | B66: Pathé Ciss | C66: 45957 | D66: 12481047
A67: DEF | B67: Eric García | C67: 45959 | D67: 46957357
... A76: DEF | B76: Huijsen | C76: 45971 | D76: 79471660

Sheet Shiquetito 9
A1: Indice | B1: Shiquetito 9
A2: Fichajes | K2: Ventas
A3: Posicion | B3: Jugador | C3: Fecha Compra | D3: Precio Compra | E3: Plantilla | K3: Posicion | L3: Jugador | M3: Fecha Venta | N3: Precio Venta | O3: Precio Compra | P3: Rentabilidad
A4: {=_xlfn._xlws.FILTER(Fichajes!C:C,Fichajes!G:G=B1)} -> POR | B4: {=_xlfn._xlws.FILTER(Fichajes!B:B,Fichajes!G:G=B1)} -> Aitor | C4: {=_xlfn._xlws.FILTER(Fichajes!F:F,Fichajes!$G:$G=$B1)} -> 45875 | D4: {=_xlfn._xlws.FILTER(Fichajes!I:I,Fichajes!$G:$G=$B1)} -> 0 | E4: =IF(B4="","",IFERROR( IF( (VLOOKUP(B4,K:N,3,FALSE)) < C4, "X", "" ), "X") ) -> X | K4: {=_xlfn._xlws.FILTER(Fichajes!B:B,Fichajes!$H:$H=B$1)} -> Endrick | L4: {=_xlfn._xlws.FILTER(Fichajes!C:C,Fichajes!$H:$H=B$1)} -> DEL | M4: {=_xlfn._xlws.FILTER(Fichajes!F:F,Fichajes!$H:$H=B$1)} -> 45881 | N4: {=_xlfn._xlws.FILTER(Fichajes!I:I,Fichajes!$H:$H=B$1)} -> 6324142 | O4: =IF(ISBLANK(N4),"",VLOOKUP(K4,B:D,3,FALSE)) -> 0 | P4: =IF(ISBLANK(N4),"",N4-O4) -> 6324142
A5: MED | B5: Almada | C5: 45875 | D5: 0 | E5: =IF(B5="","",IFERROR( IF( (VLOOKUP(B5,K:N,3,FALSE)) < C5, "X", "" ), "X") ) | K5: Miguel | L5: DEF | M5: 45881 | N5: 9729339 | O5: =IF(ISBLANK(N5),"",VLOOKUP(K5,B:D,3,FALSE)) -> 0 | P5: =IF(ISBLANK(N5),"",N5-O5) -> 9729339
A6: MED | B6: Almeida | C6: 45875 | D6: 0 | E6: =IF(B6="","",IFERROR( IF( (VLOOKUP(B6,K:N,3,FALSE)) < C6, "X", "" ), "X") ) -> X | K6: Rodrygo | L6: DEL | M6: 45881 | N6: 20644625 | O6: =IF(ISBLANK(N6),"",VLOOKUP(K6,B:D,3,FALSE)) -> 0 | P6: =IF(ISBLANK(N6),"",N6-O6) -> 20644625
A7: DEF | B7: D. Duarte | C7: 45875 | D7: 0 | E7: =IF(B7="","",IFERROR( IF( (VLOOKUP(B7,K:N,3,FALSE)) < C7, "X", "" ), "X") ) | K7: Almada | L7: MED | M7: 45889 | N7: 27002791 | O7: =IF(ISBLANK(N7),"",VLOOKUP(K7,B:D,3,FALSE)) -> 0 | P7: =IF(ISBLANK(N7),"",N7-O7) -> 27002791
A8: DEL | B8: Endrick | C8: 45875 | D8: 0 | E8: =IF(B8="","",IFERROR( IF( (VLOOKUP(B8,K:N,3,FALSE)) < C8, "X", "" ), "X") ) | K8: Raba | L8: DEL | M8: 45889 | N8: 13741840 | O8: =IF(ISBLANK(N8),"",VLOOKUP(K8,B:D,3,FALSE)) -> 0 | P8: =IF(ISBLANK(N8),"",N8-O8) -> 13741840
A9: DEF | B9: Hancko | C9: 45875 | D9: 0 | E9: =IF(B9="","",IFERROR( IF( (VLOOKUP(B9,K:N,3,FALSE)) < C9, "X", "" ), "X") ) | K9: Riquelme | L9: MED | M9: 45889 | N9: 17158711 | O9: =IF(ISBLANK(N9),"",VLOOKUP(K9,B:D,3,FALSE)) -> 0 | P9: =IF(ISBLANK(N9),"",N9-O9) -> 17158711
A10: DEF | B10: Miguel | C10: 45875 | D10: 0 | E10: =IF(B10="","",IFERROR( IF( (VLOOKUP(B10,K:N,3,FALSE)) < C10, "X", "" ), "X") ) | K10: Parejo | L10: MED | M10: 45894 | N10: 12353847 | O10: =IF(ISBLANK(N10),"",VLOOKUP(K10,B:D,3,FALSE)) -> 0 | P10: =IF(ISBLANK(N10),"",N10-O10) -> 12353847
A11: MED | B11: Moleiro | C11: 45875 | D11: 0 | E11: =IF(B11="","",IFERROR( IF( (VLOOKUP(B11,K:N,3,FALSE)) < C11, "X", "" ), "X") ) | K11: Ejuke | L11: DEL | M11: 45896 | N11: 4000000 | O11: =IF(ISBLANK(N11),"",VLOOKUP(K11,B:D,3,FALSE)) -> 4000000 | P11: =IF(ISBLANK(N11),"",N11-O11) -> 0
A12: DEF | B12: Espino | C12: 45875 | D12: 3896588 | E12: =IF(B12="","",IFERROR( IF( (VLOOKUP(B12,K:N,3,FALSE)) < C12, "X", "" ), "X") ) -> X | K12: Agoume | L12: MED | M12: 45897 | N12: 7238909 | O12: =IF(ISBLANK(N12),"",VLOOKUP(K12,B:D,3,FALSE)) -> 7238909 | P12: =IF(ISBLANK(N12),"",N12-O12) -> 0
A13: DEF | B13: Paredes | C13: 45875 | D13: 0 | E13: =IF(B13="","",IFERROR( IF( (VLOOKUP(B13,K:N,3,FALSE)) < C13, "X", "" ), "X") ) | K13: Hancko | L13: DEF | M13: 45897 | N13: 34298293 | O13: =IF(ISBLANK(N13),"",VLOOKUP(K13,B:D,3,FALSE)) -> 0 | P13: =IF(ISBLANK(N13),"",N13-O13) -> 34298293
A14: MED | B14: Parejo | C14: 45875 | D14: 0 | E14: =IF(B14="","",IFERROR( IF( (VLOOKUP(B14,K:N,3,FALSE)) < C14, "X", "" ), "X") ) | K14: Iglesias | L14: DEF | M14: 45897 | N14: 2369904 | O14: =IF(ISBLANK(N14),"",VLOOKUP(K14,B:D,3,FALSE)) -> 2100858 | P14: =IF(ISBLANK(N14),"",N14-O14) -> 269046
A15: DEL | B15: Raba | C15: 45875 | D15: 0 | E15: =IF(B15="","",IFERROR( IF( (VLOOKUP(B15,K:N,3,FALSE)) < C15, "X", "" ), "X") ) | K15: Paredes | L15: DEF | M15: 45900 | N15: 17925060 | O15: =IF(ISBLANK(N15),"",VLOOKUP(K15,B:D,3,FALSE)) -> 0 | P15: =IF(ISBLANK(N15),"",N15-O15) -> 17925060
A16: MED | B16: Riquelme | C16: 45875 | D16: 0 | E16: =IF(B16="","",IFERROR( IF( (VLOOKUP(B16,K:N,3,FALSE)) < C16, "X", "" ), "X") ) | K16: D. Duarte | L16: DEF | M16: 45906 | N16: 1672958 | O16: =IF(ISBLANK(N16),"",VLOOKUP(K16,B:D,3,FALSE)) -> 0 | P16: =IF(ISBLANK(N16),"",N16-O16) -> 1672958
... A37: MED | B37: Oriol Rey | C37: 45920 | D37: 1800000 | E37: =IF(B37="","",IFERROR( IF( (VLOOKUP(B37,K:N,3,FALSE)) < C37, "X", "" ), "X") ) -> X | K37: Raúl García | L37: DEL | M37: 45967 | N37: 4605484 | O37: =IF(ISBLANK(N37),"",VLOOKUP(K37,B:D,3,FALSE)) -> 4605484 | P37: =IF(ISBLANK(N37),"",N37-O37) -> 0
A38: MED | B38: Moriba | C38: 45922 | D38: 5284286 | E38: =IF(B38="","",IFERROR( IF( (VLOOKUP(B38,K:N,3,FALSE)) < C38, "X", "" ), "X") ) -> X | O38: =IF(ISBLANK(N38),"",VLOOKUP(K38,B:D,3,FALSE)) | P38: =IF(ISBLANK(N38),"",N38-O38)
A39: MED | B39: Pathé Ciss | C39: 45922 | D39: 11000010 | E39: =IF(B39="","",IFERROR( IF( (VLOOKUP(B39,K:N,3,FALSE)) < C39, "X", "" ), "X") ) | O39: =IF(ISBLANK(N39),"",VLOOKUP(K39,B:D,3,FALSE)) | P39: =IF(ISBLANK(N39),"",N39-O39)
A40: DEL | B40: Bryan Gil | C40: 45926 | D40: 16680850 | E40: =IF(B40="","",IFERROR( IF( (VLOOKUP(B40,K:N,3,FALSE)) < C40, "X", "" ), "X") ) -> X | O40: =IF(ISBLANK(N40),"",VLOOKUP(K40,B:D,3,FALSE)) | P40: =IF(ISBLANK(N40),"",N40-O40)
A41: DEL | B41: Rodrygo | C41: 45926 | D41: 16680750 | E41: =IF(B41="","",IFERROR( IF( (VLOOKUP(B41,K:N,3,FALSE)) < C41, "X", "" ), "X") ) -> X | O41: =IF(ISBLANK(N41),"",VLOOKUP(K41,B:D,3,FALSE)) | P41: =IF(ISBLANK(N41),"",N41-O41)
A42: DEF | B42: Lenglet | C42: 45928 | D42: 10185880 | E42: =IF(B42="","",IFERROR( IF( (VLOOKUP(B42,K:N,3,FALSE)) < C42, "X", "" ), "X") ) -> X | O42: =IF(ISBLANK(N42),"",VLOOKUP(K42,B:D,3,FALSE)) | P42: =IF(ISBLANK(N42),"",N42-O42)
A43: POR | B43: Radu | C43: 45928 | D43: 12668085 | E43: =IF(B43="","",IFERROR( IF( (VLOOKUP(B43,K:N,3,FALSE)) < C43, "X", "" ), "X") ) | O43: =IF(ISBLANK(N43),"",VLOOKUP(K43,B:D,3,FALSE)) | P43: =IF(ISBLANK(N43),"",N43-O43)
A44: DEL | B44: Morales | C44: 45942 | D44: 8396857 | E44: =IF(B44="","",IFERROR( IF( (VLOOKUP(B44,K:N,3,FALSE)) < C44, "X", "" ), "X") ) -> X | O44: =IF(ISBLANK(N44),"",VLOOKUP(K44,B:D,3,FALSE)) | P44: =IF(ISBLANK(N44),"",N44-O44)
A45: DEL | B45: Mastantuono | C45: 45942 | D45: 53968850 | E45: =IF(B45="","",IFERROR( IF( (VLOOKUP(B45,K:N,3,FALSE)) < C45, "X", "" ), "X") ) -> X | O45: =IF(ISBLANK(N45),"",VLOOKUP(K45,B:D,3,FALSE)) | P45: =IF(ISBLANK(N45),"",N45-O45)
A46: MED | B46: Sow | C46: 45944 | D46: 2213460 | E46: =IF(B46="","",IFERROR( IF( (VLOOKUP(B46,K:N,3,FALSE)) < C46, "X", "" ), "X") ) | O46: =IF(ISBLANK(N46),"",VLOOKUP(K46,B:D,3,FALSE)) | P46: =IF(ISBLANK(N46),"",N46-O46)
A47: MED | B47: Hugo Álvarez | C47: 45944 | D47: 6700000 | E47: =IF(B47="","",IFERROR( IF( (VLOOKUP(B47,K:N,3,FALSE)) < C47, "X", "" ), "X") ) -> X | O47: =IF(ISBLANK(N47),"",VLOOKUP(K47,B:D,3,FALSE)) | P47: =IF(ISBLANK(N47),"",N47-O47)
A48: MED | B48: Edu Expósito | C48: 45944 | D48: 22875987 | E48: =IF(B48="","",IFERROR( IF( (VLOOKUP(B48,K:N,3,FALSE)) < C48, "X", "" ), "X") ) | O48: =IF(ISBLANK(N48),"",VLOOKUP(K48,B:D,3,FALSE)) | P48: =IF(ISBLANK(N48),"",N48-O48)
A49: DEL | B49: Mikautadze | C49: 45944 | D49: 45100000
A50: DEF | B50: Laporte | C50: 45944 | D50: 35533525
A51: DEF | B51: Iglesias | C51: 45960 | D51: 2369904
A52: DEL | B52: Dolan | C52: 45960 | D52: 8465783
A53: POR | B53: Ryan | C53: 45960 | D53: 10000000
A54: DEF | B54: M. Alonso | C54: 45960 | D54: 18644883
A55: DEF | B55: Ratiu | C55: 45960 | D55: 28741587
A56: MED | B56: Valentín | C56: 45967 | D56: 5689088
A57: MED | B57: Thomas | C57: 45971 | D57: 4668380

Sheet davidcdl10
A1: Indice | B1: davidcdl10
A2: Fichajes | K2: Ventas
A3: Posicion | B3: Jugador | C3: Fecha Compra | D3: Precio Compra | E3: Plantilla | K3: Posicion | L3: Jugador | N3: Fecha Venta | O3: Precio Venta | P3: Precio Compra | Q3: Rentabilidad | R3: Rentabilidad Fichajes
A4: {=_xlfn._xlws.FILTER(Fichajes!C:C,Fichajes!G:G=B1)} -> MED | B4: {=_xlfn._xlws.FILTER(Fichajes!B:B,Fichajes!G:G=B1)} -> Almeida | C4: {=_xlfn._xlws.FILTER(Fichajes!F:F,Fichajes!$G:$G=$B1)} -> 45872 | D4: {=_xlfn._xlws.FILTER(Fichajes!I:I,Fichajes!$G:$G=$B1)} -> 0 | E4: =IF(B4="","",IFERROR( IF( (VLOOKUP(B4,K:O,3,FALSE)) < C4, "X", "" ), "X") ) | K4: {=_xlfn._xlws.FILTER(Fichajes!B:B,Fichajes!$H:$H=B$1)} -> Almeida | L4: {=_xlfn._xlws.FILTER(Fichajes!C:C,Fichajes!$H:$H=B$1)} -> MED | M4: {=_xlfn._xlws.FILTER(Fichajes!G:G,Fichajes!$H:$H=B$1)} -> Liga | N4: {=_xlfn._xlws.FILTER(Fichajes!F:F,Fichajes!$H:$H=B$1)} -> 45873 | O4: {=_xlfn._xlws.FILTER(Fichajes!I:I,Fichajes!$H:$H=B$1)} -> 8942183 | P4: =IF(ISBLANK(O4),"",VLOOKUP(K4,B:D,3,FALSE)) -> 0 | Q4: =IF(ISBLANK(O4),"",O4-P4) -> 8942183 | R4: =IF(P4=0,0,Q4) -> 0
A5: DEF | B5: Bade | C5: 45872 | D5: 0 | E5: =IF(B5="","",IFERROR( IF( (VLOOKUP(B5,K:O,3,FALSE)) < C5, "X", "" ), "X") ) | K5: Parejo | L5: MED | M5: Liga | N5: 45873 | O5: 16272690 | P5: =IF(ISBLANK(O5),"",VLOOKUP(K5,B:D,3,FALSE)) -> 0 | Q5: =IF(ISBLANK(O5),"",O5-P5) -> 16272690 | R5: =IF(P5=0,0,Q5) -> 0
A6: DEF | B6: Boyomo | C6: 45872 | D6: 0 | E6: =IF(B6="","",IFERROR( IF( (VLOOKUP(B6,K:O,3,FALSE)) < C6, "X", "" ), "X") ) | K6: Bade | L6: DEF | M6: Liga | N6: 45885 | O6: 11998476 | P6: =IF(ISBLANK(O6),"",VLOOKUP(K6,B:D,3,FALSE)) -> 0 | Q6: =IF(ISBLANK(O6),"",O6-P6) -> 11998476 | R6: =IF(P6=0,0,Q6) -> 0
A7: DEL | B7: De Frutos | C7: 45872 | D7: 0 | E7: =IF(B7="","",IFERROR( IF( (VLOOKUP(B7,K:O,3,FALSE)) < C7, "X", "" ), "X") ) | K7: De Frutos | L7: DEL | M7: Desteban19 | N7: 45886 | O7: 13861683 | P7: =IF(ISBLANK(O7),"",VLOOKUP(K7,B:D,3,FALSE)) -> 0 | Q7: =IF(ISBLANK(O7),"",O7-P7) -> 13861683 | R7: =IF(P7=0,0,Q7) -> 0
A8: DEF | B8: De la Fuente | C8: 45872 | D8: 0 | E8: =IF(B8="","",IFERROR( IF( (VLOOKUP(B8,K:O,3,FALSE)) < C8, "X", "" ), "X") ) | K8: Dmitrovic | L8: POR | M8: FC Recreativo de Juerga | N8: 45887 | O8: 11146825 | P8: =IF(ISBLANK(O8),"",VLOOKUP(K8,B:D,3,FALSE)) -> 0 | Q8: =IF(ISBLANK(O8),"",O8-P8) -> 11146825 | R8: =IF(P8=0,0,Q8) -> 0
A9: POR | B9: Dmitrovic | C9: 45872 | D9: 0 | E9: =IF(B9="","",IFERROR( IF( (VLOOKUP(B9,K:O,3,FALSE)) < C9, "X", "" ), "X") ) | K9: Boyomo | L9: DEF | M9: Desteban19 | N9: 45889 | O9: 14947178 | P9: =IF(ISBLANK(O9),"",VLOOKUP(K9,B:D,3,FALSE)) -> 0 | Q9: =IF(ISBLANK(O9),"",O9-P9) -> 14947178 | R9: =IF(P9=0,0,Q9) -> 0
A10: MED | B10: Fornals | C10: 45872 | D10: 0 | E10: =IF(B10="","",IFERROR( IF( (VLOOKUP(B10,K:O,3,FALSE)) < C10, "X", "" ), "X") ) | K10: Herrera | L10: MED | M10: Liga | N10: 45889 | O10: 11992446 | P10: =IF(ISBLANK(O10),"",VLOOKUP(K10,B:D,3,FALSE)) -> 0 | Q10: =IF(ISBLANK(O10),"",O10-P10) -> 11992446 | R10: =IF(P10=0,0,Q10) -> 0
A11: MED | B11: Herrera | C11: 45872 | D11: 0 | E11: =IF(B11="","",IFERROR( IF( (VLOOKUP(B11,K:O,3,FALSE)) < C11, "X", "" ), "X") ) | K11: A. F. Carreras | L11: DEF | M11: Desteban19 | N11: 45895 | O11: 50000000 | P11: =IF(ISBLANK(O11),"",VLOOKUP(K11,B:D,3,FALSE)) -> 38000000 | Q11: =IF(ISBLANK(O11),"",O11-P11) -> 12000000 | R11: =IF(P11=0,0,Q11) -> 12000000
A12: DEL | B12: Isi | C12: 45872 | D12: 0 | E12: =IF(B12="","",IFERROR( IF( (VLOOKUP(B12,K:O,3,FALSE)) < C12, "X", "" ), "X") ) | K12: De la Fuente | L12: DEF | M12: Reivaj95 | N12: 45896 | O12: 1130330 | P12: =IF(ISBLANK(O12),"",VLOOKUP(K12,B:D,3,FALSE)) -> 0 | Q12: =IF(ISBLANK(O12),"",O12-P12) -> 1130330 | R12: =IF(P12=0,0,Q12) -> 0
A13: DEL | B13: Kike García | C13: 45872 | D13: 0 | E13: =IF(B13="","",IFERROR( IF( (VLOOKUP(B13,K:O,3,FALSE)) < C13, "X", "" ), "X") ) | K13: Fornals | L13: MED | M13: JMGuti14 | N13: 45897 | O13: 28680456 | P13: =IF(ISBLANK(O13),"",VLOOKUP(K13,B:D,3,FALSE)) -> 0 | Q13: =IF(ISBLANK(O13),"",O13-P13) -> 28680456 | R13: =IF(P13=0,0,Q13) -> 0
A14: DEF | B14: Natan | C14: 45872 | D14: 0 | E14: =IF(B14="","",IFERROR( IF( (VLOOKUP(B14,K:O,3,FALSE)) < C14, "X", "" ), "X") ) | K14: Kike García | L14: DEL | M14: Liga | N14: 45897 | O14: 6026468 | P14: =IF(ISBLANK(O14),"",VLOOKUP(K14,B:D,3,FALSE)) -> 0 | Q14: =IF(ISBLANK(O14),"",O14-P14) -> 6026468 | R14: =IF(P14=0,0,Q14) -> 0
A15: MED | B15: Parejo | C15: 45872 | D15: 0 | E15: =IF(B15="","",IFERROR( IF( (VLOOKUP(B15,K:O,3,FALSE)) < C15, "X", "" ), "X") ) | K15: Areso | L15: DEF | M15: JMGuti14 | N15: 45898 | O15: 15500000 | P15: =IF(ISBLANK(O15),"",VLOOKUP(K15,B:D,3,FALSE)) -> 15500000 | Q15: =IF(ISBLANK(O15),"",O15-P15) -> 0 | R15: =IF(P15=0,0,Q15) -> 0
A16: DEL | B16: Yeremy Pino | C16: 45872 | D16: 0 | E16: =IF(B16="","",IFERROR( IF( (VLOOKUP(B16,K:O,3,FALSE)) < C16, "X", "" ), "X") ) | K16: Garcés | L16: DEF | M16: FC Recreativo de Juerga | N16: 45901 | O16: 1705015 | P16: =IF(ISBLANK(O16),"",VLOOKUP(K16,B:D,3,FALSE)) -> 1011015 | Q16: =IF(ISBLANK(O16),"",O16-P16) -> 694000 | R16: =IF(P16=0,0,Q16) -> 694000
... A48: MED | B48: Luis Milla | C48: 45916 | D48: 40232141 | E48: =IF(B48="","",IFERROR( IF( (VLOOKUP(B48,K:O,3,FALSE)) < C48, "X", "" ), "X") ) | K48: Bretones | L48: DEF | M48: AdolfitoFlick | N48: 45951 | O48: 3373737 | P48: =IF(ISBLANK(O48),"",VLOOKUP(K48,B:D,3,FALSE)) -> 3373737 | Q48: =IF(ISBLANK(O48),"",O48-P48) -> 0 | R48: =IF(P48=0,0,Q48) -> 0
A49: MED | B49: Fornals | C49: 45917 | D49: 33880456 | E49: =IF(B49="","",IFERROR( IF( (VLOOKUP(B49,K:O,3,FALSE)) < C49, "X", "" ), "X") ) | K49: Pep Chavarría | L49: DEF | M49: JMGuti14 | N49: 45952 | O49: 14035574
A50: DEL | B50: Dolan | C50: 45922 | D50: 5100000 | E50: =IF(B50="","",IFERROR( IF( (VLOOKUP(B50,K:O,3,FALSE)) < C50, "X", "" ), "X") ) | K50: Alexis | L50: DEL | M50: Liga | N50: 45957 | O50: 8373185
A51: DEF | B51: Pep Chavarría | C51: 45924 | D51: 5100010 | K51: M. Llorente | L51: DEF | M51: Desteban19 | N51: 45959 | O51: 70081501
A52: DEL | B52: Mastantuono | C52: 45925 | D52: 41978791 | K52: Etta Eyong | L52: DEL | M52: Desteban19 | N52: 45959 | O52: 110031134
A53: MED | B53: Hugo Álvarez | C53: 45926 | D53: 6700000 | K53: Ryan | L53: POR | M53: Shiquetito 9 | N53: 45960 | O53: 10000000
A54: MED | B54: Sow | C54: 45926 | D54: 2213460 | K54: Jauregizar | L54: MED | M54: yandrak | N54: 45966 | O54: 29725093
A55: DEF | B55: Abqar | C55: 45929 | D55: 18100000 | K55: Danjuma | L55: DEL | M55: AdolfitoFlick | N55: 45972 | O55: 27500000
A56: DEF | B56: Sergio Gómez | C56: 45929 | D56: 5829874
A57: DEF | B57: Suazo | C57: 45929 | D57: 8975124
A58: MED | B58: Güler | C58: 45931 | D58: 122854925
A59: POR | B59: Ryan | C59: 45934 | D59: 10000000
A60: DEF | B60: Rincón | C60: 45934 | D60: 3500000
A61: DEF | B61: Bretones | C61: 45934 | D61: 3373737
A62: DEF | B62: M. Llorente | C62: 45935 | D62: 48000000
A63: MED | B63: Morlanes | C63: 45944 | D63: 1610010
A64: DEL | B64: Alexis | C64: 45944 | D64: 20677441
A65: MED | B65: Urko | C65: 45944 | D65: 1427461
A66: DEL | B66: Etta Eyong | C66: 45945 | D66: 110031134
A67: MED | B67: Jauregizar | C67: 45949 | D67: 24476604
... A74: MED | B74: Sow | C74: 45960 | D74: 2213460

Sheet JMGuti14
A1: Indice | B1: JMGuti14
A2: Fichajes | K2: Ventas
A3: Posicion | B3: Jugador | C3: Fecha Compra | D3: Precio Compra | E3: Plantilla | K3: Posicion | L3: Jugador | M3: Fecha Venta | N3: Precio Venta | O3: Precio Compra | P3: Rentabilidad
A4: {=_xlfn._xlws.FILTER(Fichajes!C:C,Fichajes!G:G=B1)} -> MED | B4: {=_xlfn._xlws.FILTER(Fichajes!B:B,Fichajes!G:G=B1)} -> Arambarri | C4: {=_xlfn._xlws.FILTER(Fichajes!F:F,Fichajes!$G:$G=$B1)} -> 45872 | D4: {=_xlfn._xlws.FILTER(Fichajes!I:I,Fichajes!$G:$G=$B1)} -> 0 | E4: =IF(B4="","",IFERROR( IF( (VLOOKUP(B4,K:N,3,FALSE)) < C4, "X", "" ), "X") ) | K4: {=_xlfn._xlws.FILTER(Fichajes!B:B,Fichajes!$H:$H=B$1)} -> Mendy | L4: {=_xlfn._xlws.FILTER(Fichajes!C:C,Fichajes!$H:$H=B$1)} -> DEF | M4: {=_xlfn._xlws.FILTER(Fichajes!F:F,Fichajes!$H:$H=B$1)} -> 45874 | N4: {=_xlfn._xlws.FILTER(Fichajes!I:I,Fichajes!$H:$H=B$1)} -> 10606370 | O4: =IF(ISBLANK(N4),"",VLOOKUP(K4,B:D,3,FALSE)) -> 0 | P4: =IF(ISBLANK(N4),"",N4-O4) -> 10606370
A5: MED | B5: Camavinga | C5: 45872 | D5: 0 | E5: =IF(B5="","",IFERROR( IF( (VLOOKUP(B5,K:N,3,FALSE)) < C5, "X", "" ), "X") ) | K5: Arambarri | L5: MED | M5: 45877 | N5: 12000000 | O5: =IF(ISBLANK(N5),"",VLOOKUP(K5,B:D,3,FALSE)) -> 0 | P5: =IF(ISBLANK(N5),"",N5-O5) -> 12000000
A6: DEL | B6: Camello | C6: 45872 | D6: 0 | E6: =IF(B6="","",IFERROR( IF( (VLOOKUP(B6,K:N,3,FALSE)) < C6, "X", "" ), "X") ) | K6: Trejo | L6: MED | M6: 45877 | N6: 5811350 | O6: =IF(ISBLANK(N6),"",VLOOKUP(K6,B:D,3,FALSE)) -> 0 | P6: =IF(ISBLANK(N6),"",N6-O6) -> 5811350
A7: MED | B7: Guevara | C7: 45872 | D7: 0 | E7: =IF(B7="","",IFERROR( IF( (VLOOKUP(B7,K:N,3,FALSE)) < C7, "X", "" ), "X") ) | K7: Camavinga | L7: MED | M7: 45881 | N7: 20024014 | O7: =IF(ISBLANK(N7),"",VLOOKUP(K7,B:D,3,FALSE)) -> 0 | P7: =IF(ISBLANK(N7),"",N7-O7) -> 20024014
A8: DEL | B8: Duro | C8: 45872 | D8: 0 | E8: =IF(B8="","",IFERROR( IF( (VLOOKUP(B8,K:N,3,FALSE)) < C8, "X", "" ), "X") ) | K8: Guevara | L8: MED | M8: 45883 | N8: 3374524 | O8: =IF(ISBLANK(N8),"",VLOOKUP(K8,B:D,3,FALSE)) -> 0 | P8: =IF(ISBLANK(N8),"",N8-O8) -> 3374524
A9: POR | B9: Luiz Junior | C9: 45872 | D9: 0 | E9: =IF(B9="","",IFERROR( IF( (VLOOKUP(B9,K:N,3,FALSE)) < C9, "X", "" ), "X") ) | K9: Sow | L9: MED | M9: 45883 | N9: 3744184 | O9: =IF(ISBLANK(N9),"",VLOOKUP(K9,B:D,3,FALSE)) -> 0 | P9: =IF(ISBLANK(N9),"",N9-O9) -> 3744184
A10: DEF | B10: Lejeune | C10: 45872 | D10: 0 | E10: =IF(B10="","",IFERROR( IF( (VLOOKUP(B10,K:N,3,FALSE)) < C10, "X", "" ), "X") ) | K10: Luiz Junior | L10: POR | M10: 45886 | N10: 9184563 | O10: =IF(ISBLANK(N10),"",VLOOKUP(K10,B:D,3,FALSE)) -> 0 | P10: =IF(ISBLANK(N10),"",N10-O10) -> 9184563
A11: DEF | B11: Marcão | C11: 45872 | D11: 0 | E11: =IF(B11="","",IFERROR( IF( (VLOOKUP(B11,K:N,3,FALSE)) < C11, "X", "" ), "X") ) | K11: Camello | L11: DEL | M11: 45887 | N11: 3814911 | O11: =IF(ISBLANK(N11),"",VLOOKUP(K11,B:D,3,FALSE)) -> 0 | P11: =IF(ISBLANK(N11),"",N11-O11) -> 3814911
A12: DEF | B12: Mendy | C12: 45872 | D12: 0 | E12: =IF(B12="","",IFERROR( IF( (VLOOKUP(B12,K:N,3,FALSE)) < C12, "X", "" ), "X") ) | K12: Moldovan | L12: POR | M12: 45892 | N12: 1594158 | O12: =IF(ISBLANK(N12),"",VLOOKUP(K12,B:D,3,FALSE)) -> 1780021 | P12: =IF(ISBLANK(N12),"",N12-O12) -> -185863
A13: DEF | B13: Mingueza | C13: 45872 | D13: 0 | E13: =IF(B13="","",IFERROR( IF( (VLOOKUP(B13,K:N,3,FALSE)) < C13, "X", "" ), "X") ) | K13: Tchouaméni | L13: MED | M13: 45897 | N13: 51913530 | O13: =IF(ISBLANK(N13),"",VLOOKUP(K13,B:D,3,FALSE)) -> 41882338 | P13: =IF(ISBLANK(N13),"",N13-O13) -> 10031192
A14: DEL | B14: Oyarzabal | C14: 45872 | D14: 0 | E14: =IF(B14="","",IFERROR( IF( (VLOOKUP(B14,K:N,3,FALSE)) < C14, "X", "" ), "X") ) | K14: Mingueza | L14: DEF | M14: 45898 | N14: 26541798 | O14: =IF(ISBLANK(N14),"",VLOOKUP(K14,B:D,3,FALSE)) -> 0 | P14: =IF(ISBLANK(N14),"",N14-O14) -> 26541798
A15: MED | B15: Sow | C15: 45872 | D15: 0 | E15: =IF(B15="","",IFERROR( IF( (VLOOKUP(B15,K:N,3,FALSE)) < C15, "X", "" ), "X") ) | K15: Pablo García | L15: DEL | M15: 45903 | N15: 3735836 | O15: =IF(ISBLANK(N15),"",VLOOKUP(K15,B:D,3,FALSE)) -> 4021000 | P15: =IF(ISBLANK(N15),"",N15-O15) -> -285164
A16: MED | B16: Trejo | C16: 45872 | D16: 0 | E16: =IF(B16="","",IFERROR( IF( (VLOOKUP(B16,K:N,3,FALSE)) < C16, "X", "" ), "X") ) | K16: Lejeune | L16: DEF | M16: 45905 | N16: 16501453 | O16: =IF(ISBLANK(N16),"",VLOOKUP(K16,B:D,3,FALSE)) -> 0 | P16: =IF(ISBLANK(N16),"",N16-O16) -> 16501453
... A48: DEF | B48: Martín | C48: 45929 | D48: 16875421 | E48: =IF(B48="","",IFERROR( IF( (VLOOKUP(B48,K:N,3,FALSE)) < C48, "X", "" ), "X") ) | K48: Iglesias | L48: DEF | M48: 45960 | N48: 2369904 | O48: =IF(ISBLANK(N48),"",VLOOKUP(K48,B:D,3,FALSE)) -> 2369904 | P48: =IF(ISBLANK(N48),"",N48-O48) -> 0
A49: DEL | B49: Boyé | C49: 45931 | D49: 2506689 | E49: =IF(B49="","",IFERROR( IF( (VLOOKUP(B49,K:N,3,FALSE)) < C49, "X", "" ), "X") ) | K49: Dolan | L49: DEL | M49: 45960 | N49: 8465783
A50: MED | B50: Lemar | C50: 45931 | D50: 1764566 | E50: =IF(B50="","",IFERROR( IF( (VLOOKUP(B50,K:N,3,FALSE)) < C50, "X", "" ), "X") ) -> X
A51: MED | B51: Bernal | C51: 45931 | D51: 2324209
A52: MED | B52: Moleiro | C52: 45934 | D52: 20794268
A53: MED | B53: Sotelo | C53: 45937 | D53: 15000000
A54: DEF | B54: Maffeo | C54: 45938 | D54: 1532830
A55: DEL | B55: Dolan | C55: 45938 | D55: 6529830
A56: DEF | B56: Javi Rodríguez | C56: 45938 | D56: 1000000
A57: MED | B57: Pathé Ciss | C57: 45940 | D57: 11000010
A58: MED | B58: Román | C58: 45942 | D58: 406633
A59: DEF | B59: Iglesias | C59: 45945 | D59: 2369904
A60: MED | B60: Unai López | C60: 45952 | D60: 8785214
A61: MED | B61: Pedro Díaz | C61: 45952 | D61: 3201101
A62: DEL | B62: Durán | C62: 45952 | D62: 1600000
... A67: DEL | B67: Benito | C67: 45972 | D67: 520604

Sheet AdolfitoFlick
A1: Indice | B1: AdolfitoFlick
A2: Fichajes | K2: Ventas
A3: Posicion | B3: Jugador | C3: Fecha Compra | D3: Precio Compra | E3: Plantilla | K3: Posicion | L3: Jugador | M3: Fecha Venta | N3: Precio Venta | O3: Precio Compra | P3: Rentabilidad
A4: {=_xlfn._xlws.FILTER(Fichajes!C:C,Fichajes!G:G=B1)} -> MED | B4: {=_xlfn._xlws.FILTER(Fichajes!B:B,Fichajes!G:G=B1)} -> Oroz | C4: {=_xlfn._xlws.FILTER(Fichajes!F:F,Fichajes!$G:$G=$B1)} -> 45872 | D4: {=_xlfn._xlws.FILTER(Fichajes!I:I,Fichajes!$G:$G=$B1)} -> 0 | E4: =IF(B4="","",IFERROR( IF( (VLOOKUP(B4,K:N,3,FALSE)) < C4, "X", "" ), "X") ) | K4: {=_xlfn._xlws.FILTER(Fichajes!B:B,Fichajes!$H:$H=B$1)} -> Thierry | L4: {=_xlfn._xlws.FILTER(Fichajes!C:C,Fichajes!$H:$H=B$1)} -> DEF | M4: {=_xlfn._xlws.FILTER(Fichajes!F:F,Fichajes!$H:$H=B$1)} -> 45874 | N4: {=_xlfn._xlws.FILTER(Fichajes!I:I,Fichajes!$H:$H=B$1)} -> 7913098 | O4: =IF(ISBLANK(N4),"",VLOOKUP(K4,B:D,3,FALSE)) -> 0 | P4: =IF(ISBLANK(N4),"",N4-O4) -> 7913098
A5: DEF | B5: Á. Núñez | C5: 45872 | D5: 0 | E5: =IF(B5="","",IFERROR( IF( (VLOOKUP(B5,K:N,3,FALSE)) < C5, "X", "" ), "X") ) | K5: Juanlu | L5: MED | M5: 45877 | N5: 1250129 | O5: =IF(ISBLANK(N5),"",VLOOKUP(K5,B:D,3,FALSE)) -> 0 | P5: =IF(ISBLANK(N5),"",N5-O5) -> 1250129
A6: MED | B6: Comesaña | C6: 45872 | D6: 0 | E6: =IF(B6="","",IFERROR( IF( (VLOOKUP(B6,K:N,3,FALSE)) < C6, "X", "" ), "X") ) | K6: Olmo | L6: MED | M6: 45880 | N6: 57538379 | O6: =IF(ISBLANK(N6),"",VLOOKUP(K6,B:D,3,FALSE)) -> 53310169 | P6: =IF(ISBLANK(N6),"",N6-O6) -> 4228210
A7: DEF | B7: Thierry | C7: 45872 | D7: 0 | E7: =IF(B7="","",IFERROR( IF( (VLOOKUP(B7,K:N,3,FALSE)) < C7, "X", "" ), "X") ) | K7: Comesaña | L7: MED | M7: 45883 | N7: 6865726 | O7: =IF(ISBLANK(N7),"",VLOOKUP(K7,B:D,3,FALSE)) -> 0 | P7: =IF(ISBLANK(N7),"",N7-O7) -> 6865726
A8: DEF | B8: Blind | C8: 45872 | D8: 0 | E8: =IF(B8="","",IFERROR( IF( (VLOOKUP(B8,K:N,3,FALSE)) < C8, "X", "" ), "X") ) | K8: Pedraza | L8: DEF | M8: 45885 | N8: 4790298 | O8: =IF(ISBLANK(N8),"",VLOOKUP(K8,B:D,3,FALSE)) -> 0 | P8: =IF(ISBLANK(N8),"",N8-O8) -> 4790298
A9: MED | B9: Dani Rodríguez | C9: 45872 | D9: 0 | E9: =IF(B9="","",IFERROR( IF( (VLOOKUP(B9,K:N,3,FALSE)) < C9, "X", "" ), "X") ) | K9: Gerard | L9: DEL | M9: 45887 | N9: 19301382 | O9: =IF(ISBLANK(N9),"",VLOOKUP(K9,B:D,3,FALSE)) -> 0 | P9: =IF(ISBLANK(N9),"",N9-O9) -> 19301382
A10: MED | B10: Darder | C10: 45872 | D10: 0 | E10: =IF(B10="","",IFERROR( IF( (VLOOKUP(B10,K:N,3,FALSE)) < C10, "X", "" ), "X") ) | K10: Sivera | L10: POR | M10: 45888 | N10: 15904401 | O10: =IF(ISBLANK(N10),"",VLOOKUP(K10,B:D,3,FALSE)) -> 0 | P10: =IF(ISBLANK(N10),"",N10-O10) -> 15904401
A11: DEL | B11: Abde | C11: 45872 | D11: 0 | E11: =IF(B11="","",IFERROR( IF( (VLOOKUP(B11,K:N,3,FALSE)) < C11, "X", "" ), "X") ) | K11: Á. Núñez | L11: DEF | M11: 45889 | N11: 1749728 | O11: =IF(ISBLANK(N11),"",VLOOKUP(K11,B:D,3,FALSE)) -> 0 | P11: =IF(ISBLANK(N11),"",N11-O11) -> 1749728
A12: DEL | B12: Gerard | C12: 45872 | D12: 0 | E12: =IF(B12="","",IFERROR( IF( (VLOOKUP(B12,K:N,3,FALSE)) < C12, "X", "" ), "X") ) | K12: Balde | L12: DEF | M12: 45893 | N12: 68490133 | O12: =IF(ISBLANK(N12),"",VLOOKUP(K12,B:D,3,FALSE)) -> 64987987 | P12: =IF(ISBLANK(N12),"",N12-O12) -> 3502146
A13: DEL | B13: Guruzeta | C13: 45872 | D13: 0 | E13: =IF(B13="","",IFERROR( IF( (VLOOKUP(B13,K:N,3,FALSE)) < C13, "X", "" ), "X") ) | K13: Blind | L13: DEF | M13: 45895 | N13: 9506639 | O13: =IF(ISBLANK(N13),"",VLOOKUP(K13,B:D,3,FALSE)) -> 0 | P13: =IF(ISBLANK(N13),"",N13-O13) -> 9506639
A14: MED | B14: Iván Martín | C14: 45872 | D14: 0 | E14: =IF(B14="","",IFERROR( IF( (VLOOKUP(B14,K:N,3,FALSE)) < C14, "X", "" ), "X") ) | K14: Diakhaby | L14: DEF | M14: 45895 | N14: 3463499 | O14: =IF(ISBLANK(N14),"",VLOOKUP(K14,B:D,3,FALSE)) -> 4127854 | P14: =IF(ISBLANK(N14),"",N14-O14) -> -664355
A15: MED | B15: Juanlu | C15: 45872 | D15: 0 | E15: =IF(B15="","",IFERROR( IF( (VLOOKUP(B15,K:N,3,FALSE)) < C15, "X", "" ), "X") ) | K15: Dani Rodríguez | L15: MED | M15: 45896 | N15: 4585029 | O15: =IF(ISBLANK(N15),"",VLOOKUP(K15,B:D,3,FALSE)) -> 0 | P15: =IF(ISBLANK(N15),"",N15-O15) -> 4585029
A16: DEF | B16: Pedraza | C16: 45872 | D16: 0 | E16: =IF(B16="","",IFERROR( IF( (VLOOKUP(B16,K:N,3,FALSE)) < C16, "X", "" ), "X") ) | K16: Guruzeta | L16: DEL | M16: 45896 | N16: 8485556 | O16: =IF(ISBLANK(N16),"",VLOOKUP(K16,B:D,3,FALSE)) -> 0 | P16: =IF(ISBLANK(N16),"",N16-O16) -> 8485556
... A39: DEF | B39: Suazo | C39: 45905 | D39: 8975124 | E39: =IF(B39="","",IFERROR( IF( (VLOOKUP(B39,K:N,3,FALSE)) < C39, "X", "" ), "X") ) | K39: Martín | L39: DEF | M39: 45929 | N39: 16875421 | O39: =IF(ISBLANK(N39),"",VLOOKUP(K39,B:D,3,FALSE)) -> 16875421 | P39: =IF(ISBLANK(N39),"",N39-O39) -> 0
A40: MED | B40: Bernal | C40: 45908 | D40: 2313366 | K40: Suazo | L40: DEF | M40: 45929 | N40: 8975124 | O40: =IF(ISBLANK(N40),"",VLOOKUP(K40,B:D,3,FALSE)) -> 8975124 | P40: =IF(ISBLANK(N40),"",N40-O40) -> 0
A41: DEF | B41: Ratiu | C41: 45910 | D41: 21741587 | K41: Boyé | L41: DEL | M41: 45931 | N41: 2506689 | O41: =IF(ISBLANK(N41),"",VLOOKUP(K41,B:D,3,FALSE)) -> 2506689 | P41: =IF(ISBLANK(N41),"",N41-O41) -> 0
A42: DEF | B42: Martín | C42: 45911 | D42: 16875421 | K42: Dendoncker | L42: MED | M42: 45931 | N42: 8987987 | O42: =IF(ISBLANK(N42),"",VLOOKUP(K42,B:D,3,FALSE)) -> 8987987 | P42: =IF(ISBLANK(N42),"",N42-O42) -> 0
A43: DEL | B43: Boyé | C43: 45911 | D43: 2506689 | K43: Bernal | L43: MED | M43: 45931 | N43: 2324209 | O43: =IF(ISBLANK(N43),"",VLOOKUP(K43,B:D,3,FALSE)) -> 2313366 | P43: =IF(ISBLANK(N43),"",N43-O43) -> 10843
A44: MED | B44: Tchouaméni | C44: 45911 | D44: 56259306 | K44: Valles | L44: POR | M44: 45937 | N44: 8157372 | O44: =IF(ISBLANK(N44),"",VLOOKUP(K44,B:D,3,FALSE)) -> 17987875 | P44: =IF(ISBLANK(N44),"",N44-O44) -> -9830503
A45: DEL | B45: Etta Eyong | C45: 45914 | D45: 45041480 | K45: Vargas | L45: DEL | M45: 45937 | N45: 34085836 | O45: =IF(ISBLANK(N45),"",VLOOKUP(K45,B:D,3,FALSE)) -> 30085836 | P45: =IF(ISBLANK(N45),"",N45-O45) -> 4000000
A46: DEL | B46: Antony | C46: 45915 | D46: 105511535 | K46: Pere Milla | L46: DEL | M46: 45938 | N46: 10928095 | O46: =IF(ISBLANK(N46),"",VLOOKUP(K46,B:D,3,FALSE)) -> 10022080 | P46: =IF(ISBLANK(N46),"",N46-O46) -> 906015
A47: DEF | B47: Javi Rodríguez | C47: 45918 | D47: 1000000 | K47: Javi Rodríguez | L47: DEF | M47: 45938 | N47: 1000000 | O47: =IF(ISBLANK(N47),"",VLOOKUP(K47,B:D,3,FALSE)) -> 1000000 | P47: =IF(ISBLANK(N47),"",N47-O47) -> 0
A48: MED | B48: Denis Suárez | C48: 45919 | D48: 6958742 | K48: Denis Suárez | L48: MED | M48: 45942 | N48: 705614 | O48: =IF(ISBLANK(N48),"",VLOOKUP(K48,B:D,3,FALSE)) -> 6958742 | P48: =IF(ISBLANK(N48),"",N48-O48) -> -6253128
A49: MED | B49: Moncayola | C49: 45922 | D49: 12007810 | K49: Abde | L49: DEL | M49: 45945 | N49: 32239613
A50: DEL | B50: Pere Milla | C50: 45923 | D50: 10022080 | K50: Areso | L50: DEF | M50: 45945 | N50: 15500000
A51: POR | B51: Aarón | C51: 45924 | D51: 22874548 | K51: Ratiu | L51: DEF | M51: 45946 | N51: 21741587
A52: DEF | B52: Huijsen | C52: 45924 | D52: 86545402 | K52: Aarón | L52: POR | M52: 45952 | N52: 34874548
A53: DEL | B53: Yamal | C53: 45928 | D53: 156888888 | K53: Samú | L53: MED | M53: 45952 | N53: 7874521
A54: MED | B54: Valera | C54: 45929 | D54: 12098300 | K54: Unai López | L54: MED | M54: 45952 | N54: 8785214
A55: DEF | B55: Areso | C55: 45930 | D55: 15500000 | K55: Riedel | L55: DEF | M55: 45952 | N55: 18745874
A56: DEF | B56: Toljan | C56: 45930 | D56: 14047148 | K56: Danjuma | L56: DEL | M56: 45956 | N56: 23776645
A57: DEL | B57: Vargas | C57: 45923 | D57: 30085836 | K57: Moncayola | L57: MED | M57: 45959 | N57: 14007810
A58: MED | B58: Samú | C58: 45931 | D58: 3874521 | K58: Rubén G. | L58: MED | M58: 45960 | N58: 5875421
A59: MED | B59: Unai López | C59: 45936 | D59: 4785214 | K59: Cucho | L59: DEL | M59: 45964 | N59: 49503076
A60: DEF | B60: Riedel | C60: 45938 | D60: 8745874 | K60: Leo Román | L60: POR | M60: 45966 | N60: 6927389
... A69: MED | B69: Gudelj | C69: 45951 | D69: 1796111 | K69: Valera | L69: MED | M69: 45974 | N69: 16570802
A70: POR | B70: Radu | C70: 45952 | D70: 12668085
A71: DEF | B71: Tenaglia | C71: 45952 | D71: 30480521
A72: MED | B72: Navarro | C72: 45953 | D72: 4800000
A73: POR | B73: Leo Román | C73: 45957 | D73: 10875852
A74: DEF | B74: Djené | C74: 45960 | D74: 13987542
A75: MED | B75: C. Álvarez | C75: 45960 | D75: 26980873
A76: MED | B76: Oroz | C76: 45964 | D76: 3797764
A77: MED | B77: Almada | C77: 45965 | D77: 20000000
A78: MED | B78: Arriaga | C78: 45967 | D78: 6875412
A79: MED | B79: Moi Gómez | C79: 45968 | D79: 6875421
A80: MED | B80: González | C80: 45968 | D80: 26754123
A81: POR | B81: Soria | C81: 45969 | D81: 20874125
... A85: DEL | B85: Abde | C85: 45974 | D85: 43309964

Sheet Desteban19
A1: Indice | B1: Desteban19
A2: Fichajes | K2: Ventas
A3: Posicion | B3: Jugador | C3: Fecha Compra | D3: Precio Compra | E3: Plantilla | K3: Posicion | L3: Jugador | M3: Fecha Venta | N3: Precio Venta | O3: Precio Compra | P3: Rentabilidad
A4: {=_xlfn._xlws.FILTER(Fichajes!C:C,Fichajes!G:G=B1)} -> DEF | B4: {=_xlfn._xlws.FILTER(Fichajes!B:B,Fichajes!G:G=B1)} -> Bartra | C4: {=_xlfn._xlws.FILTER(Fichajes!F:F,Fichajes!$G:$G=$B1)} -> 45872 | D4: {=_xlfn._xlws.FILTER(Fichajes!I:I,Fichajes!$G:$G=$B1)} -> 0 | E4: =IF(B4="","",IFERROR( IF( (VLOOKUP(B4,K:N,3,FALSE)) < C4, "X", "" ), "X") ) | K4: {=_xlfn._xlws.FILTER(Fichajes!B:B,Fichajes!$H:$H=B$1)} -> Sergio Gómez | L4: {=_xlfn._xlws.FILTER(Fichajes!C:C,Fichajes!$H:$H=B$1)} -> DEF | M4: {=_xlfn._xlws.FILTER(Fichajes!F:F,Fichajes!$H:$H=B$1)} -> 45879 | N4: {=_xlfn._xlws.FILTER(Fichajes!I:I,Fichajes!$H:$H=B$1)} -> 14355279 | O4: =IF(ISBLANK(N4),"",VLOOKUP(K4,B:D,3,FALSE)) -> 0 | P4: =IF(ISBLANK(N4),"",N4-O4) -> 14355279
A5: MED | B5: Brais | C5: 45872 | D5: 0 | E5: =IF(B5="","",IFERROR( IF( (VLOOKUP(B5,K:N,3,FALSE)) < C5, "X", "" ), "X") ) | K5: Eric García | L5: DEF | M5: 45880 | N5: 12302286 | O5: =IF(ISBLANK(N5),"",VLOOKUP(K5,B:D,3,FALSE)) -> 0 | P5: =IF(ISBLANK(N5),"",N5-O5) -> 12302286
A6: DEF | B6: A. Christensen | C6: 45872 | D6: 0 | E6: =IF(B6="","",IFERROR( IF( (VLOOKUP(B6,K:N,3,FALSE)) < C6, "X", "" ), "X") ) | K6: A. Christensen | L6: DEF | M6: 45886 | N6: 9462162 | O6: =IF(ISBLANK(N6),"",VLOOKUP(K6,B:D,3,FALSE)) -> 0 | P6: =IF(ISBLANK(N6),"",N6-O6) -> 9462162
A7: MED | B7: R. de Galarreta | C7: 45872 | D7: 0 | E7: =IF(B7="","",IFERROR( IF( (VLOOKUP(B7,K:N,3,FALSE)) < C7, "X", "" ), "X") ) | K7: Fran García | L7: DEF | M7: 45886 | N7: 10803511 | O7: =IF(ISBLANK(N7),"",VLOOKUP(K7,B:D,3,FALSE)) -> 0 | P7: =IF(ISBLANK(N7),"",N7-O7) -> 10803511
A8: DEL | B8: Diego López | C8: 45872 | D8: 0 | E8: =IF(B8="","",IFERROR( IF( (VLOOKUP(B8,K:N,3,FALSE)) < C8, "X", "" ), "X") ) | K8: Koke | L8: MED | M8: 45886 | N8: 7972516 | O8: =IF(ISBLANK(N8),"",VLOOKUP(K8,B:D,3,FALSE)) -> 0 | P8: =IF(ISBLANK(N8),"",N8-O8) -> 7972516
A9: DEF | B9: Eric García | C9: 45872 | D9: 0 | E9: =IF(B9="","",IFERROR( IF( (VLOOKUP(B9,K:N,3,FALSE)) < C9, "X", "" ), "X") ) | K9: Nyland | L9: POR | M9: 45886 | N9: 6023207 | O9: =IF(ISBLANK(N9),"",VLOOKUP(K9,B:D,3,FALSE)) -> 0 | P9: =IF(ISBLANK(N9),"",N9-O9) -> 6023207
A10: DEL | B10: Ferran | C10: 45872 | D10: 0 | E10: =IF(B10="","",IFERROR( IF( (VLOOKUP(B10,K:N,3,FALSE)) < C10, "X", "" ), "X") ) | K10: Ferran | L10: DEL | M10: 45888 | N10: 31110758 | O10: =IF(ISBLANK(N10),"",VLOOKUP(K10,B:D,3,FALSE)) -> 0 | P10: =IF(ISBLANK(N10),"",N10-O10) -> 31110758
A11: DEF | B11: Fran García | C11: 45872 | D11: 0 | E11: =IF(B11="","",IFERROR( IF( (VLOOKUP(B11,K:N,3,FALSE)) < C11, "X", "" ), "X") ) | K11: Luis Milla | L11: MED | M11: 45888 | N11: 16095858 | O11: =IF(ISBLANK(N11),"",VLOOKUP(K11,B:D,3,FALSE)) -> 0 | P11: =IF(ISBLANK(N11),"",N11-O11) -> 16095858
A12: MED | B12: Koke | C12: 45872 | D12: 0 | E12: =IF(B12="","",IFERROR( IF( (VLOOKUP(B12,K:N,3,FALSE)) < C12, "X", "" ), "X") ) | K12: Bellerín | L12: DEF | M12: 45889 | N12: 3807248 | O12: =IF(ISBLANK(N12),"",VLOOKUP(K12,B:D,3,FALSE)) -> 5000000 | P12: =IF(ISBLANK(N12),"",N12-O12) -> -1192752
A13: MED | B13: Luis Milla | C13: 45872 | D13: 0 | E13: =IF(B13="","",IFERROR( IF( (VLOOKUP(B13,K:N,3,FALSE)) < C13, "X", "" ), "X") ) | K13: Brais | L13: MED | M13: 45889 | N13: 23947108 | O13: =IF(ISBLANK(N13),"",VLOOKUP(K13,B:D,3,FALSE)) -> 0 | P13: =IF(ISBLANK(N13),"",N13-O13) -> 23947108
A14: POR | B14: Nyland | C14: 45872 | D14: 0 | E14: =IF(B14="","",IFERROR( IF( (VLOOKUP(B14,K:N,3,FALSE)) < C14, "X", "" ), "X") ) | K14: Pepelu | L14: MED | M14: 45894 | N14: 13159584 | O14: =IF(ISBLANK(N14),"",VLOOKUP(K14,B:D,3,FALSE)) -> 0 | P14: =IF(ISBLANK(N14),"",N14-O14) -> 13159584
A15: MED | B15: Pepelu | C15: 45872 | D15: 0 | E15: =IF(B15="","",IFERROR( IF( (VLOOKUP(B15,K:N,3,FALSE)) < C15, "X", "" ), "X") ) | K15: Raphinha | L15: DEL | M15: 45894 | N15: 134340781 | O15: =IF(ISBLANK(N15),"",VLOOKUP(K15,B:D,3,FALSE)) -> 112301685 | P15: =IF(ISBLANK(N15),"",N15-O15) -> 22039096
A16: DEF | B16: Ristic | C16: 45872 | D16: 0 | E16: =IF(B16="","",IFERROR( IF( (VLOOKUP(B16,K:N,3,FALSE)) < C16, "X", "" ), "X") ) | K16: Aleñá | L16: MED | M16: 45895 | N16: 6100000 | O16: =IF(ISBLANK(N16),"",VLOOKUP(K16,B:D,3,FALSE)) -> 6100000 | P16: =IF(ISBLANK(N16),"",N16-O16) -> 0
... A48: DEL | B48: Pépé | C48: 45917 | D48: 68214570 | E48: =IF(B48="","",IFERROR( IF( (VLOOKUP(B48,K:N,3,FALSE)) < C48, "X", "" ), "X") ) | K48: Antony | L48: DEL | M48: 45936 | N48: 85961246 | O48: =IF(ISBLANK(N48),"",VLOOKUP(K48,B:D,3,FALSE)) -> 83626346 | P48: =IF(ISBLANK(N48),"",N48-O48) -> 2334900
A49: MED | B49: Urko | C49: 45920 | D49: 1427461 | E49: =IF(B49="","",IFERROR( IF( (VLOOKUP(B49,K:N,3,FALSE)) < C49, "X", "" ), "X") ) | K49: Iván Romero | L49: DEL | M49: 45941 | N49: 10073333
A50: MED | B50: Javi Guerra | C50: 45922 | D50: 33365531 | E50: =IF(B50="","",IFERROR( IF( (VLOOKUP(B50,K:N,3,FALSE)) < C50, "X", "" ), "X") ) | K50: Edu Expósito | L50: MED | M50: 45944 | N50: 22875987
A51: DEF | B51: Paredes | C51: 45922 | D51: 31497526 | E51: =IF(B51="","",IFERROR( IF( (VLOOKUP(B51,K:N,3,FALSE)) < C51, "X", "" ), "X") ) | K51: Urko | L51: MED | M51: 45944 | N51: 1427461
A52: DEL | B52: Alvarez | C52: 45923 | D52: 77951254 | E52: =IF(B52="","",IFERROR( IF( (VLOOKUP(B52,K:N,3,FALSE)) < C52, "X", "" ), "X") ) | K52: Víctor Muñoz | L52: DEL | M52: 45951 | N52: 13159467
A53: MED | B53: Pedro Díaz | C53: 45925 | D53: 3201101 | E53: =IF(B53="","",IFERROR( IF( (VLOOKUP(B53,K:N,3,FALSE)) < C53, "X", "" ), "X") ) | K53: Javi Guerra | L53: MED | M53: 45952 | N53: 18037449
A54: DEL | B54: Iván Romero | C54: 45927 | D54: 5987878 | E54: =IF(B54="","",IFERROR( IF( (VLOOKUP(B54,K:N,3,FALSE)) < C54, "X", "" ), "X") ) | K54: Pedro Díaz | L54: MED | M54: 45952 | N54: 3201101
A55: DEF | B55: Affengruber | C55: 45929 | D55: 31890001 | E55: =IF(B55="","",IFERROR( IF( (VLOOKUP(B55,K:N,3,FALSE)) < C55, "X", "" ), "X") ) -> X | K55: Valjent | L55: DEF | M55: 45952 | N55: 7108000
A56: MED | B56: Edu Expósito | C56: 45929 | D56: 22875987 | E56: =IF(B56="","",IFERROR( IF( (VLOOKUP(B56,K:N,3,FALSE)) < C56, "X", "" ), "X") ) | K56: Hancko | L56: DEF | M56: 45952 | N56: 20000000
A57: DEF | B57: Pubill | C57: 45930 | D57: 1478279 | E57: =IF(B57="","",IFERROR( IF( (VLOOKUP(B57,K:N,3,FALSE)) < C57, "X", "" ), "X") ) -> X | K57: Rashford | L57: DEL | M57: 45956 | N57: 91655316
A58: DEF | B58: Boyomo | C58: 45931 | D58: 26929228 | E58: =IF(B58="","",IFERROR( IF( (VLOOKUP(B58,K:N,3,FALSE)) < C58, "X", "" ), "X") ) -> X | K58: Femenia | L58: DEF | M58: 45958 | N58: 6501001
A59: DEL | B59: Alemão | C59: 45932 | D59: 5000000 | E59: =IF(B59="","",IFERROR( IF( (VLOOKUP(B59,K:N,3,FALSE)) < C59, "X", "" ), "X") ) | K59: Eric García | L59: DEF | M59: 45959 | N59: 46957357
A60: DEF | B60: Femenia | C60: 45932 | D60: 6501001 | E60: =IF(B60="","",IFERROR( IF( (VLOOKUP(B60,K:N,3,FALSE)) < C60, "X", "" ), "X") ) | K60: Bellingham | L60: MED | M60: 45959 | N60: 115026806
... A65: DEF | B65: Valjent | C65: 45937 | D65: 7108000 | E65: =IF(B65="","",IFERROR( IF( (VLOOKUP(B65,K:N,3,FALSE)) < C65, "X", "" ), "X") ) | K65: Almada | L65: MED | M65: 45965 | N65: 20000000
A66: MED | B66: Bellingham | C66: 45937 | D66: 81008927 | E66: =IF(B66="","",IFERROR( IF( (VLOOKUP(B66,K:N,3,FALSE)) < C66, "X", "" ), "X") )
A67: DEF | B67: Hancko | C67: 45938 | D67: 20000000 | E67: =IF(B67="","",IFERROR( IF( (VLOOKUP(B67,K:N,3,FALSE)) < C67, "X", "" ), "X") )
A68: MED | B68: Koke | C68: 45947 | D68: 13000000 | E68: =IF(B68="","",IFERROR( IF( (VLOOKUP(B68,K:N,3,FALSE)) < C68, "X", "" ), "X") ) -> X
A69: MED | B69: Almada | C69: 45951 | D69: 20000000 | E69: =IF(B69="","",IFERROR( IF( (VLOOKUP(B69,K:N,3,FALSE)) < C69, "X", "" ), "X") ) -> X
A70: DEF | B70: Riedel | C70: 45952 | D70: 18745874 | E70: =IF(B70="","",IFERROR( IF( (VLOOKUP(B70,K:N,3,FALSE)) < C70, "X", "" ), "X") ) -> X
A71: MED | B71: Febas | C71: 45953 | D71: 23210100 | E71: =IF(B71="","",IFERROR( IF( (VLOOKUP(B71,K:N,3,FALSE)) < C71, "X", "" ), "X") ) -> X
A72: MED | B72: Baena | C72: 45956 | D72: 77310010 | E72: =IF(B72="","",IFERROR( IF( (VLOOKUP(B72,K:N,3,FALSE)) < C72, "X", "" ), "X") ) -> X
A73: DEF | B73: M. Llorente | C73: 45959 | D73: 70081501 | E73: =IF(B73="","",IFERROR( IF( (VLOOKUP(B73,K:N,3,FALSE)) < C73, "X", "" ), "X") ) -> X
A74: DEL | B74: Etta Eyong | C74: 45959 | D74: 110031134 | E74: =IF(B74="","",IFERROR( IF( (VLOOKUP(B74,K:N,3,FALSE)) < C74, "X", "" ), "X") ) -> X
A75: DEL | B75: De Frutos | C75: 45959 | D75: 55082664 | E75: =IF(B75="","",IFERROR( IF( (VLOOKUP(B75,K:N,3,FALSE)) < C75, "X", "" ), "X") ) -> X
A76: DEF | B76: Vivian | C76: 45959 | D76: 39200833 | E76: =IF(B76="","",IFERROR( IF( (VLOOKUP(B76,K:N,3,FALSE)) < C76, "X", "" ), "X") ) -> X
A77: MED | B77: Fermín | C77: 45964 | D77: 55222222 | E77: =IF(B77="","",IFERROR( IF( (VLOOKUP(B77,K:N,3,FALSE)) < C77, "X", "" ), "X") ) -> X
... A81: MED | B81: Samú | C81: 45970 | D81: 7874521 | E81: =IF(B81="","",IFERROR( IF( (VLOOKUP(B81,K:N,3,FALSE)) < C81, "X", "" ), "X") ) -> X
E82: =IF(B82="","",IFERROR( IF( (VLOOKUP(B82,K:N,3,FALSE)) < C82, "X", "" ), "X") )
E83: =IF(B83="","",IFERROR( IF( (VLOOKUP(B83,K:N,3,FALSE)) < C83, "X", "" ), "X") )
E84: =IF(B84="","",IFERROR( IF( (VLOOKUP(B84,K:N,3,FALSE)) < C84, "X", "" ), "X") )
E85: =IF(B85="","",IFERROR( IF( (VLOOKUP(B85,K:N,3,FALSE)) < C85, "X", "" ), "X") )
E86: =IF(B86="","",IFERROR( IF( (VLOOKUP(B86,K:N,3,FALSE)) < C86, "X", "" ), "X") )
E87: =IF(B87="","",IFERROR( IF( (VLOOKUP(B87,K:N,3,FALSE)) < C87, "X", "" ), "X") )
E88: =IF(B88="","",IFERROR( IF( (VLOOKUP(B88,K:N,3,FALSE)) < C88, "X", "" ), "X") )
E89: =IF(B89="","",IFERROR( IF( (VLOOKUP(B89,K:N,3,FALSE)) < C89, "X", "" ), "X") )
E90: =IF(B90="","",IFERROR( IF( (VLOOKUP(B90,K:N,3,FALSE)) < C90, "X", "" ), "X") )
E91: =IF(B91="","",IFERROR( IF( (VLOOKUP(B91,K:N,3,FALSE)) < C91, "X", "" ), "X") )
E92: =IF(B92="","",IFERROR( IF( (VLOOKUP(B92,K:N,3,FALSE)) < C92, "X", "" ), "X") )
E93: =IF(B93="","",IFERROR( IF( (VLOOKUP(B93,K:N,3,FALSE)) < C93, "X", "" ), "X") )
... E250: =IF(B250="","",IFERROR( IF( (VLOOKUP(B250,K:N,3,FALSE)) < C250, "X", "" ), "X") )

Sheet FC Capitan
A1: Indice | B1: FC Capitan
A2: Fichajes | K2: Ventas
A3: Posicion | B3: Jugador | C3: Fecha Compra | D3: Precio Compra | E3: Plantilla | K3: Posicion | L3: Jugador | M3: Fecha Venta | N3: Precio Venta | O3: Precio Compra | P3: Rentabilidad
A4: {=_xlfn._xlws.FILTER(Fichajes!C:C,Fichajes!G:G=B1)} -> DEF | B4: {=_xlfn._xlws.FILTER(Fichajes!B:B,Fichajes!G:G=B1)} -> Araújo | C4: {=_xlfn._xlws.FILTER(Fichajes!F:F,Fichajes!$G:$G=$B1)} -> 45872 | D4: {=_xlfn._xlws.FILTER(Fichajes!I:I,Fichajes!$G:$G=$B1)} -> 0 | E4: =IF(B4="","",IFERROR( IF( (VLOOKUP(B4,K:N,3,FALSE)) < C4, "X", "" ), "X") ) | K4: {=_xlfn._xlws.FILTER(Fichajes!B:B,Fichajes!$H:$H=B$1)} -> Rüdiger | L4: {=_xlfn._xlws.FILTER(Fichajes!C:C,Fichajes!$H:$H=B$1)} -> DEF | M4: {=_xlfn._xlws.FILTER(Fichajes!F:F,Fichajes!$H:$H=B$1)} -> 45873 | N4: {=_xlfn._xlws.FILTER(Fichajes!I:I,Fichajes!$H:$H=B$1)} -> 27421205 | O4: =IF(ISBLANK(N4),"",VLOOKUP(K4,B:D,3,FALSE)) -> 0 | P4: =IF(ISBLANK(N4),"",N4-O4) -> 27421205
A5: DEL | B5: Asprilla | C5: 45872 | D5: 0 | E5: =IF(B5="","",IFERROR( IF( (VLOOKUP(B5,K:N,3,FALSE)) < C5, "X", "" ), "X") ) | K5: Casadó | L5: MED | M5: 45875 | N5: 11013284 | O5: =IF(ISBLANK(N5),"",VLOOKUP(K5,B:D,3,FALSE)) -> 0 | P5: =IF(ISBLANK(N5),"",N5-O5) -> 11013284
A6: MED | B6: Casadó | C6: 45872 | D6: 0 | E6: =IF(B6="","",IFERROR( IF( (VLOOKUP(B6,K:N,3,FALSE)) < C6, "X", "" ), "X") ) | K6: Miguel | L6: DEF | M6: 45875 | N6: 11013284 | O6: =IF(ISBLANK(N6),"",VLOOKUP(K6,B:D,3,FALSE)) -> 0 | P6: =IF(ISBLANK(N6),"",N6-O6) -> 11013284
A7: DEL | B7: Chimy | C7: 45872 | D7: 0 | E7: =IF(B7="","",IFERROR( IF( (VLOOKUP(B7,K:N,3,FALSE)) < C7, "X", "" ), "X") ) | K7: Araújo | L7: DEF | M7: 45877 | N7: 18411107 | O7: =IF(ISBLANK(N7),"",VLOOKUP(K7,B:D,3,FALSE)) -> 0 | P7: =IF(ISBLANK(N7),"",N7-O7) -> 18411107
A8: MED | B8: Beltrán | C8: 45872 | D8: 0 | E8: =IF(B8="","",IFERROR( IF( (VLOOKUP(B8,K:N,3,FALSE)) < C8, "X", "" ), "X") ) | K8: Zakharyan | L8: MED | M8: 45877 | N8: 4959924 | O8: =IF(ISBLANK(N8),"",VLOOKUP(K8,B:D,3,FALSE)) -> 0 | P8: =IF(ISBLANK(N8),"",N8-O8) -> 4959924
A9: DEF | B9: Giménez | C9: 45872 | D9: 0 | E9: =IF(B9="","",IFERROR( IF( (VLOOKUP(B9,K:N,3,FALSE)) < C9, "X", "" ), "X") ) | K9: Giménez | L9: DEF | M9: 45878 | N9: 10886133 | O9: =IF(ISBLANK(N9),"",VLOOKUP(K9,B:D,3,FALSE)) -> 0 | P9: =IF(ISBLANK(N9),"",N9-O9) -> 10886133
A10: POR | B10: Lunin | C10: 45872 | D10: 0 | E10: =IF(B10="","",IFERROR( IF( (VLOOKUP(B10,K:N,3,FALSE)) < C10, "X", "" ), "X") ) | K10: Lunin | L10: POR | M10: 45878 | N10: 5280074 | O10: =IF(ISBLANK(N10),"",VLOOKUP(K10,B:D,3,FALSE)) -> 0 | P10: =IF(ISBLANK(N10),"",N10-O10) -> 5280074
A11: MED | B11: Marc Roca | C11: 45872 | D11: 0 | E11: =IF(B11="","",IFERROR( IF( (VLOOKUP(B11,K:N,3,FALSE)) < C11, "X", "" ), "X") ) | K11: Militão | L11: DEF | M11: 45878 | N11: 25750396 | O11: =IF(ISBLANK(N11),"",VLOOKUP(K11,B:D,3,FALSE)) -> 0 | P11: =IF(ISBLANK(N11),"",N11-O11) -> 25750396
A12: DEF | B12: Miguel | C12: 45872 | D12: 0 | E12: =IF(B12="","",IFERROR( IF( (VLOOKUP(B12,K:N,3,FALSE)) < C12, "X", "" ), "X") ) | K12: Marc Roca | L12: MED | M12: 45879 | N12: 4918387 | O12: =IF(ISBLANK(N12),"",VLOOKUP(K12,B:D,3,FALSE)) -> 0 | P12: =IF(ISBLANK(N12),"",N12-O12) -> 4918387
A13: DEF | B13: Militão | C13: 45872 | D13: 0 | E13: =IF(B13="","",IFERROR( IF( (VLOOKUP(B13,K:N,3,FALSE)) < C13, "X", "" ), "X") ) | K13: Chimy | L13: DEL | M13: 45880 | N13: 4043910 | O13: =IF(ISBLANK(N13),"",VLOOKUP(K13,B:D,3,FALSE)) -> 0 | P13: =IF(ISBLANK(N13),"",N13-O13) -> 4043910
A14: DEL | B14: Óskarsson | C14: 45872 | D14: 0 | E14: =IF(B14="","",IFERROR( IF( (VLOOKUP(B14,K:N,3,FALSE)) < C14, "X", "" ), "X") ) | K14: Óskarsson | L14: DEL | M14: 45886 | N14: 5478829 | O14: =IF(ISBLANK(N14),"",VLOOKUP(K14,B:D,3,FALSE)) -> 0 | P14: =IF(ISBLANK(N14),"",N14-O14) -> 5478829
A15: DEF | B15: Rüdiger | C15: 45872 | D15: 0 | E15: =IF(B15="","",IFERROR( IF( (VLOOKUP(B15,K:N,3,FALSE)) < C15, "X", "" ), "X") ) | K15: Starfelt | L15: DEF | M15: 45886 | N15: 5590699 | O15: =IF(ISBLANK(N15),"",VLOOKUP(K15,B:D,3,FALSE)) -> 11010100 | P15: =IF(ISBLANK(N15),"",N15-O15) -> -5419401
A16: MED | B16: Uche | C16: 45872 | D16: 0 | E16: =IF(B16="","",IFERROR( IF( (VLOOKUP(B16,K:N,3,FALSE)) < C16, "X", "" ), "X") ) | K16: Beltrán | L16: MED | M16: 45888 | N16: 4160518 | O16: =IF(ISBLANK(N16),"",VLOOKUP(K16,B:D,3,FALSE)) -> 0 | P16: =IF(ISBLANK(N16),"",N16-O16) -> 4160518
... A28: DEF | B28: Aramburu | C28: 45886 | D28: 8100010 | E28: =IF(B28="","",IFERROR( IF( (VLOOKUP(B28,K:N,3,FALSE)) < C28, "X", "" ), "X") ) | K28: Soria | L28: POR | M28: 45903 | N28: 26425597 | O28: =IF(ISBLANK(N28),"",VLOOKUP(K28,B:D,3,FALSE)) -> 27100010 | P28: =IF(ISBLANK(N28),"",N28-O28) -> -674413
A29: POR | B29: Luiz Junior | C29: 45886 | D29: 9184563 | K29: Carvajal | L29: DEF | M29: 45908 | N29: 26884333 | O29: =IF(ISBLANK(N29),"",VLOOKUP(K29,B:D,3,FALSE)) -> 26100010 | P29: =IF(ISBLANK(N29),"",N29-O29) -> 784323
A30: MED | B30: Pedro Díaz | C30: 45888 | D30: 3201101 | K30: Pep Chavarría | L30: DEF | M30: 45909 | N30: 5150010 | O30: =IF(ISBLANK(N30),"",VLOOKUP(K30,B:D,3,FALSE)) -> 5100010 | P30: =IF(ISBLANK(N30),"",N30-O30) -> 50000
A31: DEL | B31: Raba | C31: 45889 | D31: 13741840 | K31: Herrera | L31: POR | M31: 45914 | N31: 22460839 | O31: =IF(ISBLANK(N31),"",VLOOKUP(K31,B:D,3,FALSE)) -> 22159096 | P31: =IF(ISBLANK(N31),"",N31-O31) -> 301743
A32: MED | B32: Riquelme | C32: 45889 | D32: 17158711 | K32: Riquelme | L32: MED | M32: 45915 | N32: 33788946 | O32: =IF(ISBLANK(N32),"",VLOOKUP(K32,B:D,3,FALSE)) -> 17158711 | P32: =IF(ISBLANK(N32),"",N32-O32) -> 16630235
A33: MED | B33: C. Álvarez | C33: 45890 | D33: 2611001 | K33: Valjent | L33: DEF | M33: 45915 | N33: 6095596 | O33: =IF(ISBLANK(N33),"",VLOOKUP(K33,B:D,3,FALSE)) -> 16101010 | P33: =IF(ISBLANK(N33),"",N33-O33) -> -10005414
A34: POR | B34: Soria | C34: 45890 | D34: 27100010 | K34: Pépé | L34: DEL | M34: 45917 | N34: 68214570 | O34: =IF(ISBLANK(N34),"",VLOOKUP(K34,B:D,3,FALSE)) -> 40046131 | P34: =IF(ISBLANK(N34),"",N34-O34) -> 28168439
A35: MED | B35: Brahim | C35: 45893 | D35: 17508953 | K35: Rosier | L35: DEF | M35: 45917 | N35: 22431853 | O35: =IF(ISBLANK(N35),"",VLOOKUP(K35,B:D,3,FALSE)) -> 15838779 | P35: =IF(ISBLANK(N35),"",N35-O35) -> 6593074
A36: DEF | B36: Affengruber | C36: 45912 | D36: 15365462 | K36: Cabrera | L36: DEF | M36: 45918 | N36: 15010001 | O36: =IF(ISBLANK(N36),"",VLOOKUP(K36,B:D,3,FALSE)) -> 11010001 | P36: =IF(ISBLANK(N36),"",N36-O36) -> 4000000
A37: DEF | B37: Copete | C37: 45895 | D37: 7100100 | K37: Arambarri | L37: MED | M37: 45921 | N37: 13265558 | O37: =IF(ISBLANK(N37),"",VLOOKUP(K37,B:D,3,FALSE)) -> 13100100 | P37: =IF(ISBLANK(N37),"",N37-O37) -> 165458
A38: DEF | B38: Carvajal | C38: 45896 | D38: 26100010 | K38: Alfon | L38: DEL | M38: 45922 | N38: 9411449 | O38: =IF(ISBLANK(N38),"",VLOOKUP(K38,B:D,3,FALSE)) -> 9163132 | P38: =IF(ISBLANK(N38),"",N38-O38) -> 248317
A39: DEL | B39: Ejuke | C39: 45896 | D39: 4000000 | K39: Febas | L39: MED | M39: 45922 | N39: 8210100 | O39: =IF(ISBLANK(N39),"",VLOOKUP(K39,B:D,3,FALSE)) -> 4210100 | P39: =IF(ISBLANK(N39),"",N39-O39) -> 4000000
A40: DEF | B40: Junior | C40: 45900 | D40: 12310001 | K40: Yuri | L40: DEF | M40: 45924 | N40: 14118951 | O40: =IF(ISBLANK(N40),"",VLOOKUP(K40,B:D,3,FALSE)) -> 18734306 | P40: =IF(ISBLANK(N40),"",N40-O40) -> -4615355
... A48: DEL | B48: De Frutos | C48: 45917 | D48: 27295171 | K48: Femenia | L48: DEF | M48: 45932 | N48: 6501001 | O48: =IF(ISBLANK(N48),"",VLOOKUP(K48,B:D,3,FALSE)) -> 6501001 | P48: =IF(ISBLANK(N48),"",N48-O48) -> 0
A49: DEL | B49: Ferran | C49: 45917 | D49: 60001168 | K49: Eric García | L49: DEF | M49: 45935 | N49: 45306673
A50: DEF | B50: Femenia | C50: 45917 | D50: 6501001 | K50: Araújo | L50: DEF | M50: 45935 | N50: 22297359
A51: DEF | B51: Laporte | C51: 45917 | D51: 23439691 | K51: Diakhaby | L51: DEF | M51: 45936 | N51: 8206580
A52: DEF | B52: Gayà | C52: 45918 | D52: 6609506 | K52: Muriqi | L52: DEL | M52: 45936 | N52: 26129572
A53: DEL | B53: Pépé | C53: 45900 | D53: 40046131 | K53: Luiz Junior | L53: POR | M53: 45937 | N53: 24021481
A54: DEF | B54: Eric García | C54: 45920 | D54: 26000000 | K54: Brais | L54: MED | M54: 45938 | N54: 12818323
A55: MED | B55: Morlanes | C55: 45921 | D55: 1610010 | K55: Mikautadze | L55: DEL | M55: 45944 | N55: 45100000
A56: DEL | B56: Muriqi | C56: 45921 | D56: 25610010 | K56: Morlanes | L56: MED | M56: 45944 | N56: 1610010
A57: MED | B57: Brais | C57: 45922 | D57: 21010101 | K57: Laporte | L57: DEF | M57: 45944 | N57: 35533525
A58: DEF | B58: Rosier | C58: 45900 | D58: 15838779 | K58: De Frutos | L58: DEL | M58: 45945 | N58: 42650147
A59: DEL | B59: Mikautadze | C59: 45924 | D59: 35100000 | K59: Rafa Marín | L59: DEF | M59: 45949 | N59: 41359263
A60: MED | B60: Aleñá | C60: 45925 | D60: 13434659 | K60: Rioja | L60: MED | M60: 45952 | N60: 27230877
... A78: DEF | B78: Cabrera | C78: 45948 | D78: 15010001 | K78: Gerard | L78: DEL | M78: 45973 | N78: 16610101
A79: MED | B79: Samú | C79: 45952 | D79: 7874521
A80: DEL | B80: Pere Milla | C80: 45952 | D80: 18009683
A81: MED | B81: Lozano | C81: 45953 | D81: 10014326
A82: DEF | B82: Moreno | C82: 45953 | D82: 4100010
A83: MED | B83: Javi Guerra | C83: 45954 | D83: 16333241
A84: DEL | B84: Rashford | C84: 45956 | D84: 91655316
A85: DEF | B85: Giménez | C85: 45956 | D85: 13110101
A86: MED | B86: Edu Expósito | C86: 45958 | D86: 26279253
A87: DEF | B87: Femenia | C87: 45958 | D87: 6501001
A88: DEL | B88: Gerard | C88: 45959 | D88: 16610101
A89: DEL | B89: Oyarzabal | C89: 45959 | D89: 43160079
A90: POR | B90: Pau López | C90: 45960 | D90: 14758698
... A95: PROBLEMAAAAAA | B95: PROBLEMAAAAAA | C95: 45974 | D95: 35610101

Sheet Reivaj95
A1: Indice | B1: Reivaj95
A2: Fichajes | K2: Ventas
A3: Posicion | B3: Jugador | C3: Fecha Compra | D3: Precio Compra | E3: Plantilla | K3: Posicion | L3: Jugador | M3: Fecha Venta | N3: Precio Venta | O3: Precio Compra | P3: Rentabilidad
A4: {=_xlfn._xlws.FILTER(Fichajes!C:C,Fichajes!G:G=B1)} -> MED | B4: {=_xlfn._xlws.FILTER(Fichajes!B:B,Fichajes!G:G=B1)} -> Barrenetxea | C4: {=_xlfn._xlws.FILTER(Fichajes!F:F,Fichajes!$G:$G=$B1)} -> 45872 | D4: {=_xlfn._xlws.FILTER(Fichajes!I:I,Fichajes!$G:$G=$B1)} -> 0 | E4: =IF(B4="","",IFERROR( IF( (VLOOKUP(B4,K:N,3,FALSE)) < C4, "X", "" ), "X") ) | K4: {=_xlfn._xlws.FILTER(Fichajes!B:B,Fichajes!$H:$H=B$1)} -> Endrick | L4: {=_xlfn._xlws.FILTER(Fichajes!C:C,Fichajes!$H:$H=B$1)} -> DEL | M4: {=_xlfn._xlws.FILTER(Fichajes!F:F,Fichajes!$H:$H=B$1)} -> 45873 | N4: {=_xlfn._xlws.FILTER(Fichajes!I:I,Fichajes!$H:$H=B$1)} -> 8378245 | O4: =IF(ISBLANK(N4),"",VLOOKUP(K4,B:D,3,FALSE)) -> 0 | P4: =IF(ISBLANK(N4),"",N4-O4) -> 8378245
A5: POR | B5: Batalla | C5: 45872 | D5: 0 | E5: =IF(B5="","",IFERROR( IF( (VLOOKUP(B5,K:N,3,FALSE)) < C5, "X", "" ), "X") ) | K5: Paredes | L5: DEF | M5: 45873 | N5: 11553769 | O5: =IF(ISBLANK(N5),"",VLOOKUP(K5,B:D,3,FALSE)) -> 0 | P5: =IF(ISBLANK(N5),"",N5-O5) -> 11553769
A6: MED | B6: Brahim | C6: 45872 | D6: 0 | E6: =IF(B6="","",IFERROR( IF( (VLOOKUP(B6,K:N,3,FALSE)) < C6, "X", "" ), "X") ) | K6: Barrenetxea | L6: MED | M6: 45874 | N6: 5672311 | O6: =IF(ISBLANK(N6),"",VLOOKUP(K6,B:D,3,FALSE)) -> 0 | P6: =IF(ISBLANK(N6),"",N6-O6) -> 5672311
A7: DEF | B7: Catena | C7: 45872 | D7: 0 | E7: =IF(B7="","",IFERROR( IF( (VLOOKUP(B7,K:N,3,FALSE)) < C7, "X", "" ), "X") ) | K7: Rodrygo | L7: DEL | M7: 45875 | N7: 25325866 | O7: =IF(ISBLANK(N7),"",VLOOKUP(K7,B:D,3,FALSE)) -> 0 | P7: =IF(ISBLANK(N7),"",N7-O7) -> 25325866
A8: DEF | B8: Domínguez | C8: 45872 | D8: 0 | E8: =IF(B8="","",IFERROR( IF( (VLOOKUP(B8,K:N,3,FALSE)) < C8, "X", "" ), "X") ) | K8: Brahim | L8: MED | M8: 45876 | N8: 20221672 | O8: =IF(ISBLANK(N8),"",VLOOKUP(K8,B:D,3,FALSE)) -> 0 | P8: =IF(ISBLANK(N8),"",N8-O8) -> 20221672
A9: DEL | B9: Endrick | C9: 45872 | D9: 0 | E9: =IF(B9="","",IFERROR( IF( (VLOOKUP(B9,K:N,3,FALSE)) < C9, "X", "" ), "X") ) | K9: Lenglet | L9: DEF | M9: 45877 | N9: 6883495 | O9: =IF(ISBLANK(N9),"",VLOOKUP(K9,B:D,3,FALSE)) -> 0 | P9: =IF(ISBLANK(N9),"",N9-O9) -> 6883495
A10: MED | B10: Gavi | C10: 45872 | D10: 0 | E10: =IF(B10="","",IFERROR( IF( (VLOOKUP(B10,K:N,3,FALSE)) < C10, "X", "" ), "X") ) | K10: Mojica | L10: DEF | M10: 45878 | N10: 15508519 | O10: =IF(ISBLANK(N10),"",VLOOKUP(K10,B:D,3,FALSE)) -> 0 | P10: =IF(ISBLANK(N10),"",N10-O10) -> 15508519
A11: MED | B11: Jauregizar | C11: 45872 | D11: 0 | E11: =IF(B11="","",IFERROR( IF( (VLOOKUP(B11,K:N,3,FALSE)) < C11, "X", "" ), "X") ) | K11: Gavi | L11: MED | M11: 45881 | N11: 19786242 | O11: =IF(ISBLANK(N11),"",VLOOKUP(K11,B:D,3,FALSE)) -> 0 | P11: =IF(ISBLANK(N11),"",N11-O11) -> 19786242
A12: MED | B12: Cardoso | C12: 45872 | D12: 0 | E12: =IF(B12="","",IFERROR( IF( (VLOOKUP(B12,K:N,3,FALSE)) < C12, "X", "" ), "X") ) | K12: Andrei | L12: DEF | M12: 45882 | N12: 14907854 | O12: =IF(ISBLANK(N12),"",VLOOKUP(K12,B:D,3,FALSE)) -> 14500000 | P12: =IF(ISBLANK(N12),"",N12-O12) -> 407854
A13: DEF | B13: Lenglet | C13: 45872 | D13: 0 | E13: =IF(B13="","",IFERROR( IF( (VLOOKUP(B13,K:N,3,FALSE)) < C13, "X", "" ), "X") ) | K13: Lukebakio | L13: DEL | M13: 45882 | N13: 63271385 | O13: =IF(ISBLANK(N13),"",VLOOKUP(K13,B:D,3,FALSE)) -> 60000000 | P13: =IF(ISBLANK(N13),"",N13-O13) -> 3271385
A14: DEL | B14: Mayoral | C14: 45872 | D14: 0 | E14: =IF(B14="","",IFERROR( IF( (VLOOKUP(B14,K:N,3,FALSE)) < C14, "X", "" ), "X") ) | K14: Diego Rico | L14: DEF | M14: 45884 | N14: 5281906 | O14: =IF(ISBLANK(N14),"",VLOOKUP(K14,B:D,3,FALSE)) -> 7300000 | P14: =IF(ISBLANK(N14),"",N14-O14) -> -2018094
A15: DEF | B15: Mojica | C15: 45872 | D15: 0 | E15: =IF(B15="","",IFERROR( IF( (VLOOKUP(B15,K:N,3,FALSE)) < C15, "X", "" ), "X") ) | K15: Brugui | L15: DEL | M15: 45885 | N15: 2210717 | O15: =IF(ISBLANK(N15),"",VLOOKUP(K15,B:D,3,FALSE)) -> 2113301 | P15: =IF(ISBLANK(N15),"",N15-O15) -> 97416
A16: DEF | B16: Paredes | C16: 45872 | D16: 0 | E16: =IF(B16="","",IFERROR( IF( (VLOOKUP(B16,K:N,3,FALSE)) < C16, "X", "" ), "X") ) | K16: Hassan | L16: MED | M16: 45886 | N16: 4070699 | O16: =IF(ISBLANK(N16),"",VLOOKUP(K16,B:D,3,FALSE)) -> 4005000 | P16: =IF(ISBLANK(N16),"",N16-O16) -> 65699
... A39: DEL | B39: De Frutos | C39: 45900 | D39: 18666684 | E39: =IF(B39="","",IFERROR( IF( (VLOOKUP(B39,K:N,3,FALSE)) < C39, "X", "" ), "X") ) | K39: Sibo | L39: MED | M39: 45916 | N39: 1301089 | O39: =IF(ISBLANK(N39),"",VLOOKUP(K39,B:D,3,FALSE)) -> 4000000 | P39: =IF(ISBLANK(N39),"",N39-O39) -> -2698911
A40: DEF | B40: Rafa Marín | C40: 45900 | D40: 25100001 | K40: Mouriño | L40: DEF | M40: 45893 | N40: 16430000 | O40: =IF(ISBLANK(N40),"",VLOOKUP(K40,B:D,3,FALSE)) -> 10430000 | P40: =IF(ISBLANK(N40),"",N40-O40) -> 6000000
A41: MED | B41: Puado | C41: 45901 | D41: 41053831 | K41: N. Williams | L41: DEL | M41: 45894 | N41: 102089122 | O41: =IF(ISBLANK(N41),"",VLOOKUP(K41,B:D,3,FALSE)) -> 87000000 | P41: =IF(ISBLANK(N41),"",N41-O41) -> 15089122
A42: MED | B42: Luis Milla | C42: 45902 | D42: 18956233 | K42: De la Fuente | L42: DEF | M42: 45917 | N42: 533402 | O42: =IF(ISBLANK(N42),"",VLOOKUP(K42,B:D,3,FALSE)) -> 1130330 | P42: =IF(ISBLANK(N42),"",N42-O42) -> -596928
A43: DEL | B43: Rafa Mir | C43: 45902 | D43: 11460297 | K43: Leo Román | L43: POR | M43: 45919 | N43: 6138407 | O43: =IF(ISBLANK(N43),"",VLOOKUP(K43,B:D,3,FALSE)) -> 6107069 | P43: =IF(ISBLANK(N43),"",N43-O43) -> 31338
A44: DEF | B44: Tenaglia | C44: 45902 | D44: 14284108 | K44: Pépé | L44: DEL | M44: 45900 | N44: 40046131 | O44: =IF(ISBLANK(N44),"",VLOOKUP(K44,B:D,3,FALSE)) -> 19282733 | P44: =IF(ISBLANK(N44),"",N44-O44) -> 20763398
A45: MED | B45: C. Álvarez | C45: 45904 | D45: 2611001 | K45: Rafa Mir | L45: DEL | M45: 45916 | N45: 20225343 | O45: =IF(ISBLANK(N45),"",VLOOKUP(K45,B:D,3,FALSE)) -> 11460297 | P45: =IF(ISBLANK(N45),"",N45-O45) -> 8765046
A46: DEF | B46: D. Llorente | C46: 45905 | D46: 3760715 | K46: Rosier | L46: DEF | M46: 45922 | N46: 23160593 | O46: =IF(ISBLANK(N46),"",VLOOKUP(K46,B:D,3,FALSE)) -> 8813000 | P46: =IF(ISBLANK(N46),"",N46-O46) -> 14347593
A47: DEL | B47: Bryan | C47: 45906 | D47: 17019211 | K47: D. Llorente | L47: DEF | M47: 45923 | N47: 2960237 | O47: =IF(ISBLANK(N47),"",VLOOKUP(K47,B:D,3,FALSE)) -> 3760715 | P47: =IF(ISBLANK(N47),"",N47-O47) -> -800478
A48: MED | B48: Lo Celso | C48: 45906 | D48: 75609428 | K48: Rosier | L48: DEF | M48: 45900 | N48: 15838779 | O48: =IF(ISBLANK(N48),"",VLOOKUP(K48,B:D,3,FALSE)) -> 8813000 | P48: =IF(ISBLANK(N48),"",N48-O48) -> 7025779
A49: DEL | B49: Vargas | C49: 45908 | D49: 15298469 | K49: Sow | L49: MED | M49: 45926 | N49: 2213460
A50: DEF | B50: Bartra | C50: 45909 | D50: 34151526 | K50: Bartra | L50: DEF | M50: 45927 | N50: 35852023
A51: MED | B51: Sow | C51: 45911 | D51: 2213460 | K51: Garcés | L51: DEF | M51: 45928 | N51: 5567778
A52: DEL | B52: Alemão | C52: 45913 | D52: 5000000 | K52: Asprilla | L52: DEL | M52: 45929 | N52: 3481230
A53: DEF | B53: Garcés | C53: 45915 | D53: 3431812 | K53: Tenaglia | L53: DEF | M53: 45916 | N53: 17000000
A54: MED | B54: Valera | C54: 45915 | D54: 12098300 | K54: Valera | L54: MED | M54: 45929 | N54: 12098300
A55: DEL | B55: Mbappé | C55: 45916 | D55: 154612000 | K55: Vargas | L55: DEL | M55: 45923 | N55: 30085836
A56: POR | B56: Leo Román | C56: 45917 | D56: 6107069 | K56: Arambarri | L56: MED | M56: 45931 | N56: 20000000
A57: DEF | B57: Rosier | C57: 45917 | D57: 22431853 | K57: Alemão | L57: DEL | M57: 45932 | N57: 5000000
A58: POR | B58: Ryan | C58: 45917 | D58: 5500000 | K58: Romero | L58: DEF | M58: 45933 | N58: 16000000
A59: DEL | B59: Asprilla | C59: 45918 | D59: 4680931 | K59: Dituro | L59: POR | M59: 45933 | N59: 6708375
A60: MED | B60: Olasagasti | C60: 45918 | D60: 639825 | K60: Ryan | L60: POR | M60: 45934 | N60: 10000000
... A95: DEL | B95: Guruzeta | C95: 45954 | D95: 2659046 | K95: Abde | L95: DEL | M95: 45974 | N95: 43309964
A96: DEF | B96: Mouriño | C96: 45954 | D96: 19487521
A97: DEL | B97: Virgili | C97: 45955 | D97: 5340954
A98: MED | B98: Barrios | C98: 45955 | D98: 58240000
A99: DEL | B99: Abde | C99: 45959 | D99: 32239613
A100: DEF | B100: Militão | C100: 45959 | D100: 68101190
A101: MED | B101: Luis Milla | C101: 45959 | D101: 90222396
A102: MED | B102: Güler | C102: 45960 | D102: 122854925
A103: DEL | B103: Aspas | C103: 45961 | D103: 12161036
A104: DEF | B104: Cabrera | C104: 45962 | D104: 15010001
A105: DEL | B105: Antony | C105: 45965 | D105: 105297326
A106: MED | B106: Navarro | C106: 45967 | D106: 4800000
A107: POR | B107: Herrera | C107: 45969 | D107: 28870000
... A114: DEL | B114: Iglesias | C114: 45973 | D114: 19552500

Sheet CrisGC14
A1: Indice | B1: CrisGC14
A2: Fichajes | K2: Ventas
A3: Posicion | B3: Jugador | C3: Fecha Compra | D3: Precio Compra | E3: Plantilla | K3: Posicion | L3: Jugador | M3: Fecha Venta | N3: Precio Venta | O3: Precio Compra | P3: Rentabilidad
A4: {=_xlfn._xlws.FILTER(Fichajes!C:C,Fichajes!G:G=B1)} -> MED | B4: {=_xlfn._xlws.FILTER(Fichajes!B:B,Fichajes!G:G=B1)} -> Álvaro García | C4: {=_xlfn._xlws.FILTER(Fichajes!F:F,Fichajes!$G:$G=$B1)} -> 45872 | D4: {=_xlfn._xlws.FILTER(Fichajes!I:I,Fichajes!$G:$G=$B1)} -> 0 | E4: =IF(B4="","",IFERROR( IF( (VLOOKUP(B4,K:N,3,FALSE)) < C4, "X", "" ), "X") ) | K4: {=_xlfn._xlws.FILTER(Fichajes!B:B,Fichajes!$H:$H=B$1)} -> Álvaro García | L4: {=_xlfn._xlws.FILTER(Fichajes!C:C,Fichajes!$H:$H=B$1)} -> MED | M4: {=_xlfn._xlws.FILTER(Fichajes!F:F,Fichajes!$H:$H=B$1)} -> 45875 | N4: {=_xlfn._xlws.FILTER(Fichajes!I:I,Fichajes!$H:$H=B$1)} -> 11915702 | O4: =IF(ISBLANK(N4),"",VLOOKUP(K4,B:D,3,FALSE)) -> 0 | P4: =IF(ISBLANK(N4),"",N4-O4) -> 11915702
A5: DEF | B5: Asencio | C5: 45872 | D5: 0 | E5: =IF(B5="","",IFERROR( IF( (VLOOKUP(B5,K:N,3,FALSE)) < C5, "X", "" ), "X") ) | K5: Asencio | L5: DEF | M5: 45875 | N5: 14535398 | O5: =IF(ISBLANK(N5),"",VLOOKUP(K5,B:D,3,FALSE)) -> 0 | P5: =IF(ISBLANK(N5),"",N5-O5) -> 14535398
A6: MED | B6: Becker | C6: 45872 | D6: 0 | E6: =IF(B6="","",IFERROR( IF( (VLOOKUP(B6,K:N,3,FALSE)) < C6, "X", "" ), "X") ) | K6: Becker | L6: MED | M6: 45875 | N6: 7802523 | O6: =IF(ISBLANK(N6),"",VLOOKUP(K6,B:D,3,FALSE)) -> 0 | P6: =IF(ISBLANK(N6),"",N6-O6) -> 7802523
A7: DEL | B7: Berenguer | C7: 45872 | D7: 0 | E7: =IF(B7="","",IFERROR( IF( (VLOOKUP(B7,K:N,3,FALSE)) < C7, "X", "" ), "X") ) | K7: Gallagher | L7: MED | M7: 45875 | N7: 16196589 | O7: =IF(ISBLANK(N7),"",VLOOKUP(K7,B:D,3,FALSE)) -> 0 | P7: =IF(ISBLANK(N7),"",N7-O7) -> 16196589
A8: DEF | B8: S. Cardona | C8: 45872 | D8: 0 | E8: =IF(B8="","",IFERROR( IF( (VLOOKUP(B8,K:N,3,FALSE)) < C8, "X", "" ), "X") ) | K8: Greif | L8: POR | M8: 45881 | N8: 1437484 | O8: =IF(ISBLANK(N8),"",VLOOKUP(K8,B:D,3,FALSE)) -> 1635041 | P8: =IF(ISBLANK(N8),"",N8-O8) -> -197557
A9: DEL | B9: Carlos Vicente | C9: 45872 | D9: 0 | E9: =IF(B9="","",IFERROR( IF( (VLOOKUP(B9,K:N,3,FALSE)) < C9, "X", "" ), "X") ) | K9: Fermín | L9: MED | M9: 45886 | N9: 17410012 | O9: =IF(ISBLANK(N9),"",VLOOKUP(K9,B:D,3,FALSE)) -> 0 | P9: =IF(ISBLANK(N9),"",N9-O9) -> 17410012
A10: POR | B10: Conde | C10: 45872 | D10: 0 | E10: =IF(B10="","",IFERROR( IF( (VLOOKUP(B10,K:N,3,FALSE)) < C10, "X", "" ), "X") ) -> X | K10: Sucic | L10: MED | M10: 45886 | N10: 9687480 | O10: =IF(ISBLANK(N10),"",VLOOKUP(K10,B:D,3,FALSE)) -> 0 | P10: =IF(ISBLANK(N10),"",N10-O10) -> 9687480
A11: MED | B11: Fermín | C11: 45872 | D11: 0 | E11: =IF(B11="","",IFERROR( IF( (VLOOKUP(B11,K:N,3,FALSE)) < C11, "X", "" ), "X") ) | K11: Garcés | L11: DEF | M11: 45887 | N11: 1011015 | O11: =IF(ISBLANK(N11),"",VLOOKUP(K11,B:D,3,FALSE)) -> 0 | P11: =IF(ISBLANK(N11),"",N11-O11) -> 1011015
A12: MED | B12: Gallagher | C12: 45872 | D12: 0 | E12: =IF(B12="","",IFERROR( IF( (VLOOKUP(B12,K:N,3,FALSE)) < C12, "X", "" ), "X") ) | K12: Barrenetxea | L12: MED | M12: 45893 | N12: 5678911 | O12: =IF(ISBLANK(N12),"",VLOOKUP(K12,B:D,3,FALSE)) -> 5678911 | P12: =IF(ISBLANK(N12),"",N12-O12) -> 0
A13: DEF | B13: Garcés | C13: 45872 | D13: 0 | E13: =IF(B13="","",IFERROR( IF( (VLOOKUP(B13,K:N,3,FALSE)) < C13, "X", "" ), "X") ) | K13: Gayà | L13: DEF | M13: 45893 | N13: 12638922 | O13: =IF(ISBLANK(N13),"",VLOOKUP(K13,B:D,3,FALSE)) -> 0 | P13: =IF(ISBLANK(N13),"",N13-O13) -> 12638922
A14: DEF | B14: Gayà | C14: 45872 | D14: 0 | E14: =IF(B14="","",IFERROR( IF( (VLOOKUP(B14,K:N,3,FALSE)) < C14, "X", "" ), "X") ) | K14: Romero | L14: DEL | M14: 45897 | N14: 4858486 | O14: =IF(ISBLANK(N14),"",VLOOKUP(K14,B:D,3,FALSE)) -> 0 | P14: =IF(ISBLANK(N14),"",N14-O14) -> 4858486
A15: DEL | B15: Romero | C15: 45872 | D15: 0 | E15: =IF(B15="","",IFERROR( IF( (VLOOKUP(B15,K:N,3,FALSE)) < C15, "X", "" ), "X") ) | K15: M. Alonso | L15: DEF | M15: 45897 | N15: 18644883 | O15: =IF(ISBLANK(N15),"",VLOOKUP(K15,B:D,3,FALSE)) -> 0 | P15: =IF(ISBLANK(N15),"",N15-O15) -> 18644883
A16: DEF | B16: M. Alonso | C16: 45872 | D16: 0 | E16: =IF(B16="","",IFERROR( IF( (VLOOKUP(B16,K:N,3,FALSE)) < C16, "X", "" ), "X") ) | K16: Á. Núñez | L16: DEF | M16: 45903 | N16: 6869728 | O16: =IF(ISBLANK(N16),"",VLOOKUP(K16,B:D,3,FALSE)) -> 1749728 | P16: =IF(ISBLANK(N16),"",N16-O16) -> 5120000
... A30: DEF | B30: Morey | C30: 45898 | D30: 4561231 | E30: =IF(B30="","",IFERROR( IF( (VLOOKUP(B30,K:N,3,FALSE)) < C30, "X", "" ), "X") ) -> X | K30: Mario Martín | L30: MED | M30: 45934 | N30: 2468142 | O30: =IF(ISBLANK(N30),"",VLOOKUP(K30,B:D,3,FALSE)) -> 3861510 | P30: =IF(ISBLANK(N30),"",N30-O30) -> -1393368
A31: MED | B31: Álvaro García | C31: 45907 | D31: 23000001 | K31: Darder | L31: MED | M31: 45939 | N31: 15322230 | O31: =IF(ISBLANK(N31),"",VLOOKUP(K31,B:D,3,FALSE)) -> 31560995 | P31: =IF(ISBLANK(N31),"",N31-O31) -> -16238765
A32: MED | B32: Agoume | C32: 45910 | D32: 7541427 | K32: Cucho | L32: DEL | M32: 45945 | N32: 43491641 | O32: =IF(ISBLANK(N32),"",VLOOKUP(K32,B:D,3,FALSE)) -> 20301719 | P32: =IF(ISBLANK(N32),"",N32-O32) -> 23189922
A33: DEL | B33: Diego López | C33: 45910 | D33: 27177700 | K33: Rodríguez | L33: DEF | M33: 45949 | N33: 7834207 | O33: =IF(ISBLANK(N33),"",VLOOKUP(K33,B:D,3,FALSE)) -> 10225841 | P33: =IF(ISBLANK(N33),"",N33-O33) -> -2391634
A34: DEF | B34: Foulquier | C34: 45910 | D34: 10552100 | K34: González | L34: MED | M34: 45949 | N34: 22184235 | O34: =IF(ISBLANK(N34),"",VLOOKUP(K34,B:D,3,FALSE)) -> 24447215 | P34: =IF(ISBLANK(N34),"",N34-O34) -> -2262980
A35: MED | B35: Jauregizar | C35: 45916 | D35: 18000010 | K35: Navarro | L35: MED | M35: 45953 | N35: 4800000 | O35: =IF(ISBLANK(N35),"",VLOOKUP(K35,B:D,3,FALSE)) -> 4800000 | P35: =IF(ISBLANK(N35),"",N35-O35) -> 0
A36: MED | B36: Mendoza | C36: 45916 | D36: 4172591 | K36: Agoume | L36: MED | M36: 45955 | N36: 10276217 | O36: =IF(ISBLANK(N36),"",VLOOKUP(K36,B:D,3,FALSE)) -> 7541427 | P36: =IF(ISBLANK(N36),"",N36-O36) -> 2734790
A37: DEF | B37: Mouriño | C37: 45893 | D37: 16430000 | K37: Rueda | L37: DEF | M37: 45955 | N37: 6767088 | O37: =IF(ISBLANK(N37),"",VLOOKUP(K37,B:D,3,FALSE)) -> 12000010 | P37: =IF(ISBLANK(N37),"",N37-O37) -> -5232922
A38: MED | B38: Mario Martín | C38: 45920 | D38: 3861510 | K38: Iglesias | L38: DEL | M38: 45959 | N38: 17552500 | O38: =IF(ISBLANK(N38),"",VLOOKUP(K38,B:D,3,FALSE)) -> 17552500 | P38: =IF(ISBLANK(N38),"",N38-O38) -> 0
A39: DEF | B39: Bigas | C39: 45921 | D39: 9255000 | K39: Fermín | L39: MED | M39: 45964 | N39: 55222222 | O39: =IF(ISBLANK(N39),"",VLOOKUP(K39,B:D,3,FALSE)) -> 0 | P39: =IF(ISBLANK(N39),"",N39-O39) -> 55222222
A40: DEL | B40: Cucho | C40: 45928 | D40: 20301719 | K40: Diego López | L40: DEL | M40: 45964 | N40: 10328338 | O40: =IF(ISBLANK(N40),"",VLOOKUP(K40,B:D,3,FALSE)) -> 27177700 | P40: =IF(ISBLANK(N40),"",N40-O40) -> -16849362
A41: DEF | B41: Rueda | C41: 45929 | D41: 12000010 | K41: S. Cardona | L41: DEF | M41: 45965 | N41: 26208176 | O41: =IF(ISBLANK(N41),"",VLOOKUP(K41,B:D,3,FALSE)) -> 0 | P41: =IF(ISBLANK(N41),"",N41-O41) -> 26208176
A42: MED | B42: Arambarri | C42: 45931 | D42: 20000000 | K42: Hassan | L42: MED | M42: 45965 | N42: 3596768 | O42: =IF(ISBLANK(N42),"",VLOOKUP(K42,B:D,3,FALSE)) -> 5000051 | P42: =IF(ISBLANK(N42),"",N42-O42) -> -1403283
A43: MED | B43: Dendoncker | C43: 45931 | D43: 8987987 | O43: =IF(ISBLANK(N43),"",VLOOKUP(K43,B:D,3,FALSE)) | P43: =IF(ISBLANK(N43),"",N43-O43)
A44: DEF | B44: Pétrot | C44: 45933 | D44: 547689 | O44: =IF(ISBLANK(N44),"",VLOOKUP(K44,B:D,3,FALSE)) | P44: =IF(ISBLANK(N44),"",N44-O44)
A45: DEF | B45: Costas | C45: 45933 | D45: 850978 | O45: =IF(ISBLANK(N45),"",VLOOKUP(K45,B:D,3,FALSE)) | P45: =IF(ISBLANK(N45),"",N45-O45)
A46: MED | B46: Navarro | C46: 45934 | D46: 4800000 | O46: =IF(ISBLANK(N46),"",VLOOKUP(K46,B:D,3,FALSE)) | P46: =IF(ISBLANK(N46),"",N46-O46)
A47: DEL | B47: Iglesias | C47: 45935 | D47: 17552500 | O47: =IF(ISBLANK(N47),"",VLOOKUP(K47,B:D,3,FALSE)) | P47: =IF(ISBLANK(N47),"",N47-O47)
A48: MED | B48: Agoume | C48: 45935 | D48: 12000158 | O48: =IF(ISBLANK(N48),"",VLOOKUP(K48,B:D,3,FALSE)) | P48: =IF(ISBLANK(N48),"",N48-O48)
A49: DEF | B49: Rodríguez | C49: 45936 | D49: 10225841
A50: MED | B50: Fermín | C50: 45937 | D50: 22222222
A51: DEF | B51: Lejeune | C51: 45947 | D51: 22222100
A52: MED | B52: González | C52: 45947 | D52: 24447215
A53: DEF | B53: Aramburu | C53: 45949 | D53: 2591087
A54: DEF | B54: Diego Rico | C54: 45949 | D54: 5837819
A55: MED | B55: Álvaro García | C55: 45956 | D55: 38055522
A56: DEL | B56: Toni Martinez | C56: 45957 | D56: 3445353
A57: MED | B57: Hassan | C57: 45957 | D57: 5000051
A58: DEF | B58: Mojica | C58: 45961 | D58: 8800005
A59: MED | B59: Koke | C59: 45964 | D59: 13000000
A60: DEL | B60: Cucho | C60: 45964 | D60: 49503076
... A63: MED | B63: Brais | C63: 45974 | D63: 19286482
